Workbook
Name _Toc131088033: 'IM Format'!$E$37
Name CHK_TOL: NTBA!$F$306
Name Cr: NTBA!$F$302
Name Days_month: NTBA!$F$305
Name Days_Year: 365
Name Jan_18: OFFSET([40]Formula!$C$3,,,COUNTIF([40]Formula!$B$2:$B$100,”<>”))
Name Jan_18: OFFSET([40]Formula!$C$3,,,COUNTIF([40]Formula!$B$2:$B$100,”<>”))
Name Jan_18: OFFSET([40]Formula!$C$3,,,COUNTIF([40]Formula!$B$2:$B$100,”<>”))
Name Jan_18: OFFSET([40]Formula!$C$3,,,COUNTIF([40]Formula!$B$2:$B$100,”<>”))
Name Jan_18: OFFSET([40]Formula!$C$3,,,COUNTIF([40]Formula!$B$2:$B$100,”<>”))
Name months: NTBA!$F$303
Name SCENARIOS: Capex!$F$4:$J$4
Name SCENARIOS: NTBA!$J$4:$P$4

Sheet Cells Report (2)
A1: ="Cells usage report for Model: " & $G$3 & " Sheet: " & $E$3 & " Range: " & $J$3 -> Cells usage report for Model: Sheet: Range:
D3: Sheet: | F3: Model: | I3: Range:
D5: Sheet | E5: Reference | F5: Link - model | G5: Description | H5: Comment | I5: Impact | J5: Status
B7: =IF(C7 = "", "", COUNTA(C$1:C7) & ".") -> 1. | C7: CELLS EXPORTED - cells which are exported to other sheets in the model
D9: Sheet | E9: Reference | F9: Link - model | G9: Description | H9: Comment | I9: Impact | J9: Status
J10: Pending
B14: =IF(C14 = "", "", COUNTA(C$1:C14) & ".") -> 2. | C14: CELLS USED LOCALLY - cells which are used in other calculations in the current sheet
D16: Sheet | E16: Reference | F16: Link - model | G16: Description | H16: Comment | I16: Impact | J16: Status
J17: Pending
B21: =IF(C21 = "", "", COUNTA(C$1:C21) & ".") -> 3. | C21: CELLS EXPORTED & USED LOCALLY - cells which are used in other calculations in the current sheet and also exported to other sheets
D23: Sheet | E23: Reference | F23: Link - model | G23: Description | H23: Comment | I23: Impact | J23: Status
J24: Pending
B28: =IF(C28 = "", "", COUNTA(C$1:C28) & ".") -> 4. | C28: CELLS UNUSED - cells which are not used in any calculation in the model
D30: Sheet | E30: Reference | F30: Link - model | G30: Description | H30: Comment | I30: Impact | J30: Status
J31: Pending
A35: END

Sheet Cells Report (3)
A1: ="Cells usage report for Model: " & $G$3 & " Sheet: " & $E$3 & " Range: " & $J$3 -> Cells usage report for Model: Sheet: Range:
D3: Sheet: | F3: Model: | I3: Range:
D5: Sheet | E5: Reference | F5: Link - model | G5: Description | H5: Comment | I5: Impact | J5: Status
B7: =IF(C7 = "", "", COUNTA(C$1:C7) & ".") -> 1. | C7: CELLS EXPORTED - cells which are exported to other sheets in the model
D9: Sheet | E9: Reference | F9: Link - model | G9: Description | H9: Comment | I9: Impact | J9: Status
J10: Pending
B14: =IF(C14 = "", "", COUNTA(C$1:C14) & ".") -> 2. | C14: CELLS USED LOCALLY - cells which are used in other calculations in the current sheet
D16: Sheet | E16: Reference | F16: Link - model | G16: Description | H16: Comment | I16: Impact | J16: Status
J17: Pending
B21: =IF(C21 = "", "", COUNTA(C$1:C21) & ".") -> 3. | C21: CELLS EXPORTED & USED LOCALLY - cells which are used in other calculations in the current sheet and also exported to other sheets
D23: Sheet | E23: Reference | F23: Link - model | G23: Description | H23: Comment | I23: Impact | J23: Status
J24: Pending
B28: =IF(C28 = "", "", COUNTA(C$1:C28) & ".") -> 4. | C28: CELLS UNUSED - cells which are not used in any calculation in the model
D30: Sheet | E30: Reference | F30: Link - model | G30: Description | H30: Comment | I30: Impact | J30: Status
J31: Pending
A35: END

Sheet Cells Report (4)
A1: ="Cells usage report for Model: " & $G$3 & " Sheet: " & $E$3 & " Range: " & $J$3 -> Cells usage report for Model: Sheet: Range:
D3: Sheet: | F3: Model: | I3: Range:
D5: Sheet | E5: Reference | F5: Link - model | G5: Description | H5: Comment | I5: Impact | J5: Status
B7: =IF(C7 = "", "", COUNTA(C$1:C7) & ".") -> 1. | C7: CELLS EXPORTED - cells which are exported to other sheets in the model
D9: Sheet | E9: Reference | F9: Link - model | G9: Description | H9: Comment | I9: Impact | J9: Status
J10: Pending
B14: =IF(C14 = "", "", COUNTA(C$1:C14) & ".") -> 2. | C14: CELLS USED LOCALLY - cells which are used in other calculations in the current sheet
D16: Sheet | E16: Reference | F16: Link - model | G16: Description | H16: Comment | I16: Impact | J16: Status
J17: Pending
B21: =IF(C21 = "", "", COUNTA(C$1:C21) & ".") -> 3. | C21: CELLS EXPORTED & USED LOCALLY - cells which are used in other calculations in the current sheet and also exported to other sheets
D23: Sheet | E23: Reference | F23: Link - model | G23: Description | H23: Comment | I23: Impact | J23: Status
J24: Pending
B28: =IF(C28 = "", "", COUNTA(C$1:C28) & ".") -> 4. | C28: CELLS UNUSED - cells which are not used in any calculation in the model
D30: Sheet | E30: Reference | F30: Link - model | G30: Description | H30: Comment | I30: Impact | J30: Status
J31: Pending
A35: END

Sheet Cover
B2: Madhyanchal One Infrastructure Private Limited
B4: Financial Model
B6: August 2024

Sheet Model Disclaimer
B2: Financial Model Disclaimer
B3: The financial model prepared for Madhyanchal One Infrastructure Private Limited identified in the relevant Letter of Intent has been provided to the Client and/or third party recipients (“Third Parties”) (collectively, the Recipients”) on the express understanding that: • The Model contains information and other materials that are strictly private and confidential. The Recipients agree not to disclose the Model and/or the information and other materials contained therein to any person or entity except with the prior express written consent of PwC and the Client or as may be required by law. • The Recipients acknowledge that all project assumptions, data, revenue forecasts and results contained in the Model, whether express or implied, are provided in good faith and are based on information provided to PwC by the Client and/or on the Client’s behalf. Accordingly, PwC assumes no responsibility and makes no representations with respect to the accuracy or completeness of any information provided by the Client and/or on its behalf. • The Model was prepared by PwC for the Client solely for the particular purposes of the engagement set out in the relevant Letter of Intent (“the Purpose”). PwC, its partners, directors and employees did not, in preparing the Model, intend and do not intend that any person other than the Client should rely on the Model or its preparation. Any use Third Parties or their employees may make of the Model shall be entirely at their own risk. • The Recipients agree to use the Model only for the Purpose and the Model must not be regarded as suitable for any other purpose whatsoever. • The Model must be considered in its entirety. • By retaining and using the Model, the Recipients represent to PwC that they are capable of making their own independent assessment as to the validity of the assumptions, data and results contained in the Model and the economic, financial, regulatory, legal, taxation and accounting implications of those assumptions. • The Client accepts and undertakes the risk in relation to the supply of the Model (or any part thereof) to Third Parties and undertakes not to hold PwC responsible if (i) such receipt and/or review by Third Parties results in any action at any time against the Client and/or (ii) Third Parties misuse any confidential information obtained from receipt and/or review of the Model or by way of explanation (whether given orally or in writing) from PwC. • Save to the extent that PwC has responsibility to the Client in terms of the Engagement Letter, the Recipients acknowledge and agree that PwC does not assume any liability or responsibility to the Recipients (or any of them) or to any other person for any loss, damage, cost and/or expense of any kind whatsoever arising as a result of the Recipients’ use or misuse of the Model or for any opinion, advice, recommendations, representation or information, express or implied, contained therein, notwithstanding any negligence, default or lack of care by PwC or that such loss, damage, cost and/or expense was foreseeable. • Third Parties hereby indemnify and hold PwC, its members, partners, directors, employees, related entities and agents harmless against all actions, proceedings and claims brought or threatened against PwC, its members, partners, directors, employees, related entities and agents by any person and all loss, damage, cost and/or expense (including legal expenses) relating thereto, in any way arising out of or in connection with Third Parties’ receipt and/or use of the Model or information derived from the Model as a consequence of the provision of the Model. • No independent audit of the Model has been undertaken by an independent third party. It is anticipated that the Model will be enhanced over time. • All copyright and other proprietary rights and rights of ownership in the Model shall at all times vest in and remain the property of PwC or its licensors (as appropriate).

Sheet Model_Flow 
A1: =MID(CELL("filename",A1),FIND("]",CELL("filename",A1))+1,255) -> Model_Flow
M2: Note: To navigate, press Control [
B3: KEY
C5: Sheets
E6: Input sheet
E7: Calculation sheet
E8: Output sheet
E9: Model related documentation sheet
E10: Model checks and macro sheets
C12: Cells
E13: Input cell
B16: WORK SHEET LINKAGE
E21: NTBA | I21: Time_M | M21: Financials
E22: TBA | I22: Time_A | M22: Ind AS Financials
E23: Capex | I23: Rollout | M23: Ratios
I24: Monthly Financials
I25: GST
I26: Dep & Tax
I27: Termination Value
I28: Ind AS Monthly
I29: Check
A38: ABBREVIATIONS
E39: POS | G39: Positive
E40: NTBA | G40: Non Time Based Assumptions
E41: TBA | G41: Time Based Assumptions

Sheet Index 
A1: =MID(CELL("filename",A1),FIND("]",CELL("filename",A1))+1,255) -> Index
B4: Sheet name | F4: Links | G4: Notes
B6: Output sheets
E7: Financials | F7: Financials | G7: Financials based on Indian GAAP
E8: Ind AS Financials | F8: ='Ind AS Financials'!A$1 -> Ind AS Financials | G8: Financials based on Ind As
E9: Ratios | F9: =Ratios!A$1 -> Ratios | G9: Calulation of ratios and further analysis
B11: Input sheets
E12: NTBA | F12: =NTBA!A$1 -> NTBA | G12: Non time based inputs
E13: TBA | F13: =TBA!A$1 -> TBA | G13: Time based inputs
E14: Capex | F14: =Capex!A1 -> Capex | G14: Capex Inputs
B16: Calculation sheets
E17: Time_M | F17: =Time_M!A$1 -> Time_M | G17: Calculations related to different periods used in model, flags and factors on a monthly basis
E18: Time_A | F18: =Time_A!A$1 -> Time_A | G18: Calculations related to different periods used in model, flags and factors on an annual basis
E19: GST | F19: =GST!A$1 -> GST | G19: Calculations related to GST
E20: Rollout | F20: =Rollout!A$1 -> Rollout | G20: Calculations related to Installed meters, funding , capex phasing etc.
E21: Monthly Financials | F21: ='Monthly Financials'!A$1 -> Monthly Financials | G21: Calculations related to revenue and cost.
E22: Dep & Tax | F22: ='Dep&Tax'!A$1 -> Dep&Tax | G22: Calculation related to depreciation
E23: Termination Value | F23: ='Termination Value'!A$1 -> Termination Value | G23: Calculation related to termination value
E24: Ind AS Monthly | F24: ='Ind AS Monthly'!A$1 -> Ind AS Monthly | G24: Calculation related to Leases
B26: Others
E27: Check | F27: =Check!A$1 -> Check | G27: Check sheet for various model related checks

Sheet Sensitivity
A1: =MID(CELL("filename",A1),FIND("]",CELL("filename",A1))+1,255) -> Sensitivity
C3: Scenario | D3: IRR (%) | E3: DSCR (min) | F3: DSCR (Avg) | H3: Scenario | I3: Details | J3: Quantum
C4: 1 | D4: =Ratios!F72 -> 0.12614221 | E4: =Ratios!F35 -> 1.1507718 | F4: =Ratios!F34 -> 1.2018678 | H4: 1 | I4: Base Case
H5: 2 | I5: Increase in Interest Rate by __ | J5: 0.005
H6: 3 | I6: Decrease in revenue from Operation by __ | J6: 0.1
H7: 4 | I7: Increase in Project Cost by __ | J7: 0.1
H8: 5 | I8: Increase in interest rate by __ & decrease in revenue by __ | J8: 0.50% and 10%

Sheet NTBA
A1: =RIGHT(CELL("FILENAME", $A$1), LEN(CELL("FILENAME", $A$1)) - SEARCH("]", CELL("FILENAME", $A$1))) -> NTBA | J1: [don't del col] | P1: [don't del col]
E2: =Check!F$3 -> Model Check | F2: =Check!G$3 -> 0 | G2: =Check!H$3 -> check
E4: Scenario selection | F4: =Sensitivity!C4 -> 1 | K4: 1 | L4: 2 | M4: 3 | N4: 4 | O4: 5
E5: Scenario Description | F5: {=INDEX($K5:$O5, , MATCH($F4, $K$4:$O$4,))} -> Scenario 1 | K5: Scenario 1 | L5: Scenario 2 | M5: Scenario 3 | N5: Scenario 4 | O5: Scenario 5
E7: Particulars | F7: Constant | G7: Unit | H7: Source | J7: [Range start] | P7: [Range end] | R7: Remarks
A9: TIMELINE
B11: Timeline setup
E12: 1st model column start date | F12: =INDEX($K12:$O12, MATCH($F$4, $K$4:$O$4, 0)) -> 45323 | G12: date | K12: 45323 | L12: 45323 | M12: 45323 | N12: 45323 | O12: 45323
E13: 1st model column financial year | F13: =INDEX($K13:$O13, MATCH($F$4, $K$4:$O$4, 0)) -> 2024 | G13: year | K13: =IF(MONTH(K12) <4, YEAR(K12), YEAR(K12) + 1) -> 2024 | L13: =IF(MONTH(L12) <4, YEAR(L12), YEAR(L12) + 1) -> 2024 | M13: =IF(MONTH(M12) <4, YEAR(M12), YEAR(M12) + 1) -> 2024 | N13: =IF(MONTH(N12) <4, YEAR(N12), YEAR(N12) + 1) -> 2024 | O13: =IF(MONTH(O12) <4, YEAR(O12), YEAR(O12) + 1) -> 2024
B15: Construction timeline
E16: Timeline for commencement of meter installation | F16: =INDEX($K16:$O16, MATCH($F$4, $K$4:$O$4, 0)) -> 5 | G16: months | K16: 5 | L16: 5 | M16: 5 | N16: 5 | O16: 5
E17: Construction start date | F17: =INDEX($K17:$O17, MATCH($F$4, $K$4:$O$4, 0)) -> 45474 | G17: date | K17: =EDATE( K12, K16) -> 45474 | L17: =EDATE( L12, L16) -> 45474 | M17: =EDATE( M12, M16) -> 45474 | N17: =EDATE( N12, N16) -> 45474 | O17: =EDATE( O12, O16) -> 45474
E18: Construction tenure | F18: =INDEX($K18:$O18, MATCH($F$4, $K$4:$O$4, 0)) -> 22 | G18: months | K18: =27-K16 -> 22 | L18: =27-L16 -> 22 | M18: =27-M16 -> 22 | N18: =27-N16 -> 22 | O18: =27-O16 -> 22
E19: Construction end date | F19: =INDEX($K19:$O19, MATCH($F$4, $K$4:$O$4, 0)) -> 46173 | G19: date | K19: =EOMONTH( K17, K18) -> 46173 | L19: =EOMONTH( L17, L18) -> 46173 | M19: =EOMONTH( M17, M18) -> 46173 | N19: =EOMONTH( N17, N18) -> 46173 | O19: =EOMONTH( O17, O18) -> 46173
E20: Construction start date FY | F20: =INDEX($K20:$O20, MATCH($F$4, $K$4:$O$4, 0)) -> 45747 | G20: date | K20: =DATE( IF( MONTH( K17 ) <= 3,YEAR( K17 ), YEAR( K17 ) + 1), 3, 31 ) -> 45747 | L20: =DATE( IF( MONTH( L17 ) <= 3,YEAR( L17 ), YEAR( L17 ) + 1), 3, 31 ) -> 45747 | M20: =DATE( IF( MONTH( M17 ) <= 3,YEAR( M17 ), YEAR( M17 ) + 1), 3, 31 ) -> 45747 | N20: =DATE( IF( MONTH( N17 ) <= 3,YEAR( N17 ), YEAR( N17 ) + 1), 3, 31 ) -> 45747 | O20: =DATE( IF( MONTH( O17 ) <= 3,YEAR( O17 ), YEAR( O17 ) + 1), 3, 31 ) -> 45747
B22: Operation timeline
E23: Operation start date | F23: =INDEX($K23:$O23, MATCH($F$4, $K$4:$O$4, 0)) -> 46174 | G23: date | K23: =K19+1 -> 46174 | L23: =L19+1 -> 46174 | M23: =M19+1 -> 46174 | N23: =N19+1 -> 46174 | O23: =O19+1 -> 46174
E24: Operation tenure | F24: =INDEX($K24:$O24, MATCH($F$4, $K$4:$O$4, 0)) -> 85 | G24: months | K24: =ROUND( ( K25 - K23 ) / Days_month-1, ) -> 85 | L24: =ROUND( ( L25 - L23 ) / Days_month-1, ) -> 85 | M24: =ROUND( ( M25 - M23 ) / Days_month-1, ) -> 85 | N24: =ROUND( ( N25 - N23 ) / Days_month-1, ) -> 85 | O24: =ROUND( ( O25 - O23 ) / Days_month-1, ) -> 85
E25: Operation end date | F25: =INDEX($K25:$O25, MATCH($F$4, $K$4:$O$4, 0)) -> 48760 | G25: date | K25: =Rollout!$F$46 -> 48760 | L25: =Rollout!$F$46 -> 48760 | M25: =Rollout!$F$46 -> 48760 | N25: =Rollout!$F$46 -> 48760 | O25: =Rollout!$F$46 -> 48760
E26: Operation end date FY | F26: =INDEX($K26:$O26, MATCH($F$4, $K$4:$O$4, 0)) -> 49034 | G26: date | K26: =DATE( IF(MONTH( K25 ) <=3, YEAR( K25 ), YEAR( K25) + 1), 3, 31 ) -> 49034 | L26: =DATE( IF(MONTH( L25 ) <=3, YEAR( L25 ), YEAR( L25) + 1), 3, 31 ) -> 49034 | M26: =DATE( IF(MONTH( M25 ) <=3, YEAR( M25 ), YEAR( M25) + 1), 3, 31 ) -> 49034 | N26: =DATE( IF(MONTH( N25 ) <=3, YEAR( N25 ), YEAR( N25) + 1), 3, 31 ) -> 49034 | O26: =DATE( IF(MONTH( O25 ) <=3, YEAR( O25 ), YEAR( O25) + 1), 3, 31 ) -> 49034
E27: Total Implementation Period | F27: =INDEX($K27:$O27, MATCH($F$4, $K$4:$O$4, 0)) -> 112 | G27: Months | K27: =K24 + K18+K16 -> 112 | L27: =L24 + L18+L16 -> 112 | M27: =M24 + M18+M16 -> 112 | N27: =N24 + N18+N16 -> 112 | O27: =O24 + O18+O16 -> 112
A31: REVENUE
B33: Smart Meter
E34: No of Meter Months for SBD | F34: =INDEX($K34:$O34, MATCH($F$4, $K$4:$O$4, 0)) -> 93 | G34: Nos. | K34: 93 | L34: 93 | M34: 93 | N34: 93 | O34: 93
E35: Total number of meter months for billing for SBD | F35: =INDEX($K35:$O35, MATCH($F$4, $K$4:$O$4, 0)) -> 257411724 | G35: Nos. | K35: =NTBA!K85 * NTBA!K34 -> 257411724 | L35: =NTBA!L85 * NTBA!L34 -> 257411724 | M35: =NTBA!M85 * NTBA!M34 -> 257411724 | N35: =NTBA!N85 * NTBA!N34 -> 257411724 | O35: =NTBA!O85 * NTBA!O34 -> 257411724
E36: Upfront Payment on Smart Meter - Consumer Meters | F36: =INDEX($K36:$O36, MATCH($F$4, $K$4:$O$4, 0)) -> 762.71186 | G36: INR / meter | K36: =900/1.18 -> 762.71186 | L36: =900/1.18 -> 762.71186 | M36: =900/1.18 -> 762.71186 | N36: =900/1.18 -> 762.71186 | O36: =900/1.18 -> 762.71186
E37: Upfront Payment on Smart Meter - DT Meters | F37: =INDEX($K37:$O37, MATCH($F$4, $K$4:$O$4, 0)) -> 2923.7288 | G37: INR / meter | K37: =3450/1.18 -> 2923.7288 | L37: =3450/1.18 -> 2923.7288 | M37: =3450/1.18 -> 2923.7288 | N37: =3450/1.18 -> 2923.7288 | O37: =3450/1.18 -> 2923.7288
E38: Upfront Payment on Smart Meter - Feeder Meters | F38: =INDEX($K38:$O38, MATCH($F$4, $K$4:$O$4, 0)) -> 5338.9831 | G38: INR / meter | K38: =6300/1.18 -> 5338.9831 | L38: =6300/1.18 -> 5338.9831 | M38: =6300/1.18 -> 5338.9831 | N38: =6300/1.18 -> 5338.9831 | O38: =6300/1.18 -> 5338.9831
E39: Qouted - Avg. Service Charge (PMPM) | F39: =INDEX($K39:$O39, MATCH($F$4, $K$4:$O$4, 0)) -> 79.560181 | G39: INR / meter / month | K39: 79.560181 | L39: 79.560181 | M39: =79.560181*(1-Sensitivity!$J$6) -> 71.604163 | N39: 79.560181 | O39: =79.560181*(1-Sensitivity!$J$6) -> 71.604163
E40: GST on AMISP Service Charge (In %) | F40: =INDEX($K40:$O40, MATCH($F$4, $K$4:$O$4, 0)) -> 0.18 | G40: % | K40: 0.18 | L40: 0.18 | M40: 0.18 | N40: 0.18 | O40: 0.18
B42: Revenue Schedule (Post-Installation)
E43: First Payment | F43: =INDEX($K43:$O43, MATCH($F$4, $K$4:$O$4, 0)) -> 1 | G43: % | K43: 1 | L43: 1 | M43: 1 | N43: 1 | O43: 1
E44: Second Payment | F44: =INDEX($K44:$O44, MATCH($F$4, $K$4:$O$4, 0)) -> 0 | G44: % | K44: 0 | L44: 0 | M44: 0 | N44: 0 | O44: 0
E45: Final Payment | F45: =INDEX($K45:$O45, MATCH($F$4, $K$4:$O$4, 0)) -> 0 | G45: % | K45: 0 | L45: 0 | M45: 0 | N45: 0 | O45: 0
E46: Total | F46: =INDEX($K46:$O46, MATCH($F$4, $K$4:$O$4, 0)) -> 1 | G46: % | K46: =SUM(K43:K45) -> 1 | L46: =SUM(L43:L45) -> 1 | M46: =SUM(M43:M45) -> 1 | N46: =SUM(N43:N45) -> 1 | O46: =SUM(O43:O45) -> 1
E48: First Payment | F48: =INDEX($K48:$O48, MATCH($F$4, $K$4:$O$4, 0)) -> 0 | G48: months | K48: 0 | L48: 0 | M48: 0 | N48: 0 | O48: 0
E49: Second Payment | F49: =INDEX($K49:$O49, MATCH($F$4, $K$4:$O$4, 0)) -> 0 | G49: months | K49: 0 | L49: 0 | M49: 0 | N49: 0 | O49: 0
E50: Final Payment | F50: =INDEX($K50:$O50, MATCH($F$4, $K$4:$O$4, 0)) -> 0 | G50: months | K50: 0 | L50: 0 | M50: 0 | N50: 0 | O50: 0
E52: Upfront Payment (post COD) | F52: =INDEX($K52:$O52, MATCH($F$4, $K$4:$O$4, 0)) -> 3 | G52: months | K52: 3 | L52: 3 | M52: 3 | N52: 3 | O52: 3 | R52: Note: Maximum delay in payment assumed as 3 months
E54: First Payment Milestone (% of meters installed) | F54: =INDEX($K54:$O54, MATCH($F$4, $K$4:$O$4, 0)) -> 0.01 | G54: % | K54: 0.01 | L54: 0.01 | M54: 0.01 | N54: 0.01 | O54: 0.01
E55: Min no. of meters for first billing | F55: =INDEX($K55:$O55, MATCH($F$4, $K$4:$O$4, 0)) -> 27678.68 | G55: Nos. | K55: =K54*NTBA!K85 -> 27678.68 | L55: =L54*NTBA!L85 -> 27678.68 | M55: =M54*NTBA!M85 -> 27678.68 | N55: =N54*NTBA!N85 -> 27678.68 | O55: =O54*NTBA!O85 -> 27678.68
B57: Payment from DISCOM
E58: A. Cable Charges
E59: First Payment Milestone of Cable Charges - Payable on COD | F59: =INDEX($K59:$O59, MATCH($F$4, $K$4:$O$4, 0)) -> 1 | G59: % | K59: 1 | L59: 1 | M59: 1 | N59: 1 | O59: 1
E61: B. Cable Invoicing
E62: Monthly select "0" and Quarterly select "1" | F62: =INDEX($K62:$O62, MATCH($F$4, $K$4:$O$4, 0)) -> 1 | G62: 0 = monthly, 1 = quarterly | K62: 1 | L62: 1 | M62: 1 | N62: 1 | O62: 1
E63: INR / Meter | F63: =INDEX($K63:$O63, MATCH($F$4, $K$4:$O$4, 0)) -> 708.62846 | G63: Average Price, excl GST | K63: 708.62846 | L63: 708.62846 | M63: 708.62846 | N63: 708.62846 | O63: 708.62846
B65: Daily Meter Installation
E67: All meters | F67: =INDEX($K67:$O67, MATCH($F$4, $K$4:$O$4, 0)) -> 4193.7394 | G67: Nos | K67: =$F$74 / K$18 / Days_month -> 4193.7394 | L67: =$F$74 / L18 / Days_month -> 4193.7394 | M67: =$F$74 / M18 / Days_month -> 4193.7394 | N67: =$F$74 / N18 / Days_month -> 4193.7394 | O67: =$F$74 / O18 / Days_month -> 4193.7394
C69: Meter Types
D70: GPRS & RF
E71: For Consumer Meters | F71: =INDEX($K71:$O71, MATCH($F$4, $K$4:$O$4, 0)) -> 2620466 | G71: Nos | K71: =TBA!$H11 -> 2620466 | L71: =TBA!$H11 -> 2620466 | M71: =TBA!$H11 -> 2620466 | N71: =TBA!$H11 -> 2620466 | O71: =TBA!$H11 -> 2620466
E72: For DT Meters | F72: =INDEX($K72:$O72, MATCH($F$4, $K$4:$O$4, 0)) -> 146932 | G72: Nos | K72: =TBA!$H12 -> 146932 | L72: =TBA!$H12 -> 146932 | M72: =TBA!$H12 -> 146932 | N72: =TBA!$H12 -> 146932 | O72: =TBA!$H12 -> 146932
E73: For Feeder Meters | F73: =INDEX($K73:$O73, MATCH($F$4, $K$4:$O$4, 0)) -> 470 | G73: Nos | K73: =TBA!$H13 -> 470 | L73: =TBA!$H13 -> 470 | M73: =TBA!$H13 -> 470 | N73: =TBA!$H13 -> 470 | O73: =TBA!$H13 -> 470
E74: Total no of meters - GPRS | F74: =INDEX($K74:$O74, MATCH($F$4, $K$4:$O$4, 0)) -> 2767868 | G74: Nos | K74: =SUM(K71:K73) -> 2767868 | L74: =SUM(L71:L73) -> 2767868 | M74: =SUM(M71:M73) -> 2767868 | N74: =SUM(N71:N73) -> 2767868 | O74: =SUM(O71:O73) -> 2767868
D76: RF
E77: For Consumer Meters | F77: =INDEX($K77:$O77, MATCH($F$4, $K$4:$O$4, 0)) -> 0 | G77: Nos | K77: =TBA!$H$16 -> 0 | L77: =TBA!$H$16 -> 0 | M77: =TBA!$H$16 -> 0 | N77: =TBA!$H$16 -> 0 | O77: =TBA!$H$16 -> 0
E78: For DT Meters | F78: =INDEX($K78:$O78, MATCH($F$4, $K$4:$O$4, 0)) -> 0 | G78: Nos | K78: =TBA!$H$17 -> 0 | L78: =TBA!$H$17 -> 0 | M78: =TBA!$H$17 -> 0 | N78: =TBA!$H$17 -> 0 | O78: =TBA!$H$17 -> 0
E79: For Feeder Meters | F79: =INDEX($K79:$O79, MATCH($F$4, $K$4:$O$4, 0)) -> 0 | G79: Nos | K79: =TBA!$H$18 -> 0 | L79: =TBA!$H$18 -> 0 | M79: =TBA!$H$18 -> 0 | N79: =TBA!$H$18 -> 0 | O79: =TBA!$H$18 -> 0
E80: Total no of meters - RF | F80: =INDEX($K80:$O80, MATCH($F$4, $K$4:$O$4, 0)) -> 0 | G80: Nos | K80: =SUM(K77:K79) -> 0 | L80: =SUM(L77:L79) -> 0 | M80: =SUM(M77:M79) -> 0 | N80: =SUM(N77:N79) -> 0 | O80: =SUM(O77:O79) -> 0
E82: For Consumer Meters | F82: =INDEX($K82:$O82, MATCH($F$4, $K$4:$O$4, 0)) -> 2620466 | G82: Nos | K82: =K71 + K77 -> 2620466 | L82: =L71 + L77 -> 2620466 | M82: =M71 + M77 -> 2620466 | N82: =N71 + N77 -> 2620466 | O82: =O71 + O77 -> 2620466
E83: For DT Meters | F83: =INDEX($K83:$O83, MATCH($F$4, $K$4:$O$4, 0)) -> 146932 | G83: Nos | K83: =K72 + K78 -> 146932 | L83: =L72 + L78 -> 146932 | M83: =M72 + M78 -> 146932 | N83: =N72 + N78 -> 146932 | O83: =O72 + O78 -> 146932
E84: For Feeder Meters | F84: =INDEX($K84:$O84, MATCH($F$4, $K$4:$O$4, 0)) -> 470 | G84: Nos | K84: =K73 + K79 -> 470 | L84: =L73 + L79 -> 470 | M84: =M73 + M79 -> 470 | N84: =N73 + N79 -> 470 | O84: =O73 + O79 -> 470
E85: Total no of meters | F85: =INDEX($K85:$O85, MATCH($F$4, $K$4:$O$4, 0)) -> 2767868 | G85: Nos | K85: =SUM(K82:K84) -> 2767868 | L85: =SUM(L82:L84) -> 2767868 | M85: =SUM(M82:M84) -> 2767868 | N85: =SUM(N82:N84) -> 2767868 | O85: =SUM(O82:O84) -> 2767868
E87: For Consumer Meters | F87: =INDEX($K87:$O87, MATCH($F$4, $K$4:$O$4, 0)) -> 3970.403 | G87: Nos | K87: =NTBA!K82 /NTBA!K18 / Days_month -> 3970.403 | L87: =NTBA!L82 /NTBA!L18 / Days_month -> 3970.403 | M87: =NTBA!M82 /NTBA!M18 / Days_month -> 3970.403 | N87: =NTBA!N82 /NTBA!N18 / Days_month -> 3970.403 | O87: =NTBA!O82 /NTBA!O18 / Days_month -> 3970.403
E88: For DT Meters | F88: =INDEX($K88:$O88, MATCH($F$4, $K$4:$O$4, 0)) -> 222.62424 | G88: Nos | K88: =NTBA!K83 /NTBA!K18 / Days_month -> 222.62424 | L88: =NTBA!L83 /NTBA!L18 / Days_month -> 222.62424 | M88: =NTBA!M83 /NTBA!M18 / Days_month -> 222.62424 | N88: =NTBA!N83 /NTBA!N18 / Days_month -> 222.62424 | O88: =NTBA!O83 /NTBA!O18 / Days_month -> 222.62424
E89: For Feeder Meters | F89: =INDEX($K89:$O89, MATCH($F$4, $K$4:$O$4, 0)) -> 0.71212121 | G89: Nos | K89: =NTBA!K84 /NTBA!K18 / Days_month -> 0.71212121 | L89: =NTBA!L84 /NTBA!L18 / Days_month -> 0.71212121 | M89: =NTBA!M84 /NTBA!M18 / Days_month -> 0.71212121 | N89: =NTBA!N84 /NTBA!N18 / Days_month -> 0.71212121 | O89: =NTBA!O84 /NTBA!O18 / Days_month -> 0.71212121
A92: OPEX
E94: Opex Prior Installation Milestone
E96: O & M/ FMS + PMC Charges + MDM Charges | F96: =INDEX($K96:$O96, MATCH($F$4, $K$4:$O$4, 0)) -> 4.05 | G96: INR / meter / month | K96: 4.05 | L96: 4.05 | M96: 4.05 | N96: 4.05 | O96: 4.05
E97: ATS Charges on Softwares | F97: =INDEX($K97:$O97, MATCH($F$4, $K$4:$O$4, 0)) -> 2.45 | G97: INR / meter / month | K97: 2.45 | L97: 2.45 | M97: 2.45 | N97: 2.45 | O97: 2.45
E98: Cloud Hosting Charges | F98: =INDEX($K98:$O98, MATCH($F$4, $K$4:$O$4, 0)) -> 2.8 | G98: INR / meter / month | K98: 2.8 | L98: 2.8 | M98: 2.8 | N98: 2.8 | O98: 2.8
E99: GPRS Charges for GPRS Meters | F99: =INDEX($K99:$O99, MATCH($F$4, $K$4:$O$4, 0)) -> 6.101 | G99: INR / meter / month | K99: 6.101 | L99: 6.101 | M99: 6.101 | N99: 6.101 | O99: 6.101
E100: Site Mandays Cost | F100: =INDEX($K100:$O100, MATCH($F$4, $K$4:$O$4, 0)) -> 0.778 | G100: INR Cr / month | K100: 0.778 | L100: 0.778 | M100: 0.778 | N100: 0.778 | O100: 0.778
E101: Site Running+Auditor+Training Cost | F101: =INDEX($K101:$O101, MATCH($F$4, $K$4:$O$4, 0)) -> 0.283 | G101: INR Cr / month | K101: 0.283 | L101: 0.283 | M101: 0.283 | N101: 0.283 | O101: 0.283
E102: Travel Cost | F102: =INDEX($K102:$O102, MATCH($F$4, $K$4:$O$4, 0)) -> 0.098 | G102: INR Cr / month | K102: 0.098 | L102: 0.098 | M102: 0.098 | N102: 0.098 | O102: 0.098
E103: BG, Insurance Cost & Fin. Compliance Cost | F103: =INDEX($K103:$O103, MATCH($F$4, $K$4:$O$4, 0)) -> 0.305 | G103: INR Cr / month | K103: 0.305 | L103: 0.305 | M103: 0.305 | N103: 0.305 | O103: 0.305
E104: Cables | F104: =INDEX($K104:$O104, MATCH($F$4, $K$4:$O$4, 0)) -> 685.89 | G104: INR / meter | K104: 685.89 | L104: 685.89 | M104: 685.89 | N104: 685.89 | O104: 685.89
E105: Penalty - SLA | F105: =INDEX($K105:$O105, MATCH($F$4, $K$4:$O$4, 0)) -> 0.02 | G105: % of revenue | K105: 0.02 | L105: 0.02 | M105: 0.02 | N105: 0.02 | O105: 0.02
E107: Opex Post Installation Milestone
E109: O & M/ FMS + PMC Charges + MDM Charges | F109: =INDEX($K109:$O109, MATCH($F$4, $K$4:$O$4, 0)) -> 4.05 | G109: INR / meter / month | K109: =K96 -> 4.05 | L109: =L96 -> 4.05 | M109: =M96 -> 4.05 | N109: =N96 -> 4.05 | O109: =O96 -> 4.05
E110: ATS Charges on Softwares | F110: =INDEX($K110:$O110, MATCH($F$4, $K$4:$O$4, 0)) -> 2.45 | G110: INR / meter / month | K110: =K97 -> 2.45 | L110: =L97 -> 2.45 | M110: =M97 -> 2.45 | N110: =N97 -> 2.45 | O110: =O97 -> 2.45
E111: Cloud Hosting Charges | F111: =INDEX($K111:$O111, MATCH($F$4, $K$4:$O$4, 0)) -> 2.8 | G111: INR / meter / month | K111: =K98 -> 2.8 | L111: =L98 -> 2.8 | M111: =M98 -> 2.8 | N111: =N98 -> 2.8 | O111: =O98 -> 2.8
E112: GPRS Charges for GPRS Meters | F112: =INDEX($K112:$O112, MATCH($F$4, $K$4:$O$4, 0)) -> 6.101 | G112: INR / meter / month | K112: =K99 -> 6.101 | L112: =L99 -> 6.101 | M112: =M99 -> 6.101 | N112: =N99 -> 6.101 | O112: =O99 -> 6.101
E113: Site Mandays Cost | F113: =INDEX($K113:$O113, MATCH($F$4, $K$4:$O$4, 0)) -> 0.778 | G113: INR Cr / month | K113: =K100 -> 0.778 | L113: =L100 -> 0.778 | M113: =M100 -> 0.778 | N113: =N100 -> 0.778 | O113: =O100 -> 0.778
E114: Site Running+Auditor+Training Cost | F114: =INDEX($K114:$O114, MATCH($F$4, $K$4:$O$4, 0)) -> 0.283 | G114: INR Cr / month | K114: =K101 -> 0.283 | L114: =L101 -> 0.283 | M114: =M101 -> 0.283 | N114: =N101 -> 0.283 | O114: =O101 -> 0.283
E115: Travel Cost | F115: =INDEX($K115:$O115, MATCH($F$4, $K$4:$O$4, 0)) -> 0.098 | G115: INR Cr / month | K115: =K102 -> 0.098 | L115: =L102 -> 0.098 | M115: =M102 -> 0.098 | N115: =N102 -> 0.098 | O115: =O102 -> 0.098
E116: BG, Insurance Cost & Fin. Compliance Cost | F116: =INDEX($K116:$O116, MATCH($F$4, $K$4:$O$4, 0)) -> 0.305 | G116: INR Cr / month | K116: =K103 -> 0.305 | L116: =L103 -> 0.305 | M116: =M103 -> 0.305 | N116: =N103 -> 0.305 | O116: =O103 -> 0.305
E117: Cables | F117: =INDEX($K117:$O117, MATCH($F$4, $K$4:$O$4, 0)) -> 0 | G117: INR / meter | K117: 0 | L117: 0 | M117: 0 | N117: 0 | O117: 0
E118: Penalty - SLA | F118: =INDEX($K118:$O118, MATCH($F$4, $K$4:$O$4, 0)) -> 0.005 | G118: % of revenue | K118: 0.005 | L118: 0.005 | M118: 0.005 | N118: 0.005 | O118: 0.005
E120: Escalation/ Discount on Opex | F120: =INDEX($K120:$O120, MATCH($F$4, $K$4:$O$4, 0)) -> 0 | G120: % | K120: 0 | L120: 0 | M120: 0 | N120: 0 | O120: 0
E121: Escalation on IT related expenses | F121: =INDEX($K121:$O121, MATCH($F$4, $K$4:$O$4, 0)) -> 0 | G121: % | K121: 0 | L121: 0 | M121: 0 | N121: 0 | O121: 0
E123: Payment Schedule | F123: Payment (In Month)
E124: First Payment | F124: =INDEX($K124:$O124, MATCH($F$4, $K$4:$O$4, 0)) -> 0 | G124: months | K124: 0 | L124: 0 | M124: 0 | N124: 0 | O124: 0
E125: Second Payment | F125: =INDEX($K125:$O125, MATCH($F$4, $K$4:$O$4, 0)) -> 0 | G125: months | K125: 0 | L125: 0 | M125: 0 | N125: 0 | O125: 0
E126: Final Payment | F126: =INDEX($K126:$O126, MATCH($F$4, $K$4:$O$4, 0)) -> 0 | G126: months | K126: 0 | L126: 0 | M126: 0 | N126: 0 | O126: 0
E127: Note: Maximum delay in payment assumed as 3 months
E129: GST on Opex | F129: =INDEX($K129:$O129, MATCH($F$4, $K$4:$O$4, 0)) -> 0.18 | G129: % | K129: 0.18 | L129: 0.18 | M129: 0.18 | N129: 0.18 | O129: 0.18
E131: CSR Expenses | F131: =INDEX($K131:$O131, MATCH($F$4, $K$4:$O$4, 0)) -> 0 | G131: % | K131: 0 | L131: 0 | M131: 0 | N131: 0 | O131: 0
A133: CAPEX
...

Sheet Capex
A1: =RIGHT(CELL("FILENAME", $A$1), LEN(CELL("FILENAME", $A$1)) - SEARCH("]", CELL("FILENAME", $A$1))) -> Capex
E4: Increase in Project Cost (sensitivity) | F4: =IF(Sensitivity!C4=4,Sensitivity!J7,0) -> 0
A7: CAPEX
F8: GPRS & RF | I8: RF
F9: Weighted Average Unit Rate ( INR ) | G9: Qty | H9: Amount | I9: Unit Rate ( INR ) | J9: Qty | K9: Amount
B10: A | C10: AMI Equipment Cost | G10: =G12 -> 0 | H10: =H12 + H23 -> 935.53938 | J10: =J12 + J23 -> 0 | K10: =K12 + K23 -> 0
D12: Smart Meter Energy | H12: =H14 + H17+ H20 -> 935.53938 | J12: =J14 + J17 + J20 -> 0 | K12: =K14 + K17+ K20 -> 0
D14: Consumer Meters | G14: =SUM(G15:G15) -> 2767868 | H14: =SUM(H15:H15) -> 935.53938 | J14: =SUM(J15:J15) -> 0 | K14: =SUM(K15:K15) -> 0
E15: Consumer Meters | F15: =3380*(1+$F$4) -> 3380 | G15: =NTBA!K74 -> 2767868 | H15: =F15 * G15 / 10^7 -> 935.53938 | K15: =I15 * J15 / 10^7 -> 0
D17: DT Meters | G17: =SUM(G18:G18) -> 0 | H17: =SUM(H18:H18) -> 0 | J17: =SUM(J18:J18) -> 0 | K17: =SUM(K18:K18) -> 0
E18: DT Meeters | F18: 0 | G18: 0 | H18: =F18 * G18 / 10^7 -> 0 | K18: =I18 * J18 / 10^7 -> 0
D20: Feeder Meters | G20: =SUM(G21:G21) -> 0 | H20: =SUM(H21:H21) -> 0 | J20: =SUM(J21:J21) -> 0 | K20: =SUM(K21:K21) -> 0
E21: Feeder Meters | F21: 0 | G21: 0 | H21: =F21 * G21 / 10^7 -> 0 | K21: =I21 * J21 / 10^7 -> 0
D23: Smart Meter Box
E24: For Consumer Meters | F24: 0 | G24: 0 | H24: =F24 * G24 / 10^7 -> 0 | I24: 0 | J24: =J14 -> 0 | K24: =I24 * J24 / 10^7 -> 0
E25: For DT Meters | F25: 0 | G25: =G17 -> 0 | H25: =F25 * G25 / 10^7 -> 0 | I25: 0 | J25: =J17 -> 0 | K25: =I25 * J25 / 10^7 -> 0
E26: For Feeder Meters | F26: 0 | G26: =G20 -> 0 | H26: =F26 * G26 / 10^7 -> 0 | I26: 0 | J26: =J20 -> 0 | K26: =I26 * J26 / 10^7 -> 0
B28: B | C28: Corporate, Consumer Indexing & Training | H28: =SUM(H30:H31) -> 7.89881 | K28: =SUM(K30:K31) -> 0
E30: Corporate Cost | F30: 0 | G30: 0 | H30: =F30 * G30 / 10^7 -> 0 | I30: 0 | J30: 0 | K30: =I30 * J30 / 10^7 -> 0
E31: Consumer Indexing Charges & Training Cost | F31: =78988100*(1+F4) -> 78988100 | G31: 1 | H31: =F31 * G31 / 10^7 -> 7.89881 | I31: 0 | J31: 1 | K31: =I31 * J31 / 10^7 -> 0
B33: C | C33: Advanced Metering Infrastructure (AMI) IT | H33: =H35 -> 11.836221 | K33: =K35 -> 0
E34: `
D35: Application Software | H35: =SUM(H37:H40) -> 11.836221 | K35: =SUM(K37:K40) -> 0
E37: Head End System software | F37: =19796345.91*(1+F4) -> 19796346 | G37: 1 | H37: =F37 * G37 / 10^7 -> 1.9796346 | I37: 0 | J37: 1 | K37: =I37 * J37 / 10^7 -> 0
E38: Meter Data Management software (MDM) | F38: =49635000*(1+F4) -> 49635000 | G38: 1 | H38: =F38 * G38 / 10^7 -> 4.9635 | I38: 0 | J38: 1 | K38: =I38 * J38 / 10^7 -> 0
E39: Network Monitoring & Operation Center (NMOC) | F39: =6789540*(1+F4) -> 6789540 | G39: 1 | H39: =F39 * G39 / 10^7 -> 0.678954 | I39: 0 | J39: 1 | K39: =I39 * J39 / 10^7 -> 0
E40: Any Other | F40: =42141322.31695*(1+F4) -> 42141322 | G40: 1 | H40: =F40 * G40 / 10^7 -> 4.2141322 | I40: 0 | J40: 1 | K40: =I40 * J40 / 10^7 -> 0
B42: D | C42: Installation Charges | H42: =SUM( H44:H44) -> 79.394203
E44: Installation charges for All meters | F44: =793942032.45*(1+F4) -> 7.9394203e+08 | G44: 1 | H44: =F44 * G44 / 10^7 -> 79.394203 | I44: 0 | J44: 1 | K44: =I44 * J44 / 10^7 -> 0
B47: Capex Base Amount
E48: GST on Capex (In %) | F48: 0.18 | G48: In %
E50: AMI Equipment Cost | F50: =Capex!$H$10 -> 935.53938 | G50: =Capex!F50 * Capex!$F$48 -> 168.39709 | H50: =Capex!F50 + Capex!G50 -> 1103.9365
E51: Corporate, Consumer Indexing & Training | F51: =Capex!$H$28 -> 7.89881 | G51: =Capex!F51 * Capex!$F$48 -> 1.4217858 | H51: =Capex!F51 + Capex!G51 -> 9.3205958
E52: Advanced Metering Infrastructure (AMI) IT | F52: =Capex!$H$33 -> 11.836221 | G52: =Capex!F52 * Capex!$F$48 -> 2.1305197 | H52: =Capex!F52 + Capex!G52 -> 13.966741
E53: Installation Charges | F53: =Capex!$H$42 -> 79.394203 | G53: =Capex!F53 * Capex!$F$48 -> 14.290957 | H53: =Capex!F53 + Capex!G53 -> 93.68516
E54: Armoured Cables | F54: =474.620390121488*(1-F80) -> 0 | G54: =Capex!F54 * Capex!$F$48 -> 0 | H54: =Capex!F54 + Capex!G54 -> 0
E55: Contingencies | F55: =16.7031242932969*(1+F4) -> 16.703124 | G55: =Capex!F55 * Capex!$F$48 -> 3.0065624 | H55: =Capex!F55 + Capex!G55 -> 19.709687
E56: Total Capex | F56: =SUM(F50:F55) -> 1051.3717 | G56: =SUM(G50:G55) -> 189.24691 | H56: =SUM( H50:H55 ) -> 1240.6187
E58: Financing Charges - Capex | F58: =NTBA!F227 * NTBA!F201 -> 7.0251091 | G58: INR Cr
E59: Financing Charges - GST | F59: =Capex!F58 * Capex!$F$48 -> 1.2645196 | G59: INR Cr
E60: IDC | F60: =SUM(Rollout!J146:EH146) -> 0 | G60: INR Cr
E61: Total - Financing Charges | F61: =SUM(F58:F60) -> 8.2896287 | G61: INR Cr
E63: Interest on TL and WC | G63: INR Cr
E64: DSRA | G64: INR Cr
E66: Soft Cost - Capex | F66: =Capex!F58 + F60 -> 7.0251091 | G66: INR Cr
E67: Soft Cost - GST | F67: =Capex!F59 -> 1.2645196 | G67: INR Cr
E68: Total soft cost | F68: =Capex!F61 -> 8.2896287 | G68: INR Cr
E70: Total capex | F70: =Capex!F56 + Capex!F66 -> 1058.3969 | G70: INR Cr
E71: Total GST | F71: =Capex!G56 + Capex!F67 -> 190.51143 | G71: INR Cr
E72: Total capex | F72: =Capex!H56 + Capex!H63 + Capex!H64 + Capex!F68 -> 1248.9083 | G72: INR Cr
E74: No of months of interest on TL and WC funded as part of Project Cost | G74: In Months
E76: Capex for Armoured Cables | F76: =474.620390121488*F80*0 -> 0 | G76: INR Cr
E77: GST on Armoured Cables | F77: =F76*18% -> 0 | G77: INR Cr
E78: Total cost of Armoured Cables | F78: =F76+F77 -> 0 | G78: INR Cr
E80: Armoured Cables as a part of project cost (1: No, 0: Yes) | F80: 1

Sheet TBA
A1: =RIGHT(CELL("FILENAME", $A$1), LEN(CELL("FILENAME", $A$1)) - SEARCH("]", CELL("FILENAME", $A$1))) -> TBA
E2: =Time_M!E$2 -> Model period beginning_M | J2: =Time_M!J$2 -> 45323 | K2: =Time_M!K$2 -> 45352 | L2: =Time_M!L$2 -> 45383 | M2: =Time_M!M$2 -> 45413 | N2: =Time_M!N$2 -> 45444 | O2: =Time_M!O$2 -> 45474 | P2: =Time_M!P$2 -> 45505 | Q2: =Time_M!Q$2 -> 45536 | ... EH2: =Time_M!EH$2 -> 49218
E3: =Time_M!E$3 -> Model period ending_M | F3: =Check!E$10 -> Model Check | G3: =Check!F$10 -> 0 | H3: =Check!G$10 -> check | J3: =Time_M!J$3 -> 45351 | K3: =Time_M!K$3 -> 45382 | L3: =Time_M!L$3 -> 45412 | M3: =Time_M!M$3 -> 45443 | N3: =Time_M!N$3 -> 45473 | O3: =Time_M!O$3 -> 45504 | P3: =Time_M!P$3 -> 45535 | Q3: =Time_M!Q$3 -> 45565 | ... EH3: =Time_M!EH$3 -> 49248
E4: =Time_M!E$4 -> Financial year ending period_M | J4: =Time_M!J$4 -> 45382 | K4: =Time_M!K$4 -> 45382 | L4: =Time_M!L$4 -> 45747 | M4: =Time_M!M$4 -> 45747 | N4: =Time_M!N$4 -> 45747 | O4: =Time_M!O$4 -> 45747 | P4: =Time_M!P$4 -> 45747 | Q4: =Time_M!Q$4 -> 45747 | ... EH4: =Time_M!EH$4 -> 49399
E5: =Time_M!E$5 -> Financial year ending_M | F5: Constant | G5: Unit | H5: Total | J5: =Time_M!J$5 -> 2024 | K5: =Time_M!K$5 -> 2024 | L5: =Time_M!L$5 -> 2025 | M5: =Time_M!M$5 -> 2025 | N5: =Time_M!N$5 -> 2025 | O5: =Time_M!O$5 -> 2025 | P5: =Time_M!P$5 -> 2025 | Q5: =Time_M!Q$5 -> 2025 | ... EH5: =Time_M!EH$5 -> 2035
A7: SMART METER ENERGY PHASING
B9: Hardcoded data to be inputted
C10: GPRS & RF
E11: Consumer Meter | G11: Nos. | H11: =SUM(J11:EH11) -> 2620466 | J11: 0 | K11: 0 | L11: 0 | M11: 0 | N11: 0 | O11: 3 | P11: 15000 | Q11: 30000 | R11: 70000 | S11: 80000 | T11: 80000 | U11: 80000 | V11: 100000 | W11: 120000 | X11: 140000 | Y11: 160000 | Z11: 180000 | AA11: 183000 | AB11: 155000 | AC11: 155000 | AD11: 155000 | AE11: 155000 | AF11: 155000 | AG11: 155000 | AH11: 155000 | AI11: 155000 | AJ11: 142463 | AK11: 0 | AL11: 0 | AM11: 0 | AN11: 0 | AO11: 0 | AP11: 0 | AQ11: 0 | AR11: 0 | AS11: 0 | AT11: 0 | AU11: 0 | AV11: 0 | AW11: 0 | AX11: 0 | AY11: 0 | AZ11: 0 | BA11: 0 | BB11: 0 | BC11: 0 | BD11: 0 | BE11: 0 | BF11: 0 | BG11: 0 | BH11: 0 | BI11: 0 | BJ11: 0 | BK11: 0 | BL11: 0 | BM11: 0 | BN11: 0 | BO11: 0 | BP11: 0 | BQ11: 0 | BR11: 0 | BS11: 0 | BT11: 0 | BU11: 0 | BV11: 0 | BW11: 0 | BX11: 0 | BY11: 0 | BZ11: 0 | CA11: 0 | CB11: 0 | CC11: 0 | CD11: 0 | CE11: 0 | CF11: 0 | CG11: 0 | CH11: 0 | CI11: 0 | CJ11: 0 | CK11: 0 | CL11: 0 | CM11: 0 | CN11: 0 | CO11: 0 | CP11: 0 | CQ11: 0 | CR11: 0 | CS11: 0 | CT11: 0 | CU11: 0 | CV11: 0 | CW11: 0 | CX11: 0 | CY11: 0 | CZ11: 0 | DA11: 0 | DB11: 0 | DC11: 0 | DD11: 0 | DE11: 0 | DF11: 0 | DG11: 0 | DH11: 0 | DI11: 0 | DJ11: 0 | DK11: 0 | DL11: 0 | DM11: 0 | DN11: 0 | DO11: 0 | DP11: 0 | DQ11: 0 | DR11: 0 | DS11: 0 | DT11: 0 | DU11: 0 | DV11: 0 | DW11: 0 | DX11: 0 | DY11: 0 | DZ11: 0 | EA11: 0 | EB11: 0 | EC11: 0 | ED11: 0 | EE11: 0 | EF11: 0 | EG11: 0 | EH11: 0 | EI11: 0
E12: DT Meter | G12: Nos. | H12: =SUM(J12:EH12) -> 146932 | J12: 0 | K12: 0 | L12: 0 | M12: 0 | N12: 0 | O12: 41 | P12: 800 | Q12: 3000 | R12: 8000 | S12: 8000 | T12: 8000 | U12: 8000 | V12: 8000 | W12: 10000 | X12: 15000 | Y12: 18000 | Z12: 25000 | AA12: 35091 | AB12: 0 | AC12: 0 | AD12: 0 | AE12: 0 | AF12: 0 | AG12: 0 | AH12: 0 | AI12: 0 | AJ12: 0 | AK12: 0 | AL12: 0 | AM12: 0 | AN12: 0 | AO12: 0 | AP12: 0 | AQ12: 0 | AR12: 0 | AS12: 0 | AT12: 0 | AU12: 0 | AV12: 0 | AW12: 0 | AX12: 0 | AY12: 0 | AZ12: 0 | BA12: 0 | BB12: 0 | BC12: 0 | BD12: 0 | BE12: 0 | BF12: 0 | BG12: 0 | BH12: 0 | BI12: 0 | BJ12: 0 | BK12: 0 | BL12: 0 | BM12: 0 | BN12: 0 | BO12: 0 | BP12: 0 | BQ12: 0 | BR12: 0 | BS12: 0 | BT12: 0 | BU12: 0 | BV12: 0 | BW12: 0 | BX12: 0 | BY12: 0 | BZ12: 0 | CA12: 0 | CB12: 0 | CC12: 0 | CD12: 0 | CE12: 0 | CF12: 0 | CG12: 0 | CH12: 0 | CI12: 0 | CJ12: 0 | CK12: 0 | CL12: 0 | CM12: 0 | CN12: 0 | CO12: 0 | CP12: 0 | CQ12: 0 | CR12: 0 | CS12: 0 | CT12: 0 | CU12: 0 | CV12: 0 | CW12: 0 | CX12: 0 | CY12: 0 | CZ12: 0 | DA12: 0 | DB12: 0 | DC12: 0 | DD12: 0 | DE12: 0 | DF12: 0 | DG12: 0 | DH12: 0 | DI12: 0 | DJ12: 0 | DK12: 0 | DL12: 0 | DM12: 0 | DN12: 0 | DO12: 0 | DP12: 0 | DQ12: 0 | DR12: 0 | DS12: 0 | DT12: 0 | DU12: 0 | DV12: 0 | DW12: 0 | DX12: 0 | DY12: 0 | DZ12: 0 | EA12: 0 | EB12: 0 | EC12: 0 | ED12: 0 | EE12: 0 | EF12: 0 | EG12: 0 | EH12: 0 | EI12: 0
E13: Feeder Meter | G13: Nos. | H13: =SUM(J13:EH13) -> 470 | J13: 0 | K13: 0 | L13: 0 | M13: 0 | N13: 0 | O13: 186 | P13: 84 | Q13: 200 | R13: 0 | S13: 0 | T13: 0 | U13: 0 | V13: 0 | W13: 0 | X13: 0 | Y13: 0 | Z13: 0 | AA13: 0 | AB13: 0 | AC13: 0 | AD13: 0 | AE13: 0 | AF13: 0 | AG13: 0 | AH13: 0 | AI13: 0 | AJ13: 0 | AK13: 0 | AL13: 0 | AM13: 0 | AN13: 0 | AO13: 0 | AP13: 0 | AQ13: 0 | AR13: 0 | AS13: 0 | AT13: 0 | AU13: 0 | AV13: 0 | AW13: 0 | AX13: 0 | AY13: 0 | AZ13: 0 | BA13: 0 | BB13: 0 | BC13: 0 | BD13: 0 | BE13: 0 | BF13: 0 | BG13: 0 | BH13: 0 | BI13: 0 | BJ13: 0 | BK13: 0 | BL13: 0 | BM13: 0 | BN13: 0 | BO13: 0 | BP13: 0 | BQ13: 0 | BR13: 0 | BS13: 0 | BT13: 0 | BU13: 0 | BV13: 0 | BW13: 0 | BX13: 0 | BY13: 0 | BZ13: 0 | CA13: 0 | CB13: 0 | CC13: 0 | CD13: 0 | CE13: 0 | CF13: 0 | CG13: 0 | CH13: 0 | CI13: 0 | CJ13: 0 | CK13: 0 | CL13: 0 | CM13: 0 | CN13: 0 | CO13: 0 | CP13: 0 | CQ13: 0 | CR13: 0 | CS13: 0 | CT13: 0 | CU13: 0 | CV13: 0 | CW13: 0 | CX13: 0 | CY13: 0 | CZ13: 0 | DA13: 0 | DB13: 0 | DC13: 0 | DD13: 0 | DE13: 0 | DF13: 0 | DG13: 0 | DH13: 0 | DI13: 0 | DJ13: 0 | DK13: 0 | DL13: 0 | DM13: 0 | DN13: 0 | DO13: 0 | DP13: 0 | DQ13: 0 | DR13: 0 | DS13: 0 | DT13: 0 | DU13: 0 | DV13: 0 | DW13: 0 | DX13: 0 | DY13: 0 | DZ13: 0 | EA13: 0 | EB13: 0 | EC13: 0 | ED13: 0 | EE13: 0 | EF13: 0 | EG13: 0 | EH13: 0 | EI13: 0
C15: RF
E16: Consumer Meter | G16: Nos. | H16: =SUM(J16:EH16) -> 0 | J16: 0 | K16: 0 | L16: 0 | M16: 0 | N16: 0 | O16: 0 | P16: 0 | Q16: 0 | R16: 0 | S16: 0 | T16: 0 | U16: 0 | V16: 0 | W16: 0 | X16: 0 | Y16: 0 | Z16: 0 | AA16: 0 | AB16: 0 | AC16: 0 | AD16: 0 | AE16: 0 | AF16: 0 | AG16: 0 | AH16: 0 | AI16: 0 | AJ16: 0 | AK16: 0 | AL16: 0 | AM16: 0 | AN16: 0 | AO16: 0 | AP16: 0 | AQ16: 0 | AR16: 0 | AS16: 0 | AT16: 0 | AU16: 0 | AV16: 0 | AW16: 0 | AX16: 0 | AY16: 0 | AZ16: 0 | BA16: 0 | BB16: 0 | BC16: 0 | BD16: 0 | BE16: 0 | BF16: 0 | BG16: 0 | BH16: 0 | BI16: 0 | BJ16: 0 | BK16: 0 | BL16: 0 | BM16: 0 | BN16: 0 | BO16: 0 | BP16: 0 | BQ16: 0 | BR16: 0 | BS16: 0 | BT16: 0 | BU16: 0 | BV16: 0 | BW16: 0 | BX16: 0 | BY16: 0 | BZ16: 0 | CA16: 0 | CB16: 0 | CC16: 0 | CD16: 0 | CE16: 0 | CF16: 0 | CG16: 0 | CH16: 0 | CI16: 0 | CJ16: 0 | CK16: 0 | CL16: 0 | CM16: 0 | CN16: 0 | CO16: 0 | CP16: 0 | CQ16: 0 | CR16: 0 | CS16: 0 | CT16: 0 | CU16: 0 | CV16: 0 | CW16: 0 | CX16: 0 | CY16: 0 | CZ16: 0 | DA16: 0 | DB16: 0 | DC16: 0 | DD16: 0 | DE16: 0 | DF16: 0 | DG16: 0 | DH16: 0 | DI16: 0 | DJ16: 0 | DK16: 0 | DL16: 0 | DM16: 0 | DN16: 0 | DO16: 0 | DP16: 0 | DQ16: 0 | DR16: 0 | DS16: 0 | DT16: 0 | DU16: 0 | DV16: 0 | DW16: 0 | DX16: 0 | DY16: 0 | DZ16: 0 | EA16: 0 | EB16: 0 | EC16: 0 | ED16: 0 | EE16: 0 | EF16: 0 | EG16: 0 | EH16: 0
E17: DT Meter | G17: Nos. | H17: =SUM(J17:EH17) -> 0 | J17: 0 | K17: 0 | L17: 0 | M17: 0 | N17: 0 | O17: 0 | P17: 0 | Q17: 0 | R17: 0 | S17: 0 | T17: 0 | U17: 0 | V17: 0 | W17: 0 | X17: 0 | Y17: 0 | Z17: 0 | AA17: 0 | AB17: 0 | AC17: 0 | AD17: 0 | AE17: 0 | AF17: 0 | AG17: 0 | AH17: 0 | AI17: 0 | AJ17: 0 | AK17: 0 | AL17: 0 | AM17: 0 | AN17: 0 | AO17: 0 | AP17: 0 | AQ17: 0 | AR17: 0 | AS17: 0 | AT17: 0 | AU17: 0 | AV17: 0 | AW17: 0 | AX17: 0 | AY17: 0 | AZ17: 0 | BA17: 0 | BB17: 0 | BC17: 0 | BD17: 0 | BE17: 0 | BF17: 0 | BG17: 0 | BH17: 0 | BI17: 0 | BJ17: 0 | BK17: 0 | BL17: 0 | BM17: 0 | BN17: 0 | BO17: 0 | BP17: 0 | BQ17: 0 | BR17: 0 | BS17: 0 | BT17: 0 | BU17: 0 | BV17: 0 | BW17: 0 | BX17: 0 | BY17: 0 | BZ17: 0 | CA17: 0 | CB17: 0 | CC17: 0 | CD17: 0 | CE17: 0 | CF17: 0 | CG17: 0 | CH17: 0 | CI17: 0 | CJ17: 0 | CK17: 0 | CL17: 0 | CM17: 0 | CN17: 0 | CO17: 0 | CP17: 0 | CQ17: 0 | CR17: 0 | CS17: 0 | CT17: 0 | CU17: 0 | CV17: 0 | CW17: 0 | CX17: 0 | CY17: 0 | CZ17: 0 | DA17: 0 | DB17: 0 | DC17: 0 | DD17: 0 | DE17: 0 | DF17: 0 | DG17: 0 | DH17: 0 | DI17: 0 | DJ17: 0 | DK17: 0 | DL17: 0 | DM17: 0 | DN17: 0 | DO17: 0 | DP17: 0 | DQ17: 0 | DR17: 0 | DS17: 0 | DT17: 0 | DU17: 0 | DV17: 0 | DW17: 0 | DX17: 0 | DY17: 0 | DZ17: 0 | EA17: 0 | EB17: 0 | EC17: 0 | ED17: 0 | EE17: 0 | EF17: 0 | EG17: 0 | EH17: 0
E18: Feeder Meter | G18: Nos. | H18: =SUM(J18:EH18) -> 0 | J18: 0 | K18: 0 | L18: 0 | M18: 0 | N18: 0 | O18: 0 | P18: 0 | Q18: 0 | R18: 0 | S18: 0 | T18: 0 | U18: 0 | V18: 0 | W18: 0 | X18: 0 | Y18: 0 | Z18: 0 | AA18: 0 | AB18: 0 | AC18: 0 | AD18: 0 | AE18: 0 | AF18: 0 | AG18: 0 | AH18: 0 | AI18: 0 | AJ18: 0 | AK18: 0 | AL18: 0 | AM18: 0 | AN18: 0 | AO18: 0 | AP18: 0 | AQ18: 0 | AR18: 0 | AS18: 0 | AT18: 0 | AU18: 0 | AV18: 0 | AW18: 0 | AX18: 0 | AY18: 0 | AZ18: 0 | BA18: 0 | BB18: 0 | BC18: 0 | BD18: 0 | BE18: 0 | BF18: 0 | BG18: 0 | BH18: 0 | BI18: 0 | BJ18: 0 | BK18: 0 | BL18: 0 | BM18: 0 | BN18: 0 | BO18: 0 | BP18: 0 | BQ18: 0 | BR18: 0 | BS18: 0 | BT18: 0 | BU18: 0 | BV18: 0 | BW18: 0 | BX18: 0 | BY18: 0 | BZ18: 0 | CA18: 0 | CB18: 0 | CC18: 0 | CD18: 0 | CE18: 0 | CF18: 0 | CG18: 0 | CH18: 0 | CI18: 0 | CJ18: 0 | CK18: 0 | CL18: 0 | CM18: 0 | CN18: 0 | CO18: 0 | CP18: 0 | CQ18: 0 | CR18: 0 | CS18: 0 | CT18: 0 | CU18: 0 | CV18: 0 | CW18: 0 | CX18: 0 | CY18: 0 | CZ18: 0 | DA18: 0 | DB18: 0 | DC18: 0 | DD18: 0 | DE18: 0 | DF18: 0 | DG18: 0 | DH18: 0 | DI18: 0 | DJ18: 0 | DK18: 0 | DL18: 0 | DM18: 0 | DN18: 0 | DO18: 0 | DP18: 0 | DQ18: 0 | DR18: 0 | DS18: 0 | DT18: 0 | DU18: 0 | DV18: 0 | DW18: 0 | DX18: 0 | DY18: 0 | DZ18: 0 | EA18: 0 | EB18: 0 | EC18: 0 | ED18: 0 | EE18: 0 | EF18: 0 | EG18: 0 | EH18: 0
B20: Auto-Computed
C21: GPRS & RF
E22: Consumer Meter | G22: Nos. | H22: =SUM(J22:EH22) -> 0 | J22: 0 | K22: 0 | L22: 0
E23: DT Meter | G23: Nos. | H23: =SUM(J23:EH23) -> 0 | J23: 0 | K23: 0 | L23: 0
E24: Feeder Meter | G24: Nos. | H24: =SUM(J24:EH24) -> 0 | J24: 0 | K24: 0 | L24: 0
C26: RF
E27: Consumer Meter | G27: Nos. | H27: =SUM(J27:EH27) -> 0 | J27: 0 | K27: 0 | L27: 0
E28: DT Meter | G28: Nos. | H28: =SUM(J28:EH28) -> 0 | J28: 0 | K28: 0 | L28: 0
E29: Feeder Meter | G29: Nos. | H29: =SUM(J29:EH29) -> 0 | J29: 0 | K29: 0 | L29: 0
B31: Selected Case
E32: Hardcoded/Auto computed option | F32: 1 | G32: Select | H32: 1: Hardcoded , 2 Auto computed
C34: GPRS & RF
E35: Consumer Meter | G35: Nos. | H35: =SUM(J35:EH35) -> 2620466 | J35: =CHOOSE($F$32, J11, J22 ) -> 0 | K35: =CHOOSE($F$32, K11, K22 ) -> 0 | L35: =CHOOSE($F$32, L11, L22 ) -> 0 | M35: =CHOOSE($F$32, M11, M22 ) -> 0 | N35: =CHOOSE($F$32, N11, N22 ) -> 0 | O35: =CHOOSE($F$32, O11, O22 ) -> 3 | P35: =CHOOSE($F$32, P11, P22 ) -> 15000 | Q35: =CHOOSE($F$32, Q11, Q22 ) -> 30000 | ... EH35: =CHOOSE($F$32, EH11, EH22 ) -> 0
E36: DT Meter | G36: Nos. | H36: =SUM(J36:EH36) -> 146932 | J36: =CHOOSE($F$32, J12, J23 ) -> 0 | K36: =CHOOSE($F$32, K12, K23 ) -> 0 | L36: =CHOOSE($F$32, L12, L23 ) -> 0 | M36: =CHOOSE($F$32, M12, M23 ) -> 0 | N36: =CHOOSE($F$32, N12, N23 ) -> 0 | O36: =CHOOSE($F$32, O12, O23 ) -> 41 | P36: =CHOOSE($F$32, P12, P23 ) -> 800 | Q36: =CHOOSE($F$32, Q12, Q23 ) -> 3000 | ... EH36: =CHOOSE($F$32, EH12, EH23 ) -> 0
E37: Feeder Meter | G37: Nos. | H37: =SUM(J37:EH37) -> 470 | J37: =CHOOSE($F$32, J13, J24 ) -> 0 | K37: =CHOOSE($F$32, K13, K24 ) -> 0 | L37: =CHOOSE($F$32, L13, L24 ) -> 0 | M37: =CHOOSE($F$32, M13, M24 ) -> 0 | N37: =CHOOSE($F$32, N13, N24 ) -> 0 | O37: =CHOOSE($F$32, O13, O24 ) -> 186 | P37: =CHOOSE($F$32, P13, P24 ) -> 84 | Q37: =CHOOSE($F$32, Q13, Q24 ) -> 200 | ... EH37: =CHOOSE($F$32, EH13, EH24 ) -> 0
C39: RF
E40: Consumer Meter | G40: Nos. | H40: =SUM(J40:EH40) -> 0 | J40: =CHOOSE($F$32, J16, J27 ) -> 0 | K40: =CHOOSE($F$32, K16, K27 ) -> 0 | L40: =CHOOSE($F$32, L16, L27 ) -> 0 | M40: =CHOOSE($F$32, M16, M27 ) -> 0 | N40: =CHOOSE($F$32, N16, N27 ) -> 0 | O40: =CHOOSE($F$32, O16, O27 ) -> 0 | P40: =CHOOSE($F$32, P16, P27 ) -> 0 | Q40: =CHOOSE($F$32, Q16, Q27 ) -> 0 | ... EH40: =CHOOSE($F$32, EH16, EH27 ) -> 0
E41: DT Meter | G41: Nos. | H41: =SUM(J41:EH41) -> 0 | J41: =CHOOSE($F$32, J17, J28 ) -> 0 | K41: =CHOOSE($F$32, K17, K28 ) -> 0 | L41: =CHOOSE($F$32, L17, L28 ) -> 0 | M41: =CHOOSE($F$32, M17, M28 ) -> 0 | N41: =CHOOSE($F$32, N17, N28 ) -> 0 | O41: =CHOOSE($F$32, O17, O28 ) -> 0 | P41: =CHOOSE($F$32, P17, P28 ) -> 0 | Q41: =CHOOSE($F$32, Q17, Q28 ) -> 0 | ... EH41: =CHOOSE($F$32, EH17, EH28 ) -> 0
E42: Feeder Meter | G42: Nos. | H42: =SUM(J42:EH42) -> 0 | J42: =CHOOSE($F$32, J18, J29 ) -> 0 | K42: =CHOOSE($F$32, K18, K29 ) -> 0 | L42: =CHOOSE($F$32, L18, L29 ) -> 0 | M42: =CHOOSE($F$32, M18, M29 ) -> 0 | N42: =CHOOSE($F$32, N18, N29 ) -> 0 | O42: =CHOOSE($F$32, O18, O29 ) -> 0 | P42: =CHOOSE($F$32, P18, P29 ) -> 0 | Q42: =CHOOSE($F$32, Q18, Q29 ) -> 0 | ... EH42: =CHOOSE($F$32, EH18, EH29 ) -> 0
A46: CAPEX PHASING
E48: AMI Equipment Cost | G48: % | H48: =SUM(TBA!J48:EH48) -> 1 | J48: =SUM(J11:J13)/SUM($H$11:$H$13) -> 0 | K48: =SUM(K11:K13)/SUM($H$11:$H$13) -> 0 | L48: =SUM(L11:L13)/SUM($H$11:$H$13) -> 0 | M48: =SUM(M11:M13)/SUM($H$11:$H$13) -> 0 | N48: =SUM(N11:N13)/SUM($H$11:$H$13) -> 0 | O48: =SUM(O11:O13)/SUM($H$11:$H$13) -> 8.3096448e-05 | P48: =SUM(P11:P13)/SUM($H$11:$H$13) -> 0.005738713 | Q48: =SUM(Q11:Q13)/SUM($H$11:$H$13) -> 0.011994792 | ... EH48: =SUM(EH11:EH13)/SUM($H$11:$H$13) -> 0
E49: Corporate, Consumer Indexing & Training | G49: % | H49: =SUM(TBA!J49:EH49) -> 1 | J49: =J48 -> 0 | K49: =K48 -> 0 | L49: =L48 -> 0 | M49: =M48 -> 0 | N49: =N48 -> 0 | O49: =O48 -> 8.3096448e-05 | P49: =P48 -> 0.005738713 | Q49: =Q48 -> 0.011994792 | ... EH49: =EH48 -> 0
E50: Advanced Metering Infrastructure (AMI) IT | G50: % | H50: =SUM(TBA!J50:EH50) -> 1 | J50: =J49 -> 0 | K50: =K49 -> 0 | L50: =L49 -> 0 | M50: =M49 -> 0 | N50: =N49 -> 0 | O50: =O49 -> 8.3096448e-05 | P50: =P49 -> 0.005738713 | Q50: =Q49 -> 0.011994792 | ... EH50: =EH49 -> 0
E51: Installation Charges | G51: % | H51: =SUM(TBA!J51:EH51) -> 1 | J51: =J50 -> 0 | K51: =K50 -> 0 | L51: =L50 -> 0 | M51: =M50 -> 0 | N51: =N50 -> 0 | O51: =O50 -> 8.3096448e-05 | P51: =P50 -> 0.005738713 | Q51: =Q50 -> 0.011994792 | ... EH51: =EH50 -> 0
E52: System Integration Charges | G52: % | H52: =SUM(TBA!J52:EH52) -> 1 | J52: =J51 -> 0 | K52: =K51 -> 0 | L52: =L51 -> 0 | M52: =M51 -> 0 | N52: =N51 -> 0 | O52: =O51 -> 8.3096448e-05 | P52: =P51 -> 0.005738713 | Q52: =Q51 -> 0.011994792 | ... EH52: =EH51 -> 0
E53: Contingencies | G53: % | H53: =SUM(TBA!J53:EH53) -> 1 | J53: 0 | K53: 0 | L53: 0 | M53: 0 | N53: 0 | O53: 0 | P53: 0 | Q53: 0 | R53: 0 | S53: 0 | T53: 0 | U53: 0 | V53: 0 | W53: 0 | X53: 0 | Y53: 0 | Z53: 0 | AA53: 0 | AB53: 0 | AC53: 0 | AD53: 0 | AE53: 0 | AF53: 0 | AG53: 0 | AH53: 0 | AI53: 1 | AJ53: 0 | AK53: 0 | AL53: 0 | AM53: 0 | AN53: 0 | AO53: 0 | AP53: 0 | AQ53: 0 | AR53: 0 | AS53: 0 | AT53: 0 | AU53: 0 | AV53: 0 | AW53: 0 | AX53: 0 | AY53: 0 | AZ53: 0 | BA53: 0 | BB53: 0 | BC53: 0 | BD53: 0 | BE53: 0 | BF53: 0 | BG53: 0 | BH53: 0 | BI53: 0 | BJ53: 0 | BK53: 0 | BL53: 0 | BM53: 0 | BN53: 0 | BO53: 0 | BP53: 0 | BQ53: 0 | BR53: 0 | BS53: 0 | BT53: 0 | BU53: 0 | BV53: 0 | BW53: 0 | BX53: 0 | BY53: 0 | BZ53: 0 | CA53: 0 | CB53: 0 | CC53: 0 | CD53: 0 | CE53: 0 | CF53: 0 | CG53: 0 | CH53: 0 | CI53: 0 | CJ53: 0 | CK53: 0 | CL53: 0 | CM53: 0 | CN53: 0 | CO53: 0 | CP53: 0 | CQ53: 0 | CR53: 0 | CS53: 0 | CT53: 0 | CU53: 0 | CV53: 0 | CW53: 0 | CX53: 0 | CY53: 0 | CZ53: 0 | DA53: 0 | DB53: 0 | DC53: 0 | DD53: 0 | DE53: 0 | DF53: 0 | DG53: 0 | DH53: 0 | DI53: 0 | DJ53: 0 | DK53: 0 | DL53: 0 | DM53: 0 | DN53: 0 | DO53: 0 | DP53: 0 | DQ53: 0 | DR53: 0 | DS53: 0 | DT53: 0 | DU53: 0 | DV53: 0 | DW53: 0 | DX53: 0 | DY53: 0 | DZ53: 0 | EA53: 0 | EB53: 0 | EC53: 0 | ED53: 0 | EE53: 0 | EF53: 0 | EG53: 0 | EH53: 0
E54: Financing Charges | G54: % | H54: =SUM(TBA!J54:EH54) -> 1 | J54: 0 | K54: 0 | L54: 0 | M54: 0 | N54: 0 | O54: 1 | P54: 0 | Q54: 0 | R54: 0 | S54: 0 | T54: 0 | U54: 0 | V54: 0 | W54: 0 | X54: 0 | Y54: 0 | Z54: 0 | AA54: 0 | AB54: 0 | AC54: 0 | AD54: 0 | AE54: 0 | AF54: 0 | AG54: 0 | AH54: 0 | AI54: 0 | AJ54: 0 | AK54: 0 | AL54: 0 | AM54: 0 | AN54: 0 | AO54: 0 | AP54: 0 | AQ54: 0 | AR54: 0 | AS54: 0 | AT54: 0 | AU54: 0 | AV54: 0 | AW54: 0 | AX54: 0 | AY54: 0 | AZ54: 0 | BA54: 0 | BB54: 0 | BC54: 0 | BD54: 0 | BE54: 0 | BF54: 0 | BG54: 0 | BH54: 0 | BI54: 0 | BJ54: 0 | BK54: 0 | BL54: 0 | BM54: 0 | BN54: 0 | BO54: 0 | BP54: 0 | BQ54: 0 | BR54: 0 | BS54: 0 | BT54: 0 | BU54: 0 | BV54: 0 | BW54: 0 | BX54: 0 | BY54: 0 | BZ54: 0 | CA54: 0 | CB54: 0 | CC54: 0 | CD54: 0 | CE54: 0 | CF54: 0 | CG54: 0 | CH54: 0 | CI54: 0 | CJ54: 0 | CK54: 0 | CL54: 0 | CM54: 0 | CN54: 0 | CO54: 0 | CP54: 0 | CQ54: 0 | CR54: 0 | CS54: 0 | CT54: 0 | CU54: 0 | CV54: 0 | CW54: 0 | CX54: 0 | CY54: 0 | CZ54: 0 | DA54: 0 | DB54: 0 | DC54: 0 | DD54: 0 | DE54: 0 | DF54: 0 | DG54: 0 | DH54: 0 | DI54: 0 | DJ54: 0 | DK54: 0 | DL54: 0 | DM54: 0 | DN54: 0 | DO54: 0 | DP54: 0 | DQ54: 0 | DR54: 0 | DS54: 0 | DT54: 0 | DU54: 0 | DV54: 0 | DW54: 0 | DX54: 0 | DY54: 0 | DZ54: 0 | EA54: 0 | EB54: 0 | EC54: 0 | ED54: 0 | EE54: 0 | EF54: 0 | EG54: 0 | EH54: 0
E55: Armoured Cables | G55: % | H55: =SUM(TBA!J55:EH55) -> 1 | J55: =J48 -> 0 | K55: =K48 -> 0 | L55: =L48 -> 0 | M55: =M48 -> 0 | N55: =N48 -> 0 | O55: =O48 -> 8.3096448e-05 | P55: =P48 -> 0.005738713 | Q55: =Q48 -> 0.011994792 | ... EH55: =EH48 -> 0
A57: DEBT REPAYMENT
E59: =NTBA!E$244 -> Repayment option | F59: =NTBA!F$244 -> 4 | G59: =NTBA!G$244 -> option | H59: =NTBA!H$244 -> 1 : Mntly equal , 2 : Qtrl Structured, 3 : Qtrl Equal , 4 : Mntly structured
E60: =NTBA!E$237 -> Repayment Start Date | F60: =NTBA!F$237 -> 46203 | G60: =NTBA!G$237 -> date
E61: =NTBA!E$239 -> Repayment End Date (Month) | F61: =NTBA!F$239 -> 48244 | G61: =NTBA!G$239 -> date
E62: =NTBA!E$299 -> Months in Qtr | F62: =NTBA!F$299 -> 3 | G62: =NTBA!G$299 -> month
B64: Repayment profile
E65: Monthly-Equal | G65: % | H65: =SUM(J65:EH65) -> 0
E66: Quarterly-Structured | G66: % | H66: =SUM(J66:EH66) -> 0 | J66: 0 | K66: 0 | L66: 0 | M66: 0 | N66: 0 | O66: 0 | P66: 0 | Q66: 0 | R66: 0 | S66: 0 | T66: 0 | U66: 0 | V66: 0 | W66: 0 | X66: 0 | Y66: 0 | Z66: 0 | AA66: 0 | AB66: 0 | AC66: 0 | AD66: 0 | AE66: 0 | AF66: 0 | AG66: 0 | AH66: 0 | AI66: 0 | AJ66: 0 | AK66: 0 | AL66: 0 | AM66: 0 | AN66: 0 | AO66: 0 | AP66: 0 | AQ66: 0 | AR66: 0 | AS66: 0 | AT66: 0 | AU66: 0 | AV66: 0 | AW66: 0 | AX66: 0 | AY66: 0 | AZ66: 0 | BA66: 0 | BB66: 0 | BC66: 0 | BD66: 0 | BE66: 0 | BF66: 0 | BG66: 0 | BH66: 0 | BI66: 0 | BJ66: 0 | BK66: 0 | BL66: 0 | BM66: 0 | BN66: 0 | BO66: 0 | BP66: 0 | BQ66: 0 | BR66: 0 | BS66: 0 | BT66: 0 | BU66: 0 | BV66: 0 | BW66: 0 | BX66: 0 | BY66: 0 | BZ66: 0 | CA66: 0 | CB66: 0 | CC66: 0 | CD66: 0 | CE66: 0 | CF66: 0 | CG66: 0 | CH66: 0 | CI66: 0 | CJ66: 0 | CK66: 0 | CL66: 0 | CM66: 0 | CN66: 0 | CO66: 0 | CP66: 0 | CQ66: 0 | CR66: 0 | CS66: 0 | CT66: 0 | CU66: 0 | CV66: 0 | CW66: 0 | CX66: 0 | CY66: 0 | CZ66: 0 | DA66: 0 | DB66: 0 | DC66: 0 | DD66: 0 | DE66: 0 | DF66: 0 | DG66: 0 | DH66: 0 | DI66: 0 | DJ66: 0 | DK66: 0 | DL66: 0 | DM66: 0 | DN66: 0 | DO66: 0 | DP66: 0 | DQ66: 0 | DR66: 0 | DS66: 0 | DT66: 0 | DU66: 0 | DV66: 0 | DW66: 0 | DX66: 0 | DY66: 0 | DZ66: 0 | EA66: 0 | EB66: 0 | EC66: 0 | ED66: 0 | EE66: 0 | EF66: 0 | EG66: 0 | EH66: 0
E67: Quarterly-Equal | G67: % | H67: =SUM(J67:EH67) -> 0
E68: =Time_M!E105 -> Repayment Monthly-Structured | G68: =Time_M!G105 -> % | H68: =Time_M!H105 -> 1 | J68: =Time_M!J105 -> 0 | K68: =Time_M!K105 -> 0 | L68: =Time_M!L105 -> 0 | M68: =Time_M!M105 -> 0 | N68: =Time_M!N105 -> 0 | O68: =Time_M!O105 -> 0 | P68: =Time_M!P105 -> 0 | Q68: =Time_M!Q105 -> 0 | ... EH68: =Time_M!EH105 -> 0
E69: Repayment Profile | G69: % | H69: =SUM(J69:EH69) -> 1 | J69: =CHOOSE( $F$59, J65, J66, J67, J68 ) -> 0 | K69: =CHOOSE( $F$59, K65, K66, K67, K68 ) -> 0 | L69: =CHOOSE( $F$59, L65, L66, L67, L68 ) -> 0 | M69: =CHOOSE( $F$59, M65, M66, M67, M68 ) -> 0 | N69: =CHOOSE( $F$59, N65, N66, N67, N68 ) -> 0 | O69: =CHOOSE( $F$59, O65, O66, O67, O68 ) -> 0 | P69: =CHOOSE( $F$59, P65, P66, P67, P68 ) -> 0 | Q69: =CHOOSE( $F$59, Q65, Q66, Q67, Q68 ) -> 0 | ... EH69: =CHOOSE( $F$59, EH65, EH66, EH67, EH68 ) -> 0
E71: Repayment Profile - Debt Tranche 2 | G71: % | H71: =SUM(J71:EH71) -> 1 | J71: =IF(J3=EOMONTH(NTBA!$F$23,5),100%,0) -> 0 | K71: =IF(K3=EOMONTH(NTBA!$F$23,5),100%,0) -> 0 | L71: =IF(L3=EOMONTH(NTBA!$F$23,5),100%,0) -> 0 | M71: =IF(M3=EOMONTH(NTBA!$F$23,5),100%,0) -> 0 | N71: =IF(N3=EOMONTH(NTBA!$F$23,5),100%,0) -> 0 | O71: =IF(O3=EOMONTH(NTBA!$F$23,5),100%,0) -> 0 | P71: =IF(P3=EOMONTH(NTBA!$F$23,5),100%,0) -> 0 | Q71: =IF(Q3=EOMONTH(NTBA!$F$23,5),100%,0) -> 0 | ... AM71: =IF(AM3=EOMONTH(NTBA!$F$23,5),100%,0) -> 0 | AN71: 1 | AO71: 0 | AP71: 0 | AQ71: 0 | AR71: =IF(AR3=EOMONTH(NTBA!$F$23,5),100%,0) -> 0 | AS71: =IF(AS3=EOMONTH(NTBA!$F$23,5),100%,0) -> 0 | AT71: =IF(AT3=EOMONTH(NTBA!$F$23,5),100%,0) -> 0 | AU71: =IF(AU3=EOMONTH(NTBA!$F$23,5),100%,0) -> 0 | AV71: =IF(AV3=EOMONTH(NTBA!$F$23,5),100%,0) -> 0 | AW71: =IF(AW3=EOMONTH(NTBA!$F$23,5),100%,0) -> 0 | AX71: =IF(AX3=EOMONTH(NTBA!$F$23,5),100%,0) -> 0 | AY71: =IF(AY3=EOMONTH(NTBA!$F$23,5),100%,0) -> 0 | ... EH71: =IF(EH3=EOMONTH(NTBA!$F$23,5),100%,0) -> 0
B73: Internal Accruals used for Capex
E74: Internal acrruals | H74: =SUM(J74:EH74) -> 0
B76: Yearly Repayment profile
E77: =Ratios!E4 -> Financial year ending period_A | J77: =Ratios!J4 -> 45382 | K77: =Ratios!K4 -> 45747 | L77: =Ratios!L4 -> 46112 | M77: =Ratios!M4 -> 46477 | N77: =Ratios!N4 -> 46843 | O77: =Ratios!O4 -> 47208 | P77: =Ratios!P4 -> 47573 | Q77: =Ratios!Q4 -> 47938 | ... W77: =Ratios!W4 -> 50130
E78: Repayment Percentage | J78: 0 | K78: 0 | L78: 0 | M78: =12.55%+1.05% -> 0.136 | N78: 0.1505 | O78: 0.165 | P78: 0.1805 | Q78: 0.197 | R78: =1-SUM(J78:Q78) -> 0.171
E79: DSCR | H79: =Ratios!F34 -> 1.2018678 | J79: =Ratios!J33 -> 0 | K79: =Ratios!K33 -> 0 | L79: =Ratios!L33 -> 0 | M79: =Ratios!M33 -> 1.1507718 | N79: =Ratios!N33 -> 1.2121297 | O79: =Ratios!O33 -> 1.2101847 | P79: =Ratios!P33 -> 1.2101269 | Q79: =Ratios!Q33 -> 1.212447 | R79: =Ratios!R33 -> 1.2212269
B81: End of sheet

Sheet Rollout
A1: =RIGHT(CELL("FILENAME", $A$1), LEN(CELL("FILENAME", $A$1)) - SEARCH("]", CELL("FILENAME", $A$1))) -> Rollout
E2: =Time_M!E$18 -> Model period beginning_M | J2: =Time_M!J$18 -> 45323 | K2: =Time_M!K$18 -> 45352 | L2: =Time_M!L$18 -> 45383 | M2: =Time_M!M$18 -> 45413 | N2: =Time_M!N$18 -> 45444 | O2: =Time_M!O$18 -> 45474 | P2: =Time_M!P$18 -> 45505 | Q2: =Time_M!Q$18 -> 45536 | ... EH2: =Time_M!EH$18 -> 49218
E3: =Time_M!E$22 -> Model period ending_M | F3: =Check!E$10 -> Model Check | G3: =Check!F$10 -> 0 | H3: =Check!G$10 -> check | J3: =Time_M!J$22 -> 45351 | K3: =Time_M!K$22 -> 45382 | L3: =Time_M!L$22 -> 45412 | M3: =Time_M!M$22 -> 45443 | N3: =Time_M!N$22 -> 45473 | O3: =Time_M!O$22 -> 45504 | P3: =Time_M!P$22 -> 45535 | Q3: =Time_M!Q$22 -> 45565 | ... EH3: =Time_M!EH$22 -> 49248
E4: =Time_M!E$35 -> Financial year ending period_M | J4: =Time_M!J$35 -> 45382 | K4: =Time_M!K$35 -> 45382 | L4: =Time_M!L$35 -> 45747 | M4: =Time_M!M$35 -> 45747 | N4: =Time_M!N$35 -> 45747 | O4: =Time_M!O$35 -> 45747 | P4: =Time_M!P$35 -> 45747 | Q4: =Time_M!Q$35 -> 45747 | ... EH4: =Time_M!EH$35 -> 49399
E5: =Time_M!E$32 -> Financial year ending_M | F5: Constant | G5: Unit | H5: Total | J5: =Time_M!J$32 -> 2024 | K5: =Time_M!K$32 -> 2024 | L5: =Time_M!L$32 -> 2025 | M5: =Time_M!M$32 -> 2025 | N5: =Time_M!N$32 -> 2025 | O5: =Time_M!O$32 -> 2025 | P5: =Time_M!P$32 -> 2025 | Q5: =Time_M!Q$32 -> 2025 | ... EH5: =Time_M!EH$32 -> 2035
A7: SMART ENERGY METERS
B9: Total smart meters installed
C10: GPRS & RF
E11: Consumer Meter | F11: =TBA!F$35 -> 0 | G11: =TBA!G$35 -> Nos. | H11: =TBA!H$35 -> 2620466 | I11: =TBA!I$35 -> 0 | J11: =TBA!J$35 -> 0 | K11: =TBA!K$35 -> 0 | L11: =TBA!L$35 -> 0 | M11: =TBA!M$35 -> 0 | ... EH11: =TBA!EH$35 -> 0
E12: DT Meter | F12: =TBA!F$36 -> 0 | G12: =TBA!G$36 -> Nos. | H12: =TBA!H$36 -> 146932 | I12: =TBA!I$36 -> 0 | J12: =TBA!J$36 -> 0 | K12: =TBA!K$36 -> 0 | L12: =TBA!L$36 -> 0 | M12: =TBA!M$36 -> 0 | ... EH12: =TBA!EH$36 -> 0
E13: Feeder Meter | F13: =TBA!F$37 -> 0 | G13: =TBA!G$37 -> Nos. | H13: =TBA!H$37 -> 470 | I13: =TBA!I$37 -> 0 | J13: =TBA!J$37 -> 0 | K13: =TBA!K$37 -> 0 | L13: =TBA!L$37 -> 0 | M13: =TBA!M$37 -> 0 | ... EH13: =TBA!EH$37 -> 0
C15: RF
E16: =TBA!E$40 -> Consumer Meter | F16: =TBA!F$40 -> 0 | G16: =TBA!G$40 -> Nos. | H16: =TBA!H$40 -> 0 | I16: =TBA!I$40 -> 0 | J16: =TBA!J$40 -> 0 | K16: =TBA!K$40 -> 0 | L16: =TBA!L$40 -> 0 | ... EH16: =TBA!EH$40 -> 0
E17: =TBA!E$41 -> DT Meter | F17: =TBA!F$41 -> 0 | G17: =TBA!G$41 -> Nos. | H17: =TBA!H$41 -> 0 | I17: =TBA!I$41 -> 0 | J17: =TBA!J$41 -> 0 | K17: =TBA!K$41 -> 0 | L17: =TBA!L$41 -> 0 | ... EH17: =TBA!EH$41 -> 0
E18: =TBA!E$42 -> Feeder Meter | F18: =TBA!F$42 -> 0 | G18: =TBA!G$42 -> Nos. | H18: =TBA!H$42 -> 0 | I18: =TBA!I$42 -> 0 | J18: =TBA!J$42 -> 0 | K18: =TBA!K$42 -> 0 | L18: =TBA!L$42 -> 0 | ... EH18: =TBA!EH$42 -> 0
E19: Total smart energy meters installed | G19: Nos | H19: =SUM(J19:EH19) -> 2767868 | J19: =SUM( J11:J13, J16:J18) -> 0 | K19: =SUM( K11:K13, K16:K18) -> 0 | L19: =SUM( L11:L13, L16:L18) -> 0 | M19: =SUM( M11:M13, M16:M18) -> 0 | N19: =SUM( N11:N13, N16:N18) -> 0 | O19: =SUM( O11:O13, O16:O18) -> 230 | P19: =SUM( P11:P13, P16:P18) -> 15884 | Q19: =SUM( Q11:Q13, Q16:Q18) -> 33200 | ... EH19: =SUM( EH11:EH13, EH16:EH18) -> 0
B21: Effective meters operational
E22: =NTBA!E$55 -> Min no. of meters for first billing | F22: =NTBA!F$55 -> 27678.68
E23: =E$19 -> Total smart energy meters installed | F23: =F$19 -> 0 | G23: =G$19 -> Nos | H23: =H$19 -> 2767868 | J23: =SUMIF($J$3:$EH$3,EOMONTH(Rollout!J3,-NTBA!$F$188),Rollout!$J$19:$EH$19) -> 0 | K23: =SUMIF($J$3:$EH$3,EOMONTH(Rollout!K3,-NTBA!$F$188),Rollout!$J$19:$EH$19) -> 0 | L23: =SUMIF($J$3:$EH$3,EOMONTH(Rollout!L3,-NTBA!$F$188),Rollout!$J$19:$EH$19) -> 0 | M23: =SUMIF($J$3:$EH$3,EOMONTH(Rollout!M3,-NTBA!$F$188),Rollout!$J$19:$EH$19) -> 0 | N23: =SUMIF($J$3:$EH$3,EOMONTH(Rollout!N3,-NTBA!$F$188),Rollout!$J$19:$EH$19) -> 0 | O23: =SUMIF($J$3:$EH$3,EOMONTH(Rollout!O3,-NTBA!$F$188),Rollout!$J$19:$EH$19) -> 0 | P23: =SUMIF($J$3:$EH$3,EOMONTH(Rollout!P3,-NTBA!$F$188),Rollout!$J$19:$EH$19) -> 0 | Q23: =SUMIF($J$3:$EH$3,EOMONTH(Rollout!Q3,-NTBA!$F$188),Rollout!$J$19:$EH$19) -> 230 | ... EH23: =SUMIF($J$3:$EH$3,EOMONTH(Rollout!EH3,-NTBA!$F$188),Rollout!$J$19:$EH$19) -> 0
E24: Min no. of meters for first billing | G24: flag | H24: =SUM(J24:EH24) -> 120 | J24: =IF( SUM( $J$23:J23 ) > $F22, 1, 0 ) -> 0 | K24: =IF( SUM( $J$23:K23 ) > $F22, 1, 0 ) -> 0 | L24: =IF( SUM( $J$23:L23 ) > $F22, 1, 0 ) -> 0 | M24: =IF( SUM( $J$23:M23 ) > $F22, 1, 0 ) -> 0 | N24: =IF( SUM( $J$23:N23 ) > $F22, 1, 0 ) -> 0 | O24: =IF( SUM( $J$23:O23 ) > $F22, 1, 0 ) -> 0 | P24: =IF( SUM( $J$23:P23 ) > $F22, 1, 0 ) -> 0 | Q24: =IF( SUM( $J$23:Q23 ) > $F22, 1, 0 ) -> 0 | ... EH24: =IF( SUM( $J$23:EH23 ) > $F22, 1, 0 ) -> 1
B26: First payment date
E27: =E$24 -> Min no. of meters for first billing | F27: =F$24 -> 0 | G27: =G$24 -> flag | H27: =H$24 -> 120 | I27: =I$24 -> 0 | J27: =J$24 -> 0 | K27: =K$24 -> 0 | L27: =L$24 -> 0 | ... EH27: =EH$24 -> 1
E28: 1st payment flag for meters | G28: flag | H28: =SUM(J28:EH28) -> 1 | J28: =J27 - I27 -> 0 | K28: =K27 - J27 -> 0 | L28: =L27 - K27 -> 0 | M28: =M27 - L27 -> 0 | N28: =N27 - M27 -> 0 | O28: =O27 - N27 -> 0 | P28: =P27 - O27 -> 0 | Q28: =Q27 - P27 -> 0 | ... EH28: =EH27 - EG27 -> 0
E29: =Time_M!E$22 -> Model period ending_M | F29: =Time_M!F$22 -> 0 | G29: =Time_M!G$22 -> date | H29: =Time_M!H$22 -> 0 | I29: =Time_M!I$22 -> 0 | J29: =Time_M!J$22 -> 45351 | K29: =Time_M!K$22 -> 45382 | L29: =Time_M!L$22 -> 45412 | ... EH29: =Time_M!EH$22 -> 49248
E30: 1st payment date for meters | G30: date | J30: =IF( J28 = 1, J29, "") | K30: =IF( K28 = 1, K29, "") | L30: =IF( L28 = 1, L29, "") | M30: =IF( M28 = 1, M29, "") | N30: =IF( N28 = 1, N29, "") | O30: =IF( O28 = 1, O29, "") | P30: =IF( P28 = 1, P29, "") | Q30: =IF( Q28 = 1, Q29, "") | ... EH30: =IF( EH28 = 1, EH29, "")
E31: Month min number of meters installed for 1st Payment | F31: =INDEX(J28:EH30,2,MATCH(1,J28:EH28,0)) -> 45626 | G31: date
E33: =NTBA!E$35 -> Total number of meter months for billing for SBD | F33: =NTBA!F$35 -> 257411724 | G33: =NTBA!G$35 -> Nos.
E34: =Time_M!E$64 -> Implementation Period Flag | F34: =Time_M!F$64 -> 0 | G34: =Time_M!G$64 -> flag | H34: =Time_M!H$64 -> 124 | I34: =Time_M!I$64 -> 0 | J34: =Time_M!J$64 -> 0 | K34: =Time_M!K$64 -> 0 | L34: =Time_M!L$64 -> 0 | ... EH34: =Time_M!EH$64 -> 1
E35: =E$19 -> Total smart energy meters installed | F35: =F$19 -> 0 | G35: =G$19 -> Nos | H35: =H$19 -> 2767868 | I35: =I$19 -> 0 | J35: =SUMIF($J$3:$EH$3,EOMONTH(Rollout!J3,-NTBA!$F$188),Rollout!$J$19:$EH$19) -> 0 | K35: =SUMIF($J$3:$EH$3,EOMONTH(Rollout!K3,-NTBA!$F$188),Rollout!$J$19:$EH$19) -> 0 | L35: =SUMIF($J$3:$EH$3,EOMONTH(Rollout!L3,-NTBA!$F$188),Rollout!$J$19:$EH$19) -> 0 | M35: =SUMIF($J$3:$EH$3,EOMONTH(Rollout!M3,-NTBA!$F$188),Rollout!$J$19:$EH$19) -> 0 | N35: =SUMIF($J$3:$EH$3,EOMONTH(Rollout!N3,-NTBA!$F$188),Rollout!$J$19:$EH$19) -> 0 | O35: =SUMIF($J$3:$EH$3,EOMONTH(Rollout!O3,-NTBA!$F$188),Rollout!$J$19:$EH$19) -> 0 | P35: =SUMIF($J$3:$EH$3,EOMONTH(Rollout!P3,-NTBA!$F$188),Rollout!$J$19:$EH$19) -> 0 | Q35: =SUMIF($J$3:$EH$3,EOMONTH(Rollout!Q3,-NTBA!$F$188),Rollout!$J$19:$EH$19) -> 230 | ... EH35: =SUMIF($J$3:$EH$3,EOMONTH(Rollout!EH3,-NTBA!$F$188),Rollout!$J$19:$EH$19) -> 0
E37: Effective Meters Operational | G37: Nos | J37: =IF( J$34, MIN( $F33 - SUM( I$39:$I39 ), SUM( $I$35:J35 )), SUM( I$35:$J35 )) -> 0 | K37: =IF( K$34, MIN( $F33 - SUM( $I$39:J39 ), SUM( $I$35:K35 )), SUM( J$35:$J35 )) -> 0 | L37: =IF( L$34, MIN( $F33 - SUM( $I$39:K39 ), SUM( $I$35:L35 )), SUM( $J$35:K35 )) -> 0 | M37: =IF( M$34, MIN( $F33 - SUM( $I$39:L39 ), SUM( $I$35:M35 )), SUM( $J$35:L35 )) -> 0 | N37: =IF( N$34, MIN( $F33 - SUM( $I$39:M39 ), SUM( $I$35:N35 )), SUM( $J$35:M35 )) -> 0 | O37: =IF( O$34, MIN( $F33 - SUM( $I$39:N39 ), SUM( $I$35:O35 )), SUM( $J$35:N35 )) -> 0 | P37: =IF( P$34, MIN( $F33 - SUM( $I$39:O39 ), SUM( $I$35:P35 )), SUM( $J$35:O35 )) -> 0 | Q37: =IF( Q$34, MIN( $F33 - SUM( $I$39:P39 ), SUM( $I$35:Q35 )), SUM( $J$35:P35 )) -> 230 | R37: =IF( R$34, MIN( $F33 - SUM( $I$39:Q39 ), SUM( $I$35:R35 )), SUM( $J$35:Q35 )) -> 16114 | S37: =IF( S$34, MIN( $F33 - SUM( $I$39:R39 ), SUM( $I$35:S35 )), SUM( $J$35:R35 )) -> 49314 | ... EH37: =IF( EH$34, MIN( $F33 - SUM( $I$39:EG39 ), SUM( $I$35:EH35 )), SUM( $J$35:EG35 )) -> 0
E38: Effective Meters Operational for Opex cost | G38: Nos | J38: =MAX( MIN( $F33 - SUM( $I$38:I38 ), J37 ),0) -> 0 | K38: =MAX( MIN( $F33 - SUM( $I$38:J38 ), K37 ),0) -> 0 | L38: =MAX( MIN( $F33 - SUM( $I$38:K38 ), L37 ),0) -> 0 | M38: =MAX( MIN( $F33 - SUM( $I$38:L38 ), M37 ),0) -> 0 | N38: =MAX( MIN( $F33 - SUM( $I$38:M38 ), N37 ),0) -> 0 | O38: =MAX( MIN( $F33 - SUM( $I$38:N38 ), O37 ),0) -> 0 | P38: =MAX( MIN( $F33 - SUM( $I$38:O38 ), P37 ),0) -> 0 | Q38: =MAX( MIN( $F33 - SUM( $I$38:P38 ), Q37 ),0) -> 230 | ... DQ38: =MAX( MIN( $F33 - SUM( $I$38:DP38 ), DQ37 ),0) -> 2767868 | DR38: =DQ38 -> 2767868 | DS38: =MAX( MIN( $F33 - SUM( $I$38:DR38 ), DS37 ),0) -> 0 | DT38: =MAX( MIN( $F33 - SUM( $I$38:DS38 ), DT37 ),0) -> 0 | DU38: =MAX( MIN( $F33 - SUM( $I$38:DT38 ), DU37 ),0) -> 0 | DV38: =MAX( MIN( $F33 - SUM( $I$38:DU38 ), DV37 ),0) -> 0 | DW38: =MAX( MIN( $F33 - SUM( $I$38:DV38 ), DW37 ),0) -> 0 | DX38: =MAX( MIN( $F33 - SUM( $I$38:DW38 ), DX37 ),0) -> 0 | DY38: =MAX( MIN( $F33 - SUM( $I$38:DX38 ), DY37 ),0) -> 0 | DZ38: =MAX( MIN( $F33 - SUM( $I$38:DY38 ), DZ37 ),0) -> 0 | ... EH38: =MAX( MIN( $F33 - SUM( $I$38:EG38 ), EH37 ),0) -> 0
E39: Effective Meters Operational and billed | G39: Nos | J39: =IF(J3=$F$31,J37,IF(J3>$F$31,J37,0)) -> 0 | K39: =IF(K3=$F$31,K37,IF(K3>$F$31,K37,0)) -> 0 | L39: =IF(L3=$F$31,L37,IF(L3>$F$31,L37,0)) -> 0 | M39: =IF(M3=$F$31,M37,IF(M3>$F$31,M37,0)) -> 0 | N39: =IF(N3=$F$31,N37,IF(N3>$F$31,N37,0)) -> 0 | O39: =IF(O3=$F$31,O37,IF(O3>$F$31,O37,0)) -> 0 | P39: =IF(P3=$F$31,P37,IF(P3>$F$31,P37,0)) -> 0 | Q39: =IF(Q3=$F$31,Q37,IF(Q3>$F$31,Q37,0)) -> 0 | ... EH39: =IF(EH3=$F$31,EH37,IF(EH3>$F$31,EH37,0)) -> 0
E40: Cumulative Operational Meter Months | G40: Nos | J40: =IF( J39 > 0, SUM( $J$39:J39 ), 0 ) -> 0 | K40: =IF( K39 > 0, SUM( $J$39:K39 ), 0 ) -> 0 | L40: =IF( L39 > 0, SUM( $J$39:L39 ), 0 ) -> 0 | M40: =IF( M39 > 0, SUM( $J$39:M39 ), 0 ) -> 0 | N40: =IF( N39 > 0, SUM( $J$39:N39 ), 0 ) -> 0 | O40: =IF( O39 > 0, SUM( $J$39:O39 ), 0 ) -> 0 | P40: =IF( P39 > 0, SUM( $J$39:P39 ), 0 ) -> 0 | Q40: =IF( Q39 > 0, SUM( $J$39:Q39 ), 0 ) -> 0 | ... EH40: =IF( EH39 > 0, SUM( $J$39:EH39 ), 0 ) -> 0
E42: =NTBA!E$35 -> Total number of meter months for billing for SBD | F42: =NTBA!F$35 -> 257411724 | G42: =NTBA!G$35 -> Nos.
E43: =E40 -> Cumulative Operational Meter Months | F43: =F40 -> 0 | G43: =G40 -> Nos | H43: =H40 -> 0 | I43: =I40 -> 0 | J43: =J40 -> 0 | K43: =K40 -> 0 | L43: =L40 -> 0 | ... EH43: =EH40 -> 0
E44: SBD billing flag | G44: flag | H44: =SUM(J44:EH44) -> 1 | J44: =IF( J43 = $F42, 1, 0) -> 0 | K44: =IF( K43 = $F42, 1, 0) -> 0 | L44: =IF( L43 = $F42, 1, 0) -> 0 | M44: =IF( M43 = $F42, 1, 0) -> 0 | N44: =IF( N43 = $F42, 1, 0) -> 0 | O44: =IF( O43 = $F42, 1, 0) -> 0 | P44: =IF( P43 = $F42, 1, 0) -> 0 | Q44: =IF( Q43 = $F42, 1, 0) -> 0 | ... EH44: =IF( EH43 = $F42, 1, 0) -> 0
E45: =Time_M!E$22 -> Model period ending_M | F45: =Time_M!F$22 -> 0 | G45: =Time_M!G$22 -> date | H45: =Time_M!H$22 -> 0 | I45: =Time_M!I$22 -> 0 | J45: =Time_M!J$22 -> 45351 | K45: =Time_M!K$22 -> 45382 | L45: =Time_M!L$22 -> 45412 | ... EH45: =Time_M!EH$22 -> 49248
E46: Contract End Date | F46: =INDEX(M44:EH46,2,MATCH(1,M44:EH44,0)) -> 48760 | G46: date | J46: =IF( J44 = 1, J45,"") | K46: =IF( K44 = 1, K45,"") | L46: =IF( L44 = 1, L45,"") | M46: =IF( M44 = 1, M45,"") | N46: =IF( N44 = 1, N45,"") | O46: =IF( O44 = 1, O45,"") | P46: =IF( P44 = 1, P45,"") | Q46: =IF( Q44 = 1, Q45,"") | ... EH46: =IF( EH44 = 1, EH45,"")
A49: PAYMENT FROM DISCOM (EXCL. SERVICE CHARGES)
B51: Upfront payments - per meter
E52: =NTBA!E$36 -> Upfront Payment on Smart Meter - Consumer Meters | F52: =NTBA!F$36 -> 762.71186 | G52: =NTBA!G$36 -> INR / meter
E53: =NTBA!E$37 -> Upfront Payment on Smart Meter - DT Meters | F53: =NTBA!F$37 -> 2923.7288 | G53: =NTBA!G$37 -> INR / meter
E54: =NTBA!E$38 -> Upfront Payment on Smart Meter - Feeder Meters | F54: =NTBA!F$38 -> 5338.9831 | G54: =NTBA!G$38 -> INR / meter
E56: =E$31 -> Month min number of meters installed for 1st Payment | F56: =F$31 -> 45626 | G56: =G$31 -> date
E57: =NTBA!E$25 -> Operation end date | F57: =NTBA!F$25 -> 48760 | G57: =NTBA!G$25 -> date
E58: =Time_M!E$22 -> Model period ending_M | F58: =Time_M!F$22 -> 0 | G58: =Time_M!G$22 -> date | H58: =Time_M!H$22 -> 0 | I58: =Time_M!I$22 -> 0 | J58: =Time_M!J$22 -> 45351 | K58: =Time_M!K$22 -> 45382 | L58: =Time_M!L$22 -> 45412 | ... EH58: =Time_M!EH$22 -> 49248
E59: =TBA!E$35 -> Consumer Meter | F59: =TBA!F$35 -> 0 | G59: =TBA!G$35 -> Nos. | H59: =TBA!H$35 -> 2620466 | I59: =TBA!I$35 -> 0 | J59: =SUMIF($J$3:$EH$3,EOMONTH(Rollout!J3,-NTBA!$F$188),Rollout!$J$11:$EH$11) -> 0 | K59: =SUMIF($J$3:$EH$3,EOMONTH(Rollout!K3,-NTBA!$F$188),Rollout!$J$11:$EH$11) -> 0 | L59: =SUMIF($J$3:$EH$3,EOMONTH(Rollout!L3,-NTBA!$F$188),Rollout!$J$11:$EH$11) -> 0 | M59: =SUMIF($J$3:$EH$3,EOMONTH(Rollout!M3,-NTBA!$F$188),Rollout!$J$11:$EH$11) -> 0 | N59: =SUMIF($J$3:$EH$3,EOMONTH(Rollout!N3,-NTBA!$F$188),Rollout!$J$11:$EH$11) -> 0 | O59: =SUMIF($J$3:$EH$3,EOMONTH(Rollout!O3,-NTBA!$F$188),Rollout!$J$11:$EH$11) -> 0 | P59: =SUMIF($J$3:$EH$3,EOMONTH(Rollout!P3,-NTBA!$F$188),Rollout!$J$11:$EH$11) -> 0 | Q59: =SUMIF($J$3:$EH$3,EOMONTH(Rollout!Q3,-NTBA!$F$188),Rollout!$J$11:$EH$11) -> 3 | ... EH59: =SUMIF($J$3:$EH$3,EOMONTH(Rollout!EH3,-NTBA!$F$188),Rollout!$J$11:$EH$11) -> 0
E60: =TBA!E$36 -> DT Meter | F60: =TBA!F$36 -> 0 | G60: =TBA!G$36 -> Nos. | H60: =TBA!H$36 -> 146932 | I60: =TBA!I$36 -> 0 | J60: =SUMIF($J$3:$EH$3,EOMONTH(Rollout!J3,-NTBA!$F$188),Rollout!$J$12:$EH$12) -> 0 | K60: =SUMIF($J$3:$EH$3,EOMONTH(Rollout!K3,-NTBA!$F$188),Rollout!$J$12:$EH$12) -> 0 | L60: =SUMIF($J$3:$EH$3,EOMONTH(Rollout!L3,-NTBA!$F$188),Rollout!$J$12:$EH$12) -> 0 | M60: =SUMIF($J$3:$EH$3,EOMONTH(Rollout!M3,-NTBA!$F$188),Rollout!$J$12:$EH$12) -> 0 | N60: =SUMIF($J$3:$EH$3,EOMONTH(Rollout!N3,-NTBA!$F$188),Rollout!$J$12:$EH$12) -> 0 | O60: =SUMIF($J$3:$EH$3,EOMONTH(Rollout!O3,-NTBA!$F$188),Rollout!$J$12:$EH$12) -> 0 | P60: =SUMIF($J$3:$EH$3,EOMONTH(Rollout!P3,-NTBA!$F$188),Rollout!$J$12:$EH$12) -> 0 | Q60: =SUMIF($J$3:$EH$3,EOMONTH(Rollout!Q3,-NTBA!$F$188),Rollout!$J$12:$EH$12) -> 41 | ... EH60: =SUMIF($J$3:$EH$3,EOMONTH(Rollout!EH3,-NTBA!$F$188),Rollout!$J$12:$EH$12) -> 0
E61: =TBA!E$37 -> Feeder Meter | F61: =TBA!F$37 -> 0 | G61: =TBA!G$37 -> Nos. | H61: =TBA!H$37 -> 470 | I61: =TBA!I$37 -> 0 | J61: =SUMIF($J$3:$EH$3,EOMONTH(Rollout!J3,-NTBA!$F$188),Rollout!$J$13:$EH$13) -> 0 | K61: =SUMIF($J$3:$EH$3,EOMONTH(Rollout!K3,-NTBA!$F$188),Rollout!$J$13:$EH$13) -> 0 | L61: =SUMIF($J$3:$EH$3,EOMONTH(Rollout!L3,-NTBA!$F$188),Rollout!$J$13:$EH$13) -> 0 | M61: =SUMIF($J$3:$EH$3,EOMONTH(Rollout!M3,-NTBA!$F$188),Rollout!$J$13:$EH$13) -> 0 | N61: =SUMIF($J$3:$EH$3,EOMONTH(Rollout!N3,-NTBA!$F$188),Rollout!$J$13:$EH$13) -> 0 | O61: =SUMIF($J$3:$EH$3,EOMONTH(Rollout!O3,-NTBA!$F$188),Rollout!$J$13:$EH$13) -> 0 | P61: =SUMIF($J$3:$EH$3,EOMONTH(Rollout!P3,-NTBA!$F$188),Rollout!$J$13:$EH$13) -> 0 | Q61: =SUMIF($J$3:$EH$3,EOMONTH(Rollout!Q3,-NTBA!$F$188),Rollout!$J$13:$EH$13) -> 186 | ... EH61: =SUMIF($J$3:$EH$3,EOMONTH(Rollout!EH3,-NTBA!$F$188),Rollout!$J$13:$EH$13) -> 0
E63: Advance payment Milestone 1 | G63: INR Cr | H63: =SUM(J63:EH63) -> 0
E64: Advance payment Milestone 2 | G64: INR Cr | H64: =SUM(J64:EH64) -> 0
E65: Upfront Payment from DISCOM - Linked with MI Plan (Consumer) | G65: INR Cr | H65: =SUM(J65:EH65) -> 199.86605 | J65: =IF( AND( J$58 > $F56, J$58 <= $F$57 ),( $F52 * J59 ) / Cr, IF( J$58 = $F$56, SUM( $J59:J59 ) * $F52 / Cr,0)) -> 0 | K65: =IF( AND( K$58 > $F56, K$58 <= $F$57 ),( $F52 * K59 ) / Cr, IF( K$58 = $F$56, SUM( $J59:K59 ) * $F52 / Cr,0)) -> 0 | L65: =IF( AND( L$58 > $F56, L$58 <= $F$57 ),( $F52 * L59 ) / Cr, IF( L$58 = $F$56, SUM( $J59:L59 ) * $F52 / Cr,0)) -> 0 | M65: =IF( AND( M$58 > $F56, M$58 <= $F$57 ),( $F52 * M59 ) / Cr, IF( M$58 = $F$56, SUM( $J59:M59 ) * $F52 / Cr,0)) -> 0 | N65: =IF( AND( N$58 > $F56, N$58 <= $F$57 ),( $F52 * N59 ) / Cr, IF( N$58 = $F$56, SUM( $J59:N59 ) * $F52 / Cr,0)) -> 0 | O65: =IF( AND( O$58 > $F56, O$58 <= $F$57 ),( $F52 * O59 ) / Cr, IF( O$58 = $F$56, SUM( $J59:O59 ) * $F52 / Cr,0)) -> 0 | P65: =IF( AND( P$58 > $F56, P$58 <= $F$57 ),( $F52 * P59 ) / Cr, IF( P$58 = $F$56, SUM( $J59:P59 ) * $F52 / Cr,0)) -> 0 | Q65: =IF( AND( Q$58 > $F56, Q$58 <= $F$57 ),( $F52 * Q59 ) / Cr, IF( Q$58 = $F$56, SUM( $J59:Q59 ) * $F52 / Cr,0)) -> 0 | ... EH65: =IF( AND( EH$58 > $F56, EH$58 <= $F$57 ),( $F52 * EH59 ) / Cr, IF( EH$58 = $F$56, SUM( $J59:EH59 ) * $F52 / Cr,0)) -> 0
E66: Upfront Payment from DISCOM - Linked with MI Plan (DT) | G66: INR Cr | H66: =SUM(J66:EH66) -> 42.958932 | J66: =IF( AND( J$58 > $F$56, J$58 <= $F$57 ),( $F53 * J60 ) / Cr, IF( J$58 = $F$56, SUM( $J60:J60 ) * $F53 / Cr,0)) -> 0 | K66: =IF( AND( K$58 > $F$56, K$58 <= $F$57 ),( $F53 * K60 ) / Cr, IF( K$58 = $F$56, SUM( $J60:K60 ) * $F53 / Cr,0)) -> 0 | L66: =IF( AND( L$58 > $F$56, L$58 <= $F$57 ),( $F53 * L60 ) / Cr, IF( L$58 = $F$56, SUM( $J60:L60 ) * $F53 / Cr,0)) -> 0 | M66: =IF( AND( M$58 > $F$56, M$58 <= $F$57 ),( $F53 * M60 ) / Cr, IF( M$58 = $F$56, SUM( $J60:M60 ) * $F53 / Cr,0)) -> 0 | N66: =IF( AND( N$58 > $F$56, N$58 <= $F$57 ),( $F53 * N60 ) / Cr, IF( N$58 = $F$56, SUM( $J60:N60 ) * $F53 / Cr,0)) -> 0 | O66: =IF( AND( O$58 > $F$56, O$58 <= $F$57 ),( $F53 * O60 ) / Cr, IF( O$58 = $F$56, SUM( $J60:O60 ) * $F53 / Cr,0)) -> 0 | P66: =IF( AND( P$58 > $F$56, P$58 <= $F$57 ),( $F53 * P60 ) / Cr, IF( P$58 = $F$56, SUM( $J60:P60 ) * $F53 / Cr,0)) -> 0 | Q66: =IF( AND( Q$58 > $F$56, Q$58 <= $F$57 ),( $F53 * Q60 ) / Cr, IF( Q$58 = $F$56, SUM( $J60:Q60 ) * $F53 / Cr,0)) -> 0 | ... EH66: =IF( AND( EH$58 > $F$56, EH$58 <= $F$57 ),( $F53 * EH60 ) / Cr, IF( EH$58 = $F$56, SUM( $J60:EH60 ) * $F53 / Cr,0)) -> 0
E67: Upfront Payment from DISCOM - Linked with MI Plan (Feeder) | G67: INR Cr | H67: =SUM(J67:EH67) -> 0.2509322 | J67: =IF( AND( J$58 > $F$56, J$58 <= $F$57 ),( $F54 * J61 ) / Cr, IF( J$58 = $F$56, SUM( $J61:J61 ) * $F54 / Cr,0)) -> 0 | K67: =IF( AND( K$58 > $F$56, K$58 <= $F$57 ),( $F54 * K61 ) / Cr, IF( K$58 = $F$56, SUM( $J61:K61 ) * $F54 / Cr,0)) -> 0 | L67: =IF( AND( L$58 > $F$56, L$58 <= $F$57 ),( $F54 * L61 ) / Cr, IF( L$58 = $F$56, SUM( $J61:L61 ) * $F54 / Cr,0)) -> 0 | M67: =IF( AND( M$58 > $F$56, M$58 <= $F$57 ),( $F54 * M61 ) / Cr, IF( M$58 = $F$56, SUM( $J61:M61 ) * $F54 / Cr,0)) -> 0 | N67: =IF( AND( N$58 > $F$56, N$58 <= $F$57 ),( $F54 * N61 ) / Cr, IF( N$58 = $F$56, SUM( $J61:N61 ) * $F54 / Cr,0)) -> 0 | O67: =IF( AND( O$58 > $F$56, O$58 <= $F$57 ),( $F54 * O61 ) / Cr, IF( O$58 = $F$56, SUM( $J61:O61 ) * $F54 / Cr,0)) -> 0 | P67: =IF( AND( P$58 > $F$56, P$58 <= $F$57 ),( $F54 * P61 ) / Cr, IF( P$58 = $F$56, SUM( $J61:P61 ) * $F54 / Cr,0)) -> 0 | Q67: =IF( AND( Q$58 > $F$56, Q$58 <= $F$57 ),( $F54 * Q61 ) / Cr, IF( Q$58 = $F$56, SUM( $J61:Q61 ) * $F54 / Cr,0)) -> 0 | ... EH67: =IF( AND( EH$58 > $F$56, EH$58 <= $F$57 ),( $F54 * EH61 ) / Cr, IF( EH$58 = $F$56, SUM( $J61:EH61 ) * $F54 / Cr,0)) -> 0
E68: Upfront Payment from DISCOM - Linked with Construction End (Consumer+DT) | G68: INR Cr | H68: =SUM(J68:EH68) -> 0
E69: Reduction post Upfront Payment from DISCOM - for DT Meter | G69: INR Cr | H69: =SUM(J69:EH69) -> 0
B71: Cable payments from DISCOM - supply & installments
E72: =NTBA!E$63 -> INR / Meter | F72: =NTBA!F$63 -> 708.62846 | G72: =NTBA!G$63 -> Average Price, excl GST
E73: =NTBA!E$59 -> First Payment Milestone of Cable Charges - Payable on COD | F73: =NTBA!F$59 -> 1 | G73: =NTBA!G$59 -> %
E74: =E19 -> Total smart energy meters installed | F74: =F19 -> 0 | G74: =G19 -> Nos | H74: =H19 -> 2767868 | I74: =I19 -> 0 | J74: =J19 -> 0 | K74: =K19 -> 0 | L74: =L19 -> 0 | ... EH74: =EH19 -> 0
E76: First Payment Milestone of Cable - Linked with Supply | G76: INR Cr | H76: =SUM(J76:EH76) -> 0
E77: Second Payment Milestone of Cable - Linked with MI Plan | G77: INR Cr | H77: 0 | J77: =IF( J$58 <= $F$57,( $F72 * J74 ) / Cr, IF( J$58 = $F$56, SUM( $J74:J74 ) * $F72 / Cr,0)) -> 0 | K77: =IF( K$58 <= $F$57,( $F72 * K74 ) / Cr, IF( K$58 = $F$56, SUM( $J74:K74 ) * $F72 / Cr,0)) -> 0 | L77: =IF( L$58 <= $F$57,( $F72 * L74 ) / Cr, IF( L$58 = $F$56, SUM( $J74:L74 ) * $F72 / Cr,0)) -> 0 | M77: =IF( M$58 <= $F$57,( $F72 * M74 ) / Cr, IF( M$58 = $F$56, SUM( $J74:M74 ) * $F72 / Cr,0)) -> 0 | N77: =IF( N$58 <= $F$57,( $F72 * N74 ) / Cr, IF( N$58 = $F$56, SUM( $J74:N74 ) * $F72 / Cr,0)) -> 0 | O77: =IF( O$58 <= $F$57,( $F72 * O74 ) / Cr, IF( O$58 = $F$56, SUM( $J74:O74 ) * $F72 / Cr,0)) -> 0.016298455 | P77: =IF( P$58 <= $F$57,( $F72 * P74 ) / Cr, IF( P$58 = $F$56, SUM( $J74:P74 ) * $F72 / Cr,0)) -> 1.1255855 | Q77: =IF( Q$58 <= $F$57,( $F72 * Q74 ) / Cr, IF( Q$58 = $F$56, SUM( $J74:Q74 ) * $F72 / Cr,0)) -> 2.3526465 | ... EH77: =IF( EH$58 <= $F$57,( $F72 * EH74 ) / Cr, IF( EH$58 = $F$56, SUM( $J74:EH74 ) * $F72 / Cr,0)) -> 0
E78: Final Payment Milestone of Cable - Linked with Construction End | G78: INR Cr | H78: =SUM(J78:EH78) -> 0
E79: First Payment Milestone of Cable - Linked with MI Plan | G79: INR Cr | H79: =SUM(J79:EH79) -> 0
E80: Final Payment Milestone of Cable - Linked with Construction End | G80: INR Cr | H80: =SUM(J80:EH80) -> 0
E82: =NTBA!E$62 -> Monthly select "0" and Quarterly select "1" | F82: =NTBA!F$62 -> 1 | G82: =NTBA!G$62 -> 0 = monthly, 1 = quarterly
E83: =Time_M!E83 -> Quarter end flag | F83: =Time_M!F83 -> 0 | G83: =Time_M!G83 -> flag | H83: =Time_M!H83 -> 43 | I83: =Time_M!I83 -> 0 | J83: =Time_M!J83 -> 0 | K83: =Time_M!K83 -> 1 | L83: =Time_M!L83 -> 0 | ... EH83: =Time_M!EH83 -> 0
E84: Quarterly payment | G84: INR Cr | H84: =SUM(J84:EH84) -> 196.13901 | J84: =SUM( Rollout!H76:J80 ) * J$83 -> 0 | K84: =SUM( Rollout!I76:K80 ) * K$83 -> 0 | L84: =SUM( Rollout!J76:L80 ) * L$83 -> 0 | M84: =SUM( Rollout!K76:M80 ) * M$83 -> 0 | N84: =SUM( Rollout!L76:N80 ) * N$83 -> 0 | O84: =SUM( Rollout!M76:O80 ) * O$83 -> 0 | P84: =SUM( Rollout!N76:P80 ) * P$83 -> 0 | Q84: =SUM( Rollout!O76:Q80 ) * Q$83 -> 3.4945304 | ... EH84: =SUM( Rollout!EF76:EH80 ) * EH$83 -> 0
E85: Payment from DISCOM (Upfront) | G85: INR Cr | H85: =SUM(J85:EH85) -> 243.07592 | J85: =SUM( J63:J69) -> 0 | K85: =SUM( K63:K69) -> 0 | L85: =SUM( L63:L69) -> 0 | M85: =SUM( M63:M69) -> 0 | N85: =SUM( N63:N69) -> 0 | O85: =SUM( O63:O69) -> 0 | P85: =SUM( P63:P69) -> 0 | Q85: =SUM( Q63:Q69) -> 0 | ... EH85: =SUM( EH63:EH69) -> 0
E86: Payment from DISCOM (Cable) | G86: INR Cr | H86: =SUM(J86:EH86) -> 196.13901 | J86: =+ SUM(I76:I80) *( 1- $F$82 ) + Rollout!J84 * $F$82 -> 0 | K86: =+ SUM(J76:J80) *( 1- $F$82 ) + Rollout!K84 * $F$82 -> 0 | L86: =+ SUM(K76:K80) *( 1- $F$82 ) + Rollout!L84 * $F$82 -> 0 | M86: =+ SUM(L76:L80) *( 1- $F$82 ) + Rollout!M84 * $F$82 -> 0 | N86: =+ SUM(M76:M80) *( 1- $F$82 ) + Rollout!N84 * $F$82 -> 0 | O86: =+ SUM(N76:N80) *( 1- $F$82 ) + Rollout!O84 * $F$82 -> 0 | P86: =+ SUM(O76:O80) *( 1- $F$82 ) + Rollout!P84 * $F$82 -> 0 | Q86: =+ SUM(P76:P80) *( 1- $F$82 ) + Rollout!Q84 * $F$82 -> 3.4945304 | ... EH86: =+ SUM(EG76:EG80) *( 1- $F$82 ) + Rollout!EH84 * $F$82 -> 0
A89: CAPEX
E91: =Capex!E$50 -> AMI Equipment Cost | F91: =Capex!F$50 -> 935.53938
E92: =Capex!E$51 -> Corporate, Consumer Indexing & Training | F92: =Capex!F$51 -> 7.89881
E93: =Capex!E$52 -> Advanced Metering Infrastructure (AMI) IT | F93: =Capex!F$52 -> 11.836221
E94: =Capex!E$53 -> Installation Charges | F94: =Capex!F$53 -> 79.394203
E95: =Capex!E$54 -> Armoured Cables | F95: =Capex!F$54 -> 0
E96: =Capex!E$55 -> Contingencies | F96: =Capex!F$55 -> 16.703124
E97: =Capex!E$58 -> Financing Charges - Capex | F97: =Capex!F$58 -> 7.0251091
B99: =NTBA!B$179 -> Advance Phasing from start of meter installation (in months)
E100: =NTBA!E$180 -> AMI Equipment Cost | F100: =NTBA!F$180 -> 1 | G100: =NTBA!G$180 -> months
E101: =NTBA!E$181 -> Corporate, Consumer Indexing & Training | F101: =NTBA!F$181 -> 1 | G101: =NTBA!G$181 -> months
E102: =NTBA!E$182 -> Advanced Metering Infrastructure (AMI) IT | F102: =NTBA!F$182 -> 1 | G102: =NTBA!G$182 -> months
E103: =NTBA!E$183 -> Installation Charges | F103: =NTBA!F$183 -> 1 | G103: =NTBA!G$183 -> months
E104: =NTBA!E$184 -> System Integration Charges | F104: =NTBA!F$184 -> 1 | G104: =NTBA!G$184 -> months
E105: =NTBA!E$185 -> Contingencies | F105: =NTBA!F$185 -> 1 | G105: =NTBA!G$185 -> months
E106: =NTBA!E$186 -> Financing Charges | F106: =NTBA!F$186 -> 1 | G106: =NTBA!G$186 -> months
B108: Capital phasing
E109: AMI Equipment Cost | G109: =TBA!G$48 -> % | H109: =TBA!H$48 -> 1 | J109: =TBA!J$48 -> 0 | K109: =TBA!K$48 -> 0 | L109: =TBA!L$48 -> 0 | M109: =TBA!M$48 -> 0 | N109: =TBA!N$48 -> 0 | O109: =TBA!O$48 -> 8.3096448e-05 | P109: =TBA!P$48 -> 0.005738713 | Q109: =TBA!Q$48 -> 0.011994792 | ... EH109: =TBA!EH$48 -> 0
E110: Corporate, Consumer Indexing & Training | G110: =TBA!G$49 -> % | H110: =TBA!H$49 -> 1 | J110: =TBA!J$49 -> 0 | K110: =TBA!K$49 -> 0 | L110: =TBA!L$49 -> 0 | M110: =TBA!M$49 -> 0 | N110: =TBA!N$49 -> 0 | O110: =TBA!O$49 -> 8.3096448e-05 | P110: =TBA!P$49 -> 0.005738713 | Q110: =TBA!Q$49 -> 0.011994792 | ... EH110: =TBA!EH$49 -> 0
E111: Advanced Metering Infrastructure (AMI) IT | G111: =TBA!G$50 -> % | H111: =TBA!H$50 -> 1 | J111: =TBA!J$50 -> 0 | K111: =TBA!K$50 -> 0 | L111: =TBA!L$50 -> 0 | M111: =TBA!M$50 -> 0 | N111: =TBA!N$50 -> 0 | O111: =TBA!O$50 -> 8.3096448e-05 | P111: =TBA!P$50 -> 0.005738713 | Q111: =TBA!Q$50 -> 0.011994792 | ... EH111: =TBA!EH$50 -> 0
E112: Installation Charges | G112: =TBA!G$51 -> % | H112: =TBA!H$51 -> 1 | J112: =TBA!J$51 -> 0 | K112: =TBA!K$51 -> 0 | L112: =TBA!L$51 -> 0 | M112: =TBA!M$51 -> 0 | N112: =TBA!N$51 -> 0 | O112: =TBA!O$51 -> 8.3096448e-05 | P112: =TBA!P$51 -> 0.005738713 | Q112: =TBA!Q$51 -> 0.011994792 | ... EH112: =TBA!EH$51 -> 0
E113: System Integration Charges | G113: =TBA!G$52 -> % | H113: =TBA!H$52 -> 1 | J113: =TBA!J$52 -> 0 | K113: =TBA!K$52 -> 0 | L113: =TBA!L$52 -> 0 | M113: =TBA!M$52 -> 0 | N113: =TBA!N$52 -> 0 | O113: =TBA!O$52 -> 8.3096448e-05 | P113: =TBA!P$52 -> 0.005738713 | Q113: =TBA!Q$52 -> 0.011994792 | ... EH113: =TBA!EH$52 -> 0
E114: Contingencies | G114: =TBA!G$53 -> % | H114: =TBA!H$53 -> 1 | J114: =TBA!J$53 -> 0 | K114: =TBA!K$53 -> 0 | L114: =TBA!L$53 -> 0 | M114: =TBA!M$53 -> 0 | N114: =TBA!N$53 -> 0 | O114: =TBA!O$53 -> 0 | P114: =TBA!P$53 -> 0 | Q114: =TBA!Q$53 -> 0 | ... EH114: =TBA!EH$53 -> 0
E115: Financing Charges | G115: =TBA!G$54 -> % | H115: =TBA!H$54 -> 1 | J115: =TBA!J$54 -> 0 | K115: =TBA!K$54 -> 0 | L115: =TBA!L$54 -> 0 | M115: =TBA!M$54 -> 0 | N115: =TBA!N$54 -> 0 | O115: =TBA!O$54 -> 1 | P115: =TBA!P$54 -> 0 | Q115: =TBA!Q$54 -> 0 | ... EH115: =TBA!EH$54 -> 0
B117: Project cost
E118: =Time_M!E$9 -> Model column counter | F118: =Time_M!F$9 -> 0 | G118: =Time_M!G$9 -> counter | H118: =Time_M!H$9 -> 0 | I118: =Time_M!I$9 -> 0 | J118: =Time_M!J$9 -> 1 | K118: =Time_M!K$9 -> 2 | L118: =Time_M!L$9 -> 3 | ... EH118: =Time_M!EH$9 -> 129
E120: =Capex!E50 -> AMI Equipment Cost | G120: INR Cr | H120: =SUM(J120:EF120) -> 935.53938 | J120: {=$F91 * INDEX( $J109:$EH109, , MATCH( J$118 + $F100 - 1, $J$118:$EH$118, 0 ) )} -> 0 | K120: {=$F91 * INDEX( $J109:$EH109, , MATCH( K$118 + $F100 - 1, $J$118:$EH$118, 0 ) )} -> 0 | L120: {=$F91 * INDEX( $J109:$EH109, , MATCH( L$118 + $F100 - 1, $J$118:$EH$118, 0 ) )} -> 0 | M120: {=$F91 * INDEX( $J109:$EH109, , MATCH( M$118 + $F100 - 1, $J$118:$EH$118, 0 ) )} -> 0 | N120: {=$F91 * INDEX( $J109:$EH109, , MATCH( N$118 + $F100 - 1, $J$118:$EH$118, 0 ) )} -> 0 | O120: {=$F91 * INDEX( $J109:$EH109, , MATCH( O$118 + $F100 - 1, $J$118:$EH$118, 0 ) )} -> 0.07774 | P120: {=$F91 * INDEX( $J109:$EH109, , MATCH( P$118 + $F100 - 1, $J$118:$EH$118, 0 ) )} -> 5.368792 | Q120: {=$F91 * INDEX( $J109:$EH109, , MATCH( Q$118 + $F100 - 1, $J$118:$EH$118, 0 ) )} -> 11.2216 | ... EH120: {=$F91 * INDEX( $J109:$EH109, , MATCH( EH$118 + $F100 - 1, $J$118:$EH$118, 0 ) )} -> 0
E121: =Capex!E51 -> Corporate, Consumer Indexing & Training | G121: INR Cr | H121: =SUM(J121:EF121) -> 7.89881 | J121: {=$F92 * INDEX( $J110:$EH110, , MATCH( J$118 + $F101 - 1, $J$118:$EH$118, 0 ) )} -> 0 | K121: {=$F92 * INDEX( $J110:$EH110, , MATCH( K$118 + $F101 - 1, $J$118:$EH$118, 0 ) )} -> 0 | L121: {=$F92 * INDEX( $J110:$EH110, , MATCH( L$118 + $F101 - 1, $J$118:$EH$118, 0 ) )} -> 0 | M121: {=$F92 * INDEX( $J110:$EH110, , MATCH( M$118 + $F101 - 1, $J$118:$EH$118, 0 ) )} -> 0 | N121: {=$F92 * INDEX( $J110:$EH110, , MATCH( N$118 + $F101 - 1, $J$118:$EH$118, 0 ) )} -> 0 | O121: {=$F92 * INDEX( $J110:$EH110, , MATCH( O$118 + $F101 - 1, $J$118:$EH$118, 0 ) )} -> 0.00065636306 | P121: {=$F92 * INDEX( $J110:$EH110, , MATCH( P$118 + $F101 - 1, $J$118:$EH$118, 0 ) )} -> 0.045329003 | Q121: {=$F92 * INDEX( $J110:$EH110, , MATCH( Q$118 + $F101 - 1, $J$118:$EH$118, 0 ) )} -> 0.09474458 | ... EH121: {=$F92 * INDEX( $J110:$EH110, , MATCH( EH$118 + $F101 - 1, $J$118:$EH$118, 0 ) )} -> 0
E122: =Capex!E52 -> Advanced Metering Infrastructure (AMI) IT | G122: INR Cr | H122: =SUM(J122:EF122) -> 11.836221 | J122: {=$F93 * INDEX( $J111:$EH111, , MATCH( J$118 + $F102 - 1, $J$118:$EH$118, 0 ) )} -> 0 | K122: {=$F93 * INDEX( $J111:$EH111, , MATCH( K$118 + $F102 - 1, $J$118:$EH$118, 0 ) )} -> 0 | L122: {=$F93 * INDEX( $J111:$EH111, , MATCH( L$118 + $F102 - 1, $J$118:$EH$118, 0 ) )} -> 0 | M122: {=$F93 * INDEX( $J111:$EH111, , MATCH( M$118 + $F102 - 1, $J$118:$EH$118, 0 ) )} -> 0 | N122: {=$F93 * INDEX( $J111:$EH111, , MATCH( N$118 + $F102 - 1, $J$118:$EH$118, 0 ) )} -> 0 | O122: {=$F93 * INDEX( $J111:$EH111, , MATCH( O$118 + $F102 - 1, $J$118:$EH$118, 0 ) )} -> 0.00098354791 | P122: {=$F93 * INDEX( $J111:$EH111, , MATCH( P$118 + $F102 - 1, $J$118:$EH$118, 0 ) )} -> 0.067924674 | Q122: {=$F93 * INDEX( $J111:$EH111, , MATCH( Q$118 + $F102 - 1, $J$118:$EH$118, 0 ) )} -> 0.141973 | ... EH122: {=$F93 * INDEX( $J111:$EH111, , MATCH( EH$118 + $F102 - 1, $J$118:$EH$118, 0 ) )} -> 0
E123: =Capex!E53 -> Installation Charges | G123: INR Cr | H123: =SUM(J123:EF123) -> 79.394203 | J123: {=$F94 * INDEX( $J112:$EH112, , MATCH( J$118 + $F103 - 1, $J$118:$EH$118, 0 ) )} -> 0 | K123: {=$F94 * INDEX( $J112:$EH112, , MATCH( K$118 + $F103 - 1, $J$118:$EH$118, 0 ) )} -> 0 | L123: {=$F94 * INDEX( $J112:$EH112, , MATCH( L$118 + $F103 - 1, $J$118:$EH$118, 0 ) )} -> 0 | M123: {=$F94 * INDEX( $J112:$EH112, , MATCH( M$118 + $F103 - 1, $J$118:$EH$118, 0 ) )} -> 0 | N123: {=$F94 * INDEX( $J112:$EH112, , MATCH( N$118 + $F103 - 1, $J$118:$EH$118, 0 ) )} -> 0 | O123: {=$F94 * INDEX( $J112:$EH112, , MATCH( O$118 + $F103 - 1, $J$118:$EH$118, 0 ) )} -> 0.0065973763 | P123: {=$F94 * INDEX( $J112:$EH112, , MATCH( P$118 + $F103 - 1, $J$118:$EH$118, 0 ) )} -> 0.45562054 | Q123: {=$F94 * INDEX( $J112:$EH112, , MATCH( Q$118 + $F103 - 1, $J$118:$EH$118, 0 ) )} -> 0.95231693 | ... EH123: {=$F94 * INDEX( $J112:$EH112, , MATCH( EH$118 + $F103 - 1, $J$118:$EH$118, 0 ) )} -> 0
...

Sheet Monthly Financials
A1: =RIGHT(CELL("FILENAME", $A$1), LEN(CELL("FILENAME", $A$1)) - SEARCH("]", CELL("FILENAME", $A$1))) -> Monthly Financials
E2: =Time_M!E$18 -> Model period beginning_M | J2: =Time_M!J$18 -> 45323 | K2: =Time_M!K$18 -> 45352 | L2: =Time_M!L$18 -> 45383 | M2: =Time_M!M$18 -> 45413 | N2: =Time_M!N$18 -> 45444 | O2: =Time_M!O$18 -> 45474 | P2: =Time_M!P$18 -> 45505 | Q2: =Time_M!Q$18 -> 45536 | ... EH2: =Time_M!EH$18 -> 49218
E3: =Time_M!E$22 -> Model period ending_M | F3: =Check!E$10 -> Model Check | G3: =Check!F$10 -> 0 | H3: =Check!G$10 -> check | J3: =Time_M!J$22 -> 45351 | K3: =Time_M!K$22 -> 45382 | L3: =Time_M!L$22 -> 45412 | M3: =Time_M!M$22 -> 45443 | N3: =Time_M!N$22 -> 45473 | O3: =Time_M!O$22 -> 45504 | P3: =Time_M!P$22 -> 45535 | Q3: =Time_M!Q$22 -> 45565 | ... EH3: =Time_M!EH$22 -> 49248
E4: =Time_M!E$35 -> Financial year ending period_M | J4: =Time_M!J$35 -> 45382 | K4: =Time_M!K$35 -> 45382 | L4: =Time_M!L$35 -> 45747 | M4: =Time_M!M$35 -> 45747 | N4: =Time_M!N$35 -> 45747 | O4: =Time_M!O$35 -> 45747 | P4: =Time_M!P$35 -> 45747 | Q4: =Time_M!Q$35 -> 45747 | ... EH4: =Time_M!EH$35 -> 49399
E5: =Time_M!E$32 -> Financial year ending_M | F5: Constant | G5: Unit | H5: Total | J5: =Time_M!J$32 -> 2024 | K5: =Time_M!K$32 -> 2024 | L5: =Time_M!L$32 -> 2025 | M5: =Time_M!M$32 -> 2025 | N5: =Time_M!N$32 -> 2025 | O5: =Time_M!O$32 -> 2025 | P5: =Time_M!P$32 -> 2025 | Q5: =Time_M!Q$32 -> 2025 | ... EH5: =Time_M!EH$32 -> 2035
A7: REVENUE - MONTHLY
B9: Revenue (On Accounting Basis)
C10: Upfront payment - Discom
E11: =Rollout!E85 -> Payment from DISCOM (Upfront) | F11: =Rollout!F85 -> 0 | G11: =Rollout!G85 -> INR Cr | H11: =SUM(J11:EH11) -> 243.07592 | J11: =Rollout!J85 -> 0 | K11: =Rollout!K85 -> 0 | L11: =Rollout!L85 -> 0 | M11: =Rollout!M85 -> 0 | N11: =Rollout!N85 -> 0 | O11: =Rollout!O85 -> 0 | P11: =Rollout!P85 -> 0 | Q11: =Rollout!Q85 -> 0 | ... EH11: =Rollout!EH85 -> 0
E12: =Rollout!E86 -> Payment from DISCOM (Cable) | F12: =Rollout!F86 -> 0 | G12: =Rollout!G86 -> INR Cr | H12: =SUM(J12:EH12) -> 196.13901 | J12: =Rollout!J84 -> 0 | K12: =Rollout!K84 -> 0 | L12: =Rollout!L84 -> 0 | M12: =Rollout!M84 -> 0 | N12: =Rollout!N84 -> 0 | O12: =Rollout!O84 -> 0 | P12: =Rollout!P84 -> 0 | Q12: =Rollout!Q84 -> 3.4945304 | ... EH12: =Rollout!EH84 -> 0
E13: =Time_M!E88 -> Upfront flag | F13: =Time_M!F88 -> 0 | G13: =Time_M!G88 -> flag | H13: =Time_M!H88 -> 113 | J13: =Time_M!J88 -> 1 | K13: =Time_M!K88 -> 1 | L13: =Time_M!L88 -> 1 | M13: =Time_M!M88 -> 1 | N13: =Time_M!N88 -> 1 | O13: =Time_M!O88 -> 1 | P13: =Time_M!P88 -> 1 | Q13: =Time_M!Q88 -> 1 | ... EH13: =Time_M!EH88 -> 0
E14: Upfront Payment by DISCOM | G14: INR Cr | H14: =SUM(J14:EH14) -> 439.21492 | J14: =( J12+J11) * J13 -> 0 | K14: =( K12+K11) * K13 -> 0 | L14: =( L12+L11) * L13 -> 0 | M14: =( M12+M11) * M13 -> 0 | N14: =( N12+N11) * N13 -> 0 | O14: =( O12+O11) * O13 -> 0 | P14: =( P12+P11) * P13 -> 0 | Q14: =( Q12+Q11) * Q13 -> 3.4945304 | ... EH14: =( EH12+EH11) * EH13 -> 0
D16: Upfront payment ratio
E17: =Capex!E$72 -> Total capex | F17: =Capex!F$72 -> 1248.9083 | G17: =Capex!G$72 -> INR Cr
E18: =E$14 -> Upfront Payment by DISCOM | F18: =F$14 -> 0 | G18: =G$14 -> INR Cr | H18: =H$14 -> 439.21492 | J18: =J$14 -> 0 | K18: =K$14 -> 0 | L18: =L$14 -> 0 | M18: =M$14 -> 0 | N18: =N$14 -> 0 | O18: =O$14 -> 0 | P18: =P$14 -> 0 | Q18: =Q$14 -> 3.4945304 | ... EH18: =EH$14 -> 0
E19: Upfront payment ratio | F19: =H18 / $F$17 -> 0.35167908 | G19: ratio
C21: AMISP Service Charge on Meters Installed
E22: =NTBA!E$39 -> Qouted - Avg. Service Charge (PMPM) | F22: =NTBA!F$39 -> 79.560181 | G22: =NTBA!G$39 -> INR / meter / month
E23: =NTBA!E$302 -> Conversion to Crores | F23: =NTBA!F$302 -> 10000000 | G23: =NTBA!G$302 -> Crores
E24: =Rollout!E39 -> Effective Meters Operational and billed | F24: =Rollout!F39 -> 0 | G24: =Rollout!G39 -> Nos | H24: =Rollout!H39 -> 0 | I24: =Rollout!I39 -> 0 | J24: =Rollout!J39 -> 0 | K24: =Rollout!K39 -> 0 | L24: =Rollout!L39 -> 0 | ... EH24: =Rollout!EH39 -> 0
E25: =Time_M!E$88 -> Upfront flag | F25: =Time_M!F$88 -> 0 | G25: =Time_M!G$88 -> flag | H25: =Time_M!H$88 -> 113 | I25: =Time_M!I$88 -> 0 | J25: =Time_M!J$88 -> 1 | K25: =Time_M!K$88 -> 1 | L25: =Time_M!L$88 -> 1 | ... EH25: =Time_M!EH$88 -> 0
E26: AMISP Service Charge on Meters Installed | G26: INR Cr | H26: =SUM(J26:EH26) -> 2047.9723 | J26: =( $F22 * J24 / $F23 ) * J25 -> 0 | K26: =( $F22 * K24 / $F23 ) * K25 -> 0 | L26: =( $F22 * L24 / $F23 ) * L25 -> 0 | M26: =( $F22 * M24 / $F23 ) * M25 -> 0 | N26: =( $F22 * N24 / $F23 ) * N25 -> 0 | O26: =( $F22 * O24 / $F23 ) * O25 -> 0 | P26: =( $F22 * P24 / $F23 ) * P25 -> 0 | Q26: =( $F22 * Q24 / $F23 ) * Q25 -> 0 | ... EH26: =( $F22 * EH24 / $F23 ) * EH25 -> 0
C28: Revenue Summary
E29: =E11 -> Payment from DISCOM (Upfront) | F29: ='Monthly Financials'!F$14 -> 0 | G29: ='Monthly Financials'!G$14 -> INR Cr | H29: =SUM(J29:EH29) -> 243.07592 | I29: ='Monthly Financials'!I$14 -> 0 | J29: =J11 -> 0 | K29: =K11 -> 0 | L29: =L11 -> 0 | M29: =M11 -> 0 | N29: =N11 -> 0 | O29: =O11 -> 0 | P29: =P11 -> 0 | Q29: =Q11 -> 0 | ... EH29: =EH11 -> 0
E30: =E12 -> Payment from DISCOM (Cable) | F30: ='Monthly Financials'!F$14 -> 0 | G30: ='Monthly Financials'!G$14 -> INR Cr | H30: =SUM(J30:EH30) -> 196.13901 | I30: ='Monthly Financials'!I$14 -> 0 | J30: =J12 -> 0 | K30: =K12 -> 0 | L30: =L12 -> 0 | M30: =M12 -> 0 | N30: =N12 -> 0 | O30: =O12 -> 0 | P30: =P12 -> 0 | Q30: =Q12 -> 3.4945304 | ... EH30: =EH12 -> 0
E31: =E$26 -> AMISP Service Charge on Meters Installed | F31: =F$26 -> 0 | G31: =G$26 -> INR Cr | H31: =H$26 -> 2047.9723 | I31: =I$26 -> 0 | J31: =J$26 -> 0 | K31: =K$26 -> 0 | L31: =L$26 -> 0 | ... EH31: =EH$26 -> 0
E32: Total Revenue excl GST | G32: INR Cr | H32: =SUM(J32:EH32) -> 2487.1873 | J32: =SUM(J29:J31) -> 0 | K32: =SUM(K29:K31) -> 0 | L32: =SUM(L29:L31) -> 0 | M32: =SUM(M29:M31) -> 0 | N32: =SUM(N29:N31) -> 0 | O32: =SUM(O29:O31) -> 0 | P32: =SUM(P29:P31) -> 0 | Q32: =SUM(Q29:Q31) -> 3.4945304 | ... EH32: =SUM(EH29:EH31) -> 0
E34: =NTBA!E$40 -> GST on AMISP Service Charge (In %) | F34: =NTBA!F$40 -> 0.18 | G34: =NTBA!G$40 -> %
E35: =E$32 -> Total Revenue excl GST | F35: =F$32 -> 0 | G35: =G$32 -> INR Cr | H35: =H$32 -> 2487.1873 | I35: =I$32 -> 0 | J35: =J$32 -> 0 | K35: =K$32 -> 0 | L35: =L$32 -> 0 | ... EH35: =EH$32 -> 0
E36: GST on revenue | G36: INR Cr | H36: =SUM(J36:EH36) -> 447.69371 | I36: =I$32 -> 0 | J36: =$F34 * J35 -> 0 | K36: =$F34 * K35 -> 0 | L36: =$F34 * L35 -> 0 | M36: =$F34 * M35 -> 0 | N36: =$F34 * N35 -> 0 | O36: =$F34 * O35 -> 0 | P36: =$F34 * P35 -> 0 | Q36: =$F34 * Q35 -> 0.62901547 | ... EH36: =$F34 * EH35 -> 0
E38: ='Monthly Financials'!E$32 -> Total Revenue excl GST | F38: ='Monthly Financials'!F$32 -> 0 | G38: ='Monthly Financials'!G$32 -> INR Cr | H38: ='Monthly Financials'!H$32 -> 2487.1873 | I38: ='Monthly Financials'!I$32 -> 0 | J38: ='Monthly Financials'!J$32 -> 0 | K38: ='Monthly Financials'!K$32 -> 0 | L38: ='Monthly Financials'!L$32 -> 0 | ... EH38: ='Monthly Financials'!EH$32 -> 0
E39: ='Monthly Financials'!E$36 -> GST on revenue | F39: ='Monthly Financials'!F$36 -> 0 | G39: ='Monthly Financials'!G$36 -> INR Cr | H39: ='Monthly Financials'!H$36 -> 447.69371 | I39: ='Monthly Financials'!I$36 -> 0 | J39: ='Monthly Financials'!J$36 -> 0 | K39: ='Monthly Financials'!K$36 -> 0 | L39: ='Monthly Financials'!L$36 -> 0 | ... EH39: ='Monthly Financials'!EH$36 -> 0
E40: Total Revenue incl. GST (On Accounting Basis) | G40: INR Cr | H40: =SUM(J40:EH40) -> 2934.881 | J40: =SUM(J38:J39) -> 0 | K40: =SUM(K38:K39) -> 0 | L40: =SUM(L38:L39) -> 0 | M40: =SUM(M38:M39) -> 0 | N40: =SUM(N38:N39) -> 0 | O40: =SUM(O38:O39) -> 0 | P40: =SUM(P38:P39) -> 0 | Q40: =SUM(Q38:Q39) -> 4.1235459 | ... EH40: =SUM(EH38:EH39) -> 0
B42: Total Revenue (On Cash Basis)
C43: Upfront Payment by DISCOM
E44: =NTBA!E$48 -> First Payment | F44: =NTBA!F$48 -> 0 | G44: =NTBA!G$48 -> months
E45: =NTBA!E$43 -> First Payment | F45: =NTBA!F$43 -> 1 | G45: =NTBA!G$43 -> %
E46: =Time_M!E$9 -> Model column counter | F46: =Time_M!F$9 -> 0 | G46: =Time_M!G$9 -> counter | H46: =Time_M!H$107 -> 0 | I46: =Time_M!I$107 -> 0 | J46: =Time_M!J$9 -> 1 | K46: =Time_M!K$9 -> 2 | L46: =Time_M!L$9 -> 3 | M46: =Time_M!M$9 -> 4 | N46: =Time_M!N$9 -> 5 | O46: =Time_M!O$9 -> 6 | P46: =Time_M!P$9 -> 7 | Q46: =Time_M!Q$9 -> 8 | ... EH46: =Time_M!EH$9 -> 129
E47: =E11 -> Payment from DISCOM (Upfront) | F47: ='Monthly Financials'!F$14 -> 0 | G47: ='Monthly Financials'!G$14 -> INR Cr | H47: =SUM(J47:EH47) -> 243.07592 | J47: =J11 -> 0 | K47: =K11 -> 0 | L47: =L11 -> 0 | M47: =M11 -> 0 | N47: =N11 -> 0 | O47: =O11 -> 0 | P47: =P11 -> 0 | Q47: =Q11 -> 0 | ... EH47: =EH11 -> 0
E48: =E12 -> Payment from DISCOM (Cable) | F48: ='Monthly Financials'!F$14 -> 0 | G48: ='Monthly Financials'!G$14 -> INR Cr | H48: =SUM(J48:EH48) -> 196.13901 | I48: ='Monthly Financials'!I$14 -> 0 | J48: =J12 -> 0 | K48: =K12 -> 0 | L48: =L12 -> 0 | M48: =M12 -> 0 | N48: =N12 -> 0 | O48: =O12 -> 0 | P48: =P12 -> 0 | Q48: =Q12 -> 3.4945304 | ... EH48: =EH12 -> 0
E49: =E47 -> Payment from DISCOM (Upfront) | F49: ='Monthly Financials'!F$14 -> 0 | G49: INR Cr | H49: =SUM(J49:EH49) -> 243.07592 | J49: {=+_xlfn.IFNA(INDEX($J$47:$EH$47,,MATCH(J$46-$F$44,$J$46:$EH$46,)),)*0+IF(J3=EOMONTH(NTBA!$F$19,NTBA!$F$52),SUM('Monthly Financials'!$I$47:J47),0)} -> 0 | K49: {=+_xlfn.IFNA(INDEX($J$47:$EH$47,,MATCH(K$46-$F$44,$J$46:$EH$46,)),)*0+IF(K3=EOMONTH(NTBA!$F$19,NTBA!$F$52),SUM('Monthly Financials'!$I$47:K47),0)} -> 0 | L49: {=+_xlfn.IFNA(INDEX($J$47:$EH$47,,MATCH(L$46-$F$44,$J$46:$EH$46,)),)*0+IF(L3=EOMONTH(NTBA!$F$19,NTBA!$F$52),SUM('Monthly Financials'!$I$47:L47),0)} -> 0 | M49: {=+_xlfn.IFNA(INDEX($J$47:$EH$47,,MATCH(M$46-$F$44,$J$46:$EH$46,)),)*0+IF(M3=EOMONTH(NTBA!$F$19,NTBA!$F$52),SUM('Monthly Financials'!$I$47:M47),0)} -> 0 | N49: {=+_xlfn.IFNA(INDEX($J$47:$EH$47,,MATCH(N$46-$F$44,$J$46:$EH$46,)),)*0+IF(N3=EOMONTH(NTBA!$F$19,NTBA!$F$52),SUM('Monthly Financials'!$I$47:N47),0)} -> 0 | O49: {=+_xlfn.IFNA(INDEX($J$47:$EH$47,,MATCH(O$46-$F$44,$J$46:$EH$46,)),)*0+IF(O3=EOMONTH(NTBA!$F$19,NTBA!$F$52),SUM('Monthly Financials'!$I$47:O47),0)} -> 0 | P49: {=+_xlfn.IFNA(INDEX($J$47:$EH$47,,MATCH(P$46-$F$44,$J$46:$EH$46,)),)*0+IF(P3=EOMONTH(NTBA!$F$19,NTBA!$F$52),SUM('Monthly Financials'!$I$47:P47),0)} -> 0 | Q49: {=+_xlfn.IFNA(INDEX($J$47:$EH$47,,MATCH(Q$46-$F$44,$J$46:$EH$46,)),)*0+IF(Q3=EOMONTH(NTBA!$F$19,NTBA!$F$52),SUM('Monthly Financials'!$I$47:Q47),0)} -> 0 | ... EH49: {=+_xlfn.IFNA(INDEX($J$47:$EH$47,,MATCH(EH$46-$F$44,$J$46:$EH$46,)),)*0+IF(EH3=EOMONTH(NTBA!$F$19,NTBA!$F$52),SUM('Monthly Financials'!$I$47:EH47),0)} -> 0
E50: =E48 -> Payment from DISCOM (Cable) | F50: ='Monthly Financials'!F$14 -> 0 | G50: INR Cr | H50: =SUM(J50:EH50) -> 196.13901 | J50: {=_xlfn.IFNA(INDEX($J$48:$EH$48,,MATCH(J$46-$F$44,$J$46:$EH$46,)),)} -> 0 | K50: {=_xlfn.IFNA(INDEX($J$48:$EH$48,,MATCH(K$46-$F$44,$J$46:$EH$46,)),)} -> 0 | L50: {=_xlfn.IFNA(INDEX($J$48:$EH$48,,MATCH(L$46-$F$44,$J$46:$EH$46,)),)} -> 0 | M50: {=_xlfn.IFNA(INDEX($J$48:$EH$48,,MATCH(M$46-$F$44,$J$46:$EH$46,)),)} -> 0 | N50: {=_xlfn.IFNA(INDEX($J$48:$EH$48,,MATCH(N$46-$F$44,$J$46:$EH$46,)),)} -> 0 | O50: {=_xlfn.IFNA(INDEX($J$48:$EH$48,,MATCH(O$46-$F$44,$J$46:$EH$46,)),)} -> 0 | P50: {=_xlfn.IFNA(INDEX($J$48:$EH$48,,MATCH(P$46-$F$44,$J$46:$EH$46,)),)} -> 0 | Q50: {=_xlfn.IFNA(INDEX($J$48:$EH$48,,MATCH(Q$46-$F$44,$J$46:$EH$46,)),)} -> 3.4945304 | ... EH50: {=_xlfn.IFNA(INDEX($J$48:$EH$48,,MATCH(EH$46-$F$44,$J$46:$EH$46,)),)} -> 0
C52: AMISP Service Charge on Meters Installed
E53: =NTBA!E$48 -> First Payment | F53: =NTBA!F$48 -> 0 | G53: =NTBA!G$48 -> months
E54: =NTBA!E$49 -> Second Payment | F54: =NTBA!F$49 -> 0 | G54: =NTBA!G$49 -> months
E55: =NTBA!E$50 -> Final Payment | F55: =NTBA!F$50 -> 0 | G55: =NTBA!G$50 -> months
E57: =NTBA!E$43 -> First Payment | F57: =NTBA!F$43 -> 1 | G57: =NTBA!G$43 -> %
E58: =NTBA!E$44 -> Second Payment | F58: =NTBA!F$44 -> 0 | G58: =NTBA!G$44 -> %
E59: =NTBA!E$45 -> Final Payment | F59: =NTBA!F$45 -> 0 | G59: =NTBA!G$45 -> %
E61: =Time_M!E$9 -> Model column counter | F61: =Time_M!F$9 -> 0 | G61: =Time_M!G$9 -> counter | H61: =Time_M!H$107 -> 0 | I61: =Time_M!I$107 -> 0 | J61: =Time_M!J$9 -> 1 | K61: =Time_M!K$9 -> 2 | L61: =Time_M!L$9 -> 3 | M61: =Time_M!M$9 -> 4 | N61: =Time_M!N$9 -> 5 | O61: =Time_M!O$9 -> 6 | P61: =Time_M!P$9 -> 7 | Q61: =Time_M!Q$9 -> 8 | ... EH61: =Time_M!EH$9 -> 129
E62: ='Monthly Financials'!E$26 -> AMISP Service Charge on Meters Installed | F62: ='Monthly Financials'!F$26 -> 0 | G62: ='Monthly Financials'!G$26 -> INR Cr | H62: ='Monthly Financials'!H$26 -> 2047.9723 | I62: ='Monthly Financials'!I$26 -> 0 | J62: ='Monthly Financials'!J$26 -> 0 | K62: ='Monthly Financials'!K$26 -> 0 | L62: ='Monthly Financials'!L$26 -> 0 | ... EH62: ='Monthly Financials'!EH$26 -> 0
E63: First payment | G63: INR Cr | H63: =SUM(J63:EH63) -> 2047.9723 | J63: =_xlfn.IFNA(INDEX($J$62:$EH$62,,MATCH(J$61-$F53,$J$61:$EH$61,)),) -> 0 | K63: =_xlfn.IFNA(INDEX($J$62:$EH$62,,MATCH(K$61-$F53,$J$61:$EH$61,)),) -> 0 | L63: =_xlfn.IFNA(INDEX($J$62:$EH$62,,MATCH(L$61-$F53,$J$61:$EH$61,)),) -> 0 | M63: =_xlfn.IFNA(INDEX($J$62:$EH$62,,MATCH(M$61-$F53,$J$61:$EH$61,)),) -> 0 | N63: =_xlfn.IFNA(INDEX($J$62:$EH$62,,MATCH(N$61-$F53,$J$61:$EH$61,)),) -> 0 | O63: =_xlfn.IFNA(INDEX($J$62:$EH$62,,MATCH(O$61-$F53,$J$61:$EH$61,)),) -> 0 | P63: =_xlfn.IFNA(INDEX($J$62:$EH$62,,MATCH(P$61-$F53,$J$61:$EH$61,)),) -> 0 | Q63: =_xlfn.IFNA(INDEX($J$62:$EH$62,,MATCH(Q$61-$F53,$J$61:$EH$61,)),) -> 0 | ... EH63: =_xlfn.IFNA(INDEX($J$62:$EH$62,,MATCH(EH$61-$F53,$J$61:$EH$61,)),) -> 0
E64: Second Payment | G64: INR Cr | H64: =SUM(J64:EH64) -> 0 | J64: =IF( $F54, _xlfn.IFNA( INDEX($J$62:$EH$62, , MATCH(J$61 - $F54, $J$61:$EH$61,)),),) -> 0 | K64: =IF( $F54, _xlfn.IFNA( INDEX($J$62:$EH$62, , MATCH(K$61 - $F54, $J$61:$EH$61,)),),) -> 0 | L64: =IF( $F54, _xlfn.IFNA( INDEX($J$62:$EH$62, , MATCH(L$61 - $F54, $J$61:$EH$61,)),),) -> 0 | M64: =IF( $F54, _xlfn.IFNA( INDEX($J$62:$EH$62, , MATCH(M$61 - $F54, $J$61:$EH$61,)),),) -> 0 | N64: =IF( $F54, _xlfn.IFNA( INDEX($J$62:$EH$62, , MATCH(N$61 - $F54, $J$61:$EH$61,)),),) -> 0 | O64: =IF( $F54, _xlfn.IFNA( INDEX($J$62:$EH$62, , MATCH(O$61 - $F54, $J$61:$EH$61,)),),) -> 0 | P64: =IF( $F54, _xlfn.IFNA( INDEX($J$62:$EH$62, , MATCH(P$61 - $F54, $J$61:$EH$61,)),),) -> 0 | Q64: =IF( $F54, _xlfn.IFNA( INDEX($J$62:$EH$62, , MATCH(Q$61 - $F54, $J$61:$EH$61,)),),) -> 0 | ... EH64: =IF( $F54, _xlfn.IFNA( INDEX($J$62:$EH$62, , MATCH(EH$61 - $F54, $J$61:$EH$61,)),),) -> 0
E65: Final Payment | G65: INR Cr | H65: =SUM(J65:EH65) -> 0 | J65: =IF( $F55, _xlfn.IFNA( INDEX($J$62:$EH$62, , MATCH(J$61 - $F55, $J$61:$EH$61,)),),) -> 0 | K65: =IF( $F55, _xlfn.IFNA( INDEX($J$62:$EH$62, , MATCH(K$61 - $F55, $J$61:$EH$61,)),),) -> 0 | L65: =IF( $F55, _xlfn.IFNA( INDEX($J$62:$EH$62, , MATCH(L$61 - $F55, $J$61:$EH$61,)),),) -> 0 | M65: =IF( $F55, _xlfn.IFNA( INDEX($J$62:$EH$62, , MATCH(M$61 - $F55, $J$61:$EH$61,)),),) -> 0 | N65: =IF( $F55, _xlfn.IFNA( INDEX($J$62:$EH$62, , MATCH(N$61 - $F55, $J$61:$EH$61,)),),) -> 0 | O65: =IF( $F55, _xlfn.IFNA( INDEX($J$62:$EH$62, , MATCH(O$61 - $F55, $J$61:$EH$61,)),),) -> 0 | P65: =IF( $F55, _xlfn.IFNA( INDEX($J$62:$EH$62, , MATCH(P$61 - $F55, $J$61:$EH$61,)),),) -> 0 | Q65: =IF( $F55, _xlfn.IFNA( INDEX($J$62:$EH$62, , MATCH(Q$61 - $F55, $J$61:$EH$61,)),),) -> 0 | ... EH65: =IF( $F55, _xlfn.IFNA( INDEX($J$62:$EH$62, , MATCH(EH$61 - $F55, $J$61:$EH$61,)),),) -> 0
C67: Revenue Summary
E68: =E47 -> Payment from DISCOM (Upfront) | H68: =H$49 -> 243.07592 | J68: =J$49 -> 0 | K68: =K$49 -> 0 | L68: =L$49 -> 0 | M68: =M$49 -> 0 | N68: =N$49 -> 0 | O68: =O$49 -> 0 | P68: =P$49 -> 0 | Q68: =Q$49 -> 0 | ... EH68: =EH$49 -> 0
E69: =E$50 -> Payment from DISCOM (Cable) | F69: =F$50 -> 0 | G69: =G$50 -> INR Cr | H69: =H$50 -> 196.13901 | I69: =I$50 -> 0 | J69: =J$50 -> 0 | K69: =K$50 -> 0 | L69: =L$50 -> 0 | ... EH69: =EH$50 -> 0
E70: ='Monthly Financials'!E$63 -> First payment | F70: ='Monthly Financials'!F$63 -> 0 | G70: ='Monthly Financials'!G$63 -> INR Cr | H70: ='Monthly Financials'!H$63 -> 2047.9723 | I70: ='Monthly Financials'!I$63 -> 0 | J70: ='Monthly Financials'!J$63 -> 0 | K70: ='Monthly Financials'!K$63 -> 0 | L70: ='Monthly Financials'!L$63 -> 0 | ... EH70: ='Monthly Financials'!EH$63 -> 0
E71: ='Monthly Financials'!E$64 -> Second Payment | F71: ='Monthly Financials'!F$64 -> 0 | G71: ='Monthly Financials'!G$64 -> INR Cr | H71: ='Monthly Financials'!H$64 -> 0 | I71: ='Monthly Financials'!I$64 -> 0 | J71: ='Monthly Financials'!J$64 -> 0 | K71: ='Monthly Financials'!K$64 -> 0 | L71: ='Monthly Financials'!L$64 -> 0 | ... EH71: ='Monthly Financials'!EH$64 -> 0
E72: ='Monthly Financials'!E$65 -> Final Payment | F72: ='Monthly Financials'!F$65 -> 0 | G72: ='Monthly Financials'!G$65 -> INR Cr | H72: ='Monthly Financials'!H$65 -> 0 | I72: ='Monthly Financials'!I$65 -> 0 | J72: ='Monthly Financials'!J$65 -> 0 | K72: ='Monthly Financials'!K$65 -> 0 | L72: ='Monthly Financials'!L$65 -> 0 | ... EH72: ='Monthly Financials'!EH$65 -> 0
E73: Total Revenue excl. GST (On Cash Basis) | G73: INR Cr | H73: =SUM(J73:EH73) -> 2487.1873 | J73: =SUM(J68:J72) -> 0 | K73: =SUM(K68:K72) -> 0 | L73: =SUM(L68:L72) -> 0 | M73: =SUM(M68:M72) -> 0 | N73: =SUM(N68:N72) -> 0 | O73: =SUM(O68:O72) -> 0 | P73: =SUM(P68:P72) -> 0 | Q73: =SUM(Q68:Q72) -> 3.4945304 | ... EH73: =SUM(EH68:EH72) -> 0
E75: =NTBA!E$40 -> GST on AMISP Service Charge (In %) | F75: =NTBA!F$40 -> 0.18 | G75: =NTBA!G$40 -> %
E76: =E$73 -> Total Revenue excl. GST (On Cash Basis) | F76: =F$73 -> 0 | G76: =G$73 -> INR Cr | H76: =H$73 -> 2487.1873 | I76: =I$73 -> 0 | J76: =J$73 -> 0 | K76: =K$73 -> 0 | L76: =L$73 -> 0 | ... EH76: =EH$73 -> 0
E77: GST on revenue | G77: INR Cr | H77: =SUM(J77:EH77) -> 447.69371 | J77: =$F75 * J76 -> 0 | K77: =$F75 * K76 -> 0 | L77: =$F75 * L76 -> 0 | M77: =$F75 * M76 -> 0 | N77: =$F75 * N76 -> 0 | O77: =$F75 * O76 -> 0 | P77: =$F75 * P76 -> 0 | Q77: =$F75 * Q76 -> 0.62901547 | ... EH77: =$F75 * EH76 -> 0
E79: ='Monthly Financials'!E$73 -> Total Revenue excl. GST (On Cash Basis) | F79: ='Monthly Financials'!F$73 -> 0 | G79: ='Monthly Financials'!G$73 -> INR Cr | H79: ='Monthly Financials'!H$73 -> 2487.1873 | I79: ='Monthly Financials'!I$73 -> 0 | J79: ='Monthly Financials'!J$73 -> 0 | K79: ='Monthly Financials'!K$73 -> 0 | L79: ='Monthly Financials'!L$73 -> 0 | ... EH79: ='Monthly Financials'!EH$73 -> 0
E80: ='Monthly Financials'!E$77 -> GST on revenue | F80: ='Monthly Financials'!F$77 -> 0 | G80: ='Monthly Financials'!G$77 -> INR Cr | H80: ='Monthly Financials'!H$77 -> 447.69371 | I80: ='Monthly Financials'!I$77 -> 0 | J80: ='Monthly Financials'!J$77 -> 0 | K80: ='Monthly Financials'!K$77 -> 0 | L80: ='Monthly Financials'!L$77 -> 0 | ... EH80: ='Monthly Financials'!EH$77 -> 0
E81: Total Revenue incl. GST (On Cash Basis) | G81: INR Cr | H81: =SUM(J81:EH81) -> 2934.881 | J81: =SUM(J79:J80) -> 0 | K81: =SUM(K79:K80) -> 0 | L81: =SUM(L79:L80) -> 0 | M81: =SUM(M79:M80) -> 0 | N81: =SUM(N79:N80) -> 0 | O81: =SUM(O79:O80) -> 0 | P81: =SUM(P79:P80) -> 0 | Q81: =SUM(Q79:Q80) -> 4.1235459 | ... EH81: =SUM(EH79:EH80) -> 0
A84: OPEX - MONTHLY
B86: Total Opex (On Accounting Basis)
E87: Opex Prior to Installation Milestone
E88: =NTBA!E$96 -> O & M/ FMS + PMC Charges + MDM Charges | F88: =NTBA!F$96 -> 4.05 | G88: =NTBA!G$96 -> INR / meter / month
E89: =NTBA!E$97 -> ATS Charges on Softwares | F89: =NTBA!F$97 -> 2.45 | G89: =NTBA!G$97 -> INR / meter / month
E90: =NTBA!E$98 -> Cloud Hosting Charges | F90: =NTBA!F$98 -> 2.8 | G90: =NTBA!G$98 -> INR / meter / month
E91: =NTBA!E$99 -> GPRS Charges for GPRS Meters | F91: =NTBA!F$99 -> 6.101 | G91: =NTBA!G$99 -> INR / meter / month
E92: =NTBA!E$100 -> Site Mandays Cost | F92: =NTBA!F$100 -> 0.778 | G92: =NTBA!G$100 -> INR Cr / month
E93: =NTBA!E$101 -> Site Running+Auditor+Training Cost | F93: =NTBA!F$101 -> 0.283 | G93: =NTBA!G$101 -> INR Cr / month
E94: =NTBA!E$102 -> Travel Cost | F94: =NTBA!F$102 -> 0.098 | G94: =NTBA!G$102 -> INR Cr / month
E95: =NTBA!E$103 -> BG, Insurance Cost & Fin. Compliance Cost | F95: =NTBA!F$103 -> 0.305 | G95: =NTBA!G$103 -> INR Cr / month
E96: Cable Cost | F96: =NTBA!F$104 -> 685.89 | G96: INR/ meter
E97: =NTBA!E105 -> Penalty - SLA | F97: =NTBA!F105 -> 0.02 | G97: =NTBA!G105 -> % of revenue
E99: Opex Post Installation Milestone
E100: =NTBA!E$96 -> O & M/ FMS + PMC Charges + MDM Charges | F100: =NTBA!F109 -> 4.05 | G100: =NTBA!G$96 -> INR / meter / month
E101: =NTBA!E$97 -> ATS Charges on Softwares | F101: =NTBA!F110 -> 2.45 | G101: =NTBA!G$97 -> INR / meter / month
E102: =NTBA!E$98 -> Cloud Hosting Charges | F102: =NTBA!F111 -> 2.8 | G102: =NTBA!G$98 -> INR / meter / month
E103: =NTBA!E$99 -> GPRS Charges for GPRS Meters | F103: =NTBA!F112 -> 6.101 | G103: =NTBA!G$99 -> INR / meter / month
E104: =NTBA!E$100 -> Site Mandays Cost | F104: =NTBA!F113 -> 0.778 | G104: =NTBA!G$100 -> INR Cr / month
E105: =NTBA!E$101 -> Site Running+Auditor+Training Cost | F105: =NTBA!F114 -> 0.283 | G105: =NTBA!G$101 -> INR Cr / month
E106: =NTBA!E$102 -> Travel Cost | F106: =NTBA!F115 -> 0.098 | G106: =NTBA!G$102 -> INR Cr / month
E107: =NTBA!E$103 -> BG, Insurance Cost & Fin. Compliance Cost | F107: =NTBA!F116 -> 0.305 | G107: =NTBA!G$103 -> INR Cr / month
E108: =E96 -> Cable Cost | F108: =NTBA!F117 -> 0 | G108: INR/ meter
E109: =NTBA!E118 -> Penalty - SLA | F109: =NTBA!F118 -> 0.005 | G109: =G97 -> % of revenue
E111: =NTBA!E$120 -> Escalation/ Discount on Opex | F111: =NTBA!F$120 -> 0 | G111: =NTBA!G$120 -> %
E112: =NTBA!E$121 -> Escalation on IT related expenses | F112: =NTBA!F$121 -> 0 | G112: =NTBA!G$120 -> %
E113: =NTBA!E$302 -> Conversion to Crores | F113: =NTBA!F$302 -> 10000000 | G113: =NTBA!G$302 -> Crores
E114: =NTBA!E$303 -> Months in Year | F114: =NTBA!F$303 -> 12 | G114: =NTBA!G$303 -> Months
E115: =Time_M!E$65 -> Implementation Month Counter | F115: =Time_M!F$65 -> 0 | G115: =Time_M!G$65 -> counter | H115: =Time_M!H$65 -> 0 | I115: =Time_M!I$65 -> 0 | J115: =Time_M!J$65 -> 0 | K115: =Time_M!K$65 -> 0 | L115: =Time_M!L$65 -> 0 | ... EH115: =Time_M!EH$65 -> 124
E116: Effective Meters Operational and billed | G116: Nos | H116: =SUM(J116:EH116) -> 257428068 | J116: =SUMIF(Rollout!$J$3:$EH$3,'Monthly Financials'!J3,Rollout!$J$37:$EH$37) -> 0 | K116: =SUMIF(Rollout!$J$3:$EH$3,'Monthly Financials'!K3,Rollout!$J$37:$EH$37) -> 0 | L116: =SUMIF(Rollout!$J$3:$EH$3,'Monthly Financials'!L3,Rollout!$J$37:$EH$37) -> 0 | M116: =SUMIF(Rollout!$J$3:$EH$3,'Monthly Financials'!M3,Rollout!$J$37:$EH$37) -> 0 | N116: =SUMIF(Rollout!$J$3:$EH$3,'Monthly Financials'!N3,Rollout!$J$37:$EH$37) -> 0 | O116: =SUMIF(Rollout!$J$3:$EH$3,'Monthly Financials'!O3,Rollout!$J$37:$EH$37) -> 0 | P116: =SUMIF(Rollout!$J$3:$EH$3,'Monthly Financials'!P3,Rollout!$J$37:$EH$37) -> 0 | Q116: =SUMIF(Rollout!$J$3:$EH$3,'Monthly Financials'!Q3,Rollout!$J$37:$EH$37) -> 230 | ... EH116: =SUMIF(Rollout!$J$3:$EH$3,'Monthly Financials'!EH3,Rollout!$J$37:$EH$37) -> 0
E117: =Rollout!E$38 -> Effective Meters Operational for Opex cost | F117: =Rollout!F$38 -> 0 | G117: =Rollout!G$38 -> Nos | H117: =Rollout!H$38 -> 0 | I117: =Rollout!I$38 -> 0 | J117: =Rollout!J$38 -> 0 | K117: =Rollout!K$38 -> 0 | L117: =Rollout!L$38 -> 0 | ... EH117: =Rollout!EH$38 -> 0
E119: ='Monthly Financials'!E88 -> O & M/ FMS + PMC Charges + MDM Charges | G119: INR Cr | H119: =SUM(J119:EF119) -> 104.67748 | J119: =IF(J$3<=NTBA!$F$25,IF(J$3<=NTBA!$F$19,'Monthly Financials'!$F88*(J$117/$F$113)*(1+$F$112/$F$114)^J$115,IF(J$3>NTBA!$F$19,'Monthly Financials'!$F100*(J$117/$F$113)*(1+$F$112/$F$114)^J$115,0)),0) -> 0 | K119: =IF(K$3<=NTBA!$F$25,IF(K$3<=NTBA!$F$19,'Monthly Financials'!$F88*(K$117/$F$113)*(1+$F$112/$F$114)^K$115,IF(K$3>NTBA!$F$19,'Monthly Financials'!$F100*(K$117/$F$113)*(1+$F$112/$F$114)^K$115,0)),0) -> 0 | L119: =IF(L$3<=NTBA!$F$25,IF(L$3<=NTBA!$F$19,'Monthly Financials'!$F88*(L$117/$F$113)*(1+$F$112/$F$114)^L$115,IF(L$3>NTBA!$F$19,'Monthly Financials'!$F100*(L$117/$F$113)*(1+$F$112/$F$114)^L$115,0)),0) -> 0 | M119: =IF(M$3<=NTBA!$F$25,IF(M$3<=NTBA!$F$19,'Monthly Financials'!$F88*(M$117/$F$113)*(1+$F$112/$F$114)^M$115,IF(M$3>NTBA!$F$19,'Monthly Financials'!$F100*(M$117/$F$113)*(1+$F$112/$F$114)^M$115,0)),0) -> 0 | N119: =IF(N$3<=NTBA!$F$25,IF(N$3<=NTBA!$F$19,'Monthly Financials'!$F88*(N$117/$F$113)*(1+$F$112/$F$114)^N$115,IF(N$3>NTBA!$F$19,'Monthly Financials'!$F100*(N$117/$F$113)*(1+$F$112/$F$114)^N$115,0)),0) -> 0 | O119: =IF(O$3<=NTBA!$F$25,IF(O$3<=NTBA!$F$19,'Monthly Financials'!$F88*(O$117/$F$113)*(1+$F$112/$F$114)^O$115,IF(O$3>NTBA!$F$19,'Monthly Financials'!$F100*(O$117/$F$113)*(1+$F$112/$F$114)^O$115,0)),0) -> 0 | P119: =IF(P$3<=NTBA!$F$25,IF(P$3<=NTBA!$F$19,'Monthly Financials'!$F88*(P$117/$F$113)*(1+$F$112/$F$114)^P$115,IF(P$3>NTBA!$F$19,'Monthly Financials'!$F100*(P$117/$F$113)*(1+$F$112/$F$114)^P$115,0)),0) -> 0 | Q119: =IF(Q$3<=NTBA!$F$25,IF(Q$3<=NTBA!$F$19,'Monthly Financials'!$F88*(Q$117/$F$113)*(1+$F$112/$F$114)^Q$115,IF(Q$3>NTBA!$F$19,'Monthly Financials'!$F100*(Q$117/$F$113)*(1+$F$112/$F$114)^Q$115,0)),0) -> 9.315e-05 | ... EH119: =IF(EH$3<=NTBA!$F$25,IF(EH$3<=NTBA!$F$19,'Monthly Financials'!$F88*(EH$117/$F$113)*(1+$F$112/$F$114)^EH$115,IF(EH$3>NTBA!$F$19,'Monthly Financials'!$F100*(EH$117/$F$113)*(1+$F$112/$F$114)^EH$115,0)),0) -> 0
E120: ='Monthly Financials'!E89 -> ATS Charges on Softwares | G120: INR Cr | H120: =SUM(J120:EF120) -> 63.323413 | J120: =IF(J$3<=NTBA!$F$25,IF(J$3<=NTBA!$F$19,'Monthly Financials'!$F89*(J$117/$F$113)*(1+$F$112/$F$114)^J$115,IF(J$3>NTBA!$F$19,'Monthly Financials'!$F101*(J$117/$F$113)*(1+$F$112/$F$114)^J$115,0)),0) -> 0 | K120: =IF(K$3<=NTBA!$F$25,IF(K$3<=NTBA!$F$19,'Monthly Financials'!$F89*(K$117/$F$113)*(1+$F$112/$F$114)^K$115,IF(K$3>NTBA!$F$19,'Monthly Financials'!$F101*(K$117/$F$113)*(1+$F$112/$F$114)^K$115,0)),0) -> 0 | L120: =IF(L$3<=NTBA!$F$25,IF(L$3<=NTBA!$F$19,'Monthly Financials'!$F89*(L$117/$F$113)*(1+$F$112/$F$114)^L$115,IF(L$3>NTBA!$F$19,'Monthly Financials'!$F101*(L$117/$F$113)*(1+$F$112/$F$114)^L$115,0)),0) -> 0 | M120: =IF(M$3<=NTBA!$F$25,IF(M$3<=NTBA!$F$19,'Monthly Financials'!$F89*(M$117/$F$113)*(1+$F$112/$F$114)^M$115,IF(M$3>NTBA!$F$19,'Monthly Financials'!$F101*(M$117/$F$113)*(1+$F$112/$F$114)^M$115,0)),0) -> 0 | N120: =IF(N$3<=NTBA!$F$25,IF(N$3<=NTBA!$F$19,'Monthly Financials'!$F89*(N$117/$F$113)*(1+$F$112/$F$114)^N$115,IF(N$3>NTBA!$F$19,'Monthly Financials'!$F101*(N$117/$F$113)*(1+$F$112/$F$114)^N$115,0)),0) -> 0 | O120: =IF(O$3<=NTBA!$F$25,IF(O$3<=NTBA!$F$19,'Monthly Financials'!$F89*(O$117/$F$113)*(1+$F$112/$F$114)^O$115,IF(O$3>NTBA!$F$19,'Monthly Financials'!$F101*(O$117/$F$113)*(1+$F$112/$F$114)^O$115,0)),0) -> 0 | P120: =IF(P$3<=NTBA!$F$25,IF(P$3<=NTBA!$F$19,'Monthly Financials'!$F89*(P$117/$F$113)*(1+$F$112/$F$114)^P$115,IF(P$3>NTBA!$F$19,'Monthly Financials'!$F101*(P$117/$F$113)*(1+$F$112/$F$114)^P$115,0)),0) -> 0 | Q120: =IF(Q$3<=NTBA!$F$25,IF(Q$3<=NTBA!$F$19,'Monthly Financials'!$F89*(Q$117/$F$113)*(1+$F$112/$F$114)^Q$115,IF(Q$3>NTBA!$F$19,'Monthly Financials'!$F101*(Q$117/$F$113)*(1+$F$112/$F$114)^Q$115,0)),0) -> 5.635e-05 | ... EH120: =IF(EH$3<=NTBA!$F$25,IF(EH$3<=NTBA!$F$19,'Monthly Financials'!$F89*(EH$117/$F$113)*(1+$F$112/$F$114)^EH$115,IF(EH$3>NTBA!$F$19,'Monthly Financials'!$F101*(EH$117/$F$113)*(1+$F$112/$F$114)^EH$115,0)),0) -> 0
...

Sheet Ind AS Monthly
A1: =RIGHT(CELL("FILENAME", $A$1), LEN(CELL("FILENAME", $A$1)) - SEARCH("]", CELL("FILENAME", $A$1))) -> Ind AS Monthly
E2: =Time_M!E$18 -> Model period beginning_M | J2: =Time_M!J$18 -> 45323 | K2: =Time_M!K$18 -> 45352 | L2: =Time_M!L$18 -> 45383 | M2: =Time_M!M$18 -> 45413 | N2: =Time_M!N$18 -> 45444 | O2: =Time_M!O$18 -> 45474 | P2: =Time_M!P$18 -> 45505 | Q2: =Time_M!Q$18 -> 45536 | ... EH2: =Time_M!EH$18 -> 49218
E3: =Time_M!E$22 -> Model period ending_M | F3: =Check!E$10 -> Model Check | G3: =Check!F$10 -> 0 | H3: =Check!G$10 -> check | J3: =Time_M!J$22 -> 45351 | K3: =Time_M!K$22 -> 45382 | L3: =Time_M!L$22 -> 45412 | M3: =Time_M!M$22 -> 45443 | N3: =Time_M!N$22 -> 45473 | O3: =Time_M!O$22 -> 45504 | P3: =Time_M!P$22 -> 45535 | Q3: =Time_M!Q$22 -> 45565 | ... EH3: =Time_M!EH$22 -> 49248
E4: =Time_M!E$35 -> Financial year ending period_M | J4: =Time_M!J$35 -> 45382 | K4: =Time_M!K$35 -> 45382 | L4: =Time_M!L$35 -> 45747 | M4: =Time_M!M$35 -> 45747 | N4: =Time_M!N$35 -> 45747 | O4: =Time_M!O$35 -> 45747 | P4: =Time_M!P$35 -> 45747 | Q4: =Time_M!Q$35 -> 45747 | ... EH4: =Time_M!EH$35 -> 49399
E5: =Time_M!E$32 -> Financial year ending_M | F5: Constant | G5: Unit | H5: Total | J5: =Time_M!J$32 -> 2024 | K5: =Time_M!K$32 -> 2024 | L5: =Time_M!L$32 -> 2025 | M5: =Time_M!M$32 -> 2025 | N5: =Time_M!N$32 -> 2025 | O5: =Time_M!O$32 -> 2025 | P5: =Time_M!P$32 -> 2025 | Q5: =Time_M!Q$32 -> 2025 | ... EH5: =Time_M!EH$32 -> 2035
A7: FINANCIAL LEASE
E9: Financial Lease Receivable | G9: INR Cr | H9: =SUM(J9:EH9) -> 995.9323 | J9: {=TRANSPOSE($H$50:$H$178 )} -> 0 | K9: 0 | L9: 0 | M9: 0 | N9: 0 | O9: 0 | P9: 0 | Q9: 0.09038629 | R9: 6.2038709 | S9: 12.886405 | T9: 30.084378 | U9: 33.724302 | V9: 33.505582 | W9: 33.285175 | X9: 40.577404 | Y9: 48.512532 | Z9: 57.444603 | AA9: 65.508913 | AB9: 74.912115 | AC9: 79.123903 | AD9: 55.824693 | AE9: 55.411882 | AF9: 54.995888 | AG9: 54.576687 | AH9: 54.154256 | AI9: 53.728568 | AJ9: 53.299599 | AK9: 52.867323 | AL9: 45.213839 | AM9: 0 | AN9: 0 | AO9: 0 | AP9: 0 | AQ9: 0 | AR9: 0 | AS9: 0 | AT9: 0 | AU9: 0 | AV9: 0 | AW9: 0 | AX9: 0 | AY9: 0 | AZ9: 0 | BA9: 0 | BB9: 0 | BC9: 0 | BD9: 0 | BE9: 0 | BF9: 0 | BG9: 0 | BH9: 0 | BI9: 0 | BJ9: 0 | BK9: 0 | BL9: 0 | BM9: 0 | BN9: 0 | BO9: 0 | BP9: 0 | BQ9: 0 | BR9: 0 | BS9: 0 | BT9: 0 | BU9: 0 | BV9: 0 | BW9: 0 | BX9: 0 | BY9: 0 | BZ9: 0 | CA9: 0 | CB9: 0 | CC9: 0 | CD9: 0 | CE9: 0 | CF9: 0 | CG9: 0 | CH9: 0 | CI9: 0 | CJ9: 0 | CK9: 0 | CL9: 0 | CM9: 0 | CN9: 0 | CO9: 0 | CP9: 0 | CQ9: 0 | CR9: 0 | CS9: 0 | CT9: 0 | CU9: 0 | CV9: 0 | CW9: 0 | CX9: 0 | CY9: 0 | CZ9: 0 | DA9: 0 | DB9: 0 | DC9: 0 | DD9: 0 | DE9: 0 | DF9: 0 | DG9: 0 | DH9: 0 | DI9: 0 | DJ9: 0 | DK9: 0 | DL9: 0 | DM9: 0 | DN9: 0 | DO9: 0 | DP9: 0 | DQ9: 0 | DR9: 0 | DS9: 0 | DT9: 0 | DU9: 0 | DV9: 0 | DW9: 0 | DX9: 0 | DY9: 0 | DZ9: 0 | EA9: 0 | EB9: 0 | EC9: 0 | ED9: 0 | EE9: 0 | EF9: 0 | EG9: 0 | EH9: 0
B11: Financial Lease Receivable (FLR) balance
E12: Financial Lease Receivable (FLR) balance BEG | G12: INR Cr | J12: =I16 -> 0 | K12: =J16 -> 0 | L12: =K16 -> 0 | M12: =L16 -> 0 | N12: =M16 -> 0 | O12: =N16 -> 0 | P12: =O16 -> 0 | Q12: =P16 -> 0 | ... EH12: =EG16 -> -9.5933176e-12
E13: Add: FLR | G13: INR Cr | H13: =SUM(J13:EH13) -> 995.9323 | J13: =J9 -> 0 | K13: =K9 -> 0 | L13: =L9 -> 0 | M13: =M9 -> 0 | N13: =N9 -> 0 | O13: =O9 -> 0 | P13: =P9 -> 0 | Q13: =Q9 -> 0.09038629 | ... EH13: =EH9 -> 0
E14: =E$21 -> Interest on FLR | G14: =G$21 -> INR Cr | H14: =H$21 -> 393.55559 | J14: =J$21 -> 0 | K14: =K$21 -> 0 | L14: =L$21 -> 0 | M14: =M$21 -> 0 | N14: =N$21 -> 0 | O14: =O$21 -> 0 | P14: =P$21 -> 0 | Q14: =Q$21 -> 0 | ... EH14: =EH$21 -> -7.394849e-14
E15: Less: Payment Received | G15: INR Cr | H15: =SUM(J15:EH15) -> 1389.4879 | J15: =J179 -> 0 | K15: =K179 -> 0 | L15: =L179 -> 0 | M15: =M179 -> 0 | N15: =N179 -> 0 | O15: =O179 -> 0 | P15: =P179 -> 0 | Q15: =Q179 -> 0.0012415216 | ... EH15: =EH179 -> 0
E16: Financial Lease Receivable (FLR) balance | G16: INR Cr | J16: =J12 + J13 + J14 - J15 -> 0 | K16: =K12 + K13 + K14 - K15 -> 0 | L16: =L12 + L13 + L14 - L15 -> 0 | M16: =M12 + M13 + M14 - M15 -> 0 | N16: =N12 + N13 + N14 - N15 -> 0 | O16: =O12 + O13 + O14 - O15 -> 0 | P16: =P12 + P13 + P14 - P15 -> 0 | Q16: =Q12 + Q13 + Q14 - Q15 -> 0.089144768 | ... EH16: =EH12 + EH13 + EH14 - EH15 -> -9.6672661e-12
C18: Interest on FLR
E19: =NTBA!E$287 -> Discounting Factor | F19: =NTBA!F$287 -> 0.0925 | G19: =NTBA!G$287 -> %
E20: =E$12 -> Financial Lease Receivable (FLR) balance BEG | F20: =F$12 -> 0 | G20: =G$12 -> INR Cr | H20: =H$12 -> 0 | J20: =J$12 -> 0 | K20: =K$12 -> 0 | L20: =L$12 -> 0 | M20: =M$12 -> 0 | N20: =N$12 -> 0 | O20: =O$12 -> 0 | P20: =P$12 -> 0 | Q20: =Q$12 -> 0 | ... EH20: =EH$12 -> -9.5933176e-12
E21: Interest on FLR | G21: INR Cr | H21: =SUM(J21:EH21) -> 393.55559 | J21: =J20 * $F$19 / months -> 0 | K21: =K20 * $F$19 / months -> 0 | L21: =L20 * $F$19 / months -> 0 | M21: =M20 * $F$19 / months -> 0 | N21: =N20 * $F$19 / months -> 0 | O21: =O20 * $F$19 / months -> 0 | P21: =P20 * $F$19 / months -> 0 | Q21: =Q20 * $F$19 / months -> 0 | ... EH21: =EH20 * $F$19 / months -> -7.394849e-14
E23: =NTBA!E$286 -> IRR | F23: =NTBA!F$286 -> 0.14 | G23: =NTBA!G$286 -> %
E24: Opex Cost | F24: =(SUM('Ind AS Financials'!$H$15:$H$22 )/NTBA!F85)*10^7/NTBA!$F$34 -> 21.549396 | G24: INR
E25: Tax | F25: =NTBA!$F$279 -> 0.25168 | G25: %
E26: Opex Revenue | F26: =F24 * ( 1 + $F$23 /( 1 - $F$25 )) -> 25.580981 | G26: INR
E27: =Rollout!E39 -> Effective Meters Operational and billed | F27: =Rollout!F39 -> 0 | G27: =Rollout!G39 -> Nos | H27: =Rollout!H39 -> 0 | J27: =Rollout!J39 -> 0 | K27: =Rollout!K39 -> 0 | L27: =Rollout!L39 -> 0 | M27: =Rollout!M39 -> 0 | N27: =Rollout!N39 -> 0 | O27: =Rollout!O39 -> 0 | P27: =Rollout!P39 -> 0 | Q27: =Rollout!Q39 -> 0 | ... EH27: =Rollout!EH39 -> 0
E28: Opex Revenue | G28: INR Cr | H28: =SUM(J28:EH28) -> 658.48444 | J28: =$F$26 * J27 / Cr -> 0 | K28: =$F$26 * K27 / Cr -> 0 | L28: =$F$26 * L27 / Cr -> 0 | M28: =$F$26 * M27 / Cr -> 0 | N28: =$F$26 * N27 / Cr -> 0 | O28: =$F$26 * O27 / Cr -> 0 | P28: =$F$26 * P27 / Cr -> 0 | Q28: =$F$26 * Q27 / Cr -> 0 | ... EH28: =$F$26 * EH27 / Cr -> 0
E30: ='Monthly Financials'!E29 -> Payment from DISCOM (Upfront) | G30: INR Cr | H30: =SUM(J30:EH30) -> 243.07592 | J30: ='Monthly Financials'!J29 -> 0 | K30: ='Monthly Financials'!K29 -> 0 | L30: ='Monthly Financials'!L29 -> 0 | M30: ='Monthly Financials'!M29 -> 0 | N30: ='Monthly Financials'!N29 -> 0 | O30: ='Monthly Financials'!O29 -> 0 | P30: ='Monthly Financials'!P29 -> 0 | Q30: ='Monthly Financials'!Q29 -> 0 | ... EH30: ='Monthly Financials'!EH29 -> 0
E31: ='Monthly Financials'!E30 -> Payment from DISCOM (Cable) | G31: INR Cr | H31: =SUM(J31:EH31) -> 196.13901 | J31: ='Monthly Financials'!J30 -> 0 | K31: ='Monthly Financials'!K30 -> 0 | L31: ='Monthly Financials'!L30 -> 0 | M31: ='Monthly Financials'!M30 -> 0 | N31: ='Monthly Financials'!N30 -> 0 | O31: ='Monthly Financials'!O30 -> 0 | P31: ='Monthly Financials'!P30 -> 0 | Q31: ='Monthly Financials'!Q30 -> 3.4945304 | ... EH31: ='Monthly Financials'!EH30 -> 0
E32: Cost Recognition | G32: INR Cr | H32: =SUM(J32:EH32) -> 1058.3969 | J32: =SUMIF(Rollout!$J$3:$EH$3,EOMONTH('Ind AS Monthly'!J3,-NTBA!$F$188),Rollout!$J$130:$EH$130) -> 0 | K32: =SUMIF(Rollout!$J$3:$EH$3,EOMONTH('Ind AS Monthly'!K3,-NTBA!$F$188),Rollout!$J$130:$EH$130) -> 0 | L32: =SUMIF(Rollout!$J$3:$EH$3,EOMONTH('Ind AS Monthly'!L3,-NTBA!$F$188),Rollout!$J$130:$EH$130) -> 0 | M32: =SUMIF(Rollout!$J$3:$EH$3,EOMONTH('Ind AS Monthly'!M3,-NTBA!$F$188),Rollout!$J$130:$EH$130) -> 0 | N32: =SUMIF(Rollout!$J$3:$EH$3,EOMONTH('Ind AS Monthly'!N3,-NTBA!$F$188),Rollout!$J$130:$EH$130) -> 0 | O32: =SUMIF(Rollout!$J$3:$EH$3,EOMONTH('Ind AS Monthly'!O3,-NTBA!$F$188),Rollout!$J$130:$EH$130) -> 0 | P32: =SUMIF(Rollout!$J$3:$EH$3,EOMONTH('Ind AS Monthly'!P3,-NTBA!$F$188),Rollout!$J$130:$EH$130) -> 0 | Q32: =SUMIF(Rollout!$J$3:$EH$3,EOMONTH('Ind AS Monthly'!Q3,-NTBA!$F$188),Rollout!$J$130:$EH$130) -> 7.1110864 | ... EH32: =SUMIF(Rollout!$J$3:$EH$3,EOMONTH('Ind AS Monthly'!EH3,-NTBA!$F$188),Rollout!$J$130:$EH$130) -> 0
A35: INDAS ACCOUNTING
E37: ='Ind AS Monthly'!E$26 -> Opex Revenue | F37: ='Ind AS Monthly'!F$26 -> 25.580981 | G37: INR
E38: Capex Revenue | F38: =NTBA!F39 -'Ind AS Monthly'!F37 -> 53.9792 | G38: INR
E39: Total Capex Revenue other than upfront payment | F39: =F37 + F38 -> 79.560181 | G39: INR
E40: Accounting Check | F40: =SUM( G50:G178 ) - F38 * NTBA!$F$35 / Cr -> 0 | G40: check | J40: =SUM(J50:J178) -> 0 | K40: =SUM(K50:K178) -> 0 | L40: =SUM(L50:L178) -> 0 | M40: =SUM(M50:M178) -> 0 | N40: =SUM(N50:N178) -> 0 | O40: =SUM(O50:O178) -> 0 | P40: =SUM(P50:P178) -> 0 | Q40: =SUM(Q50:Q178) -> 0.0012415216 | ... EH40: =SUM(EH50:EH178) -> 0
E42: =NTBA!E$287 -> Discounting Factor | F42: =NTBA!F$287 -> 0.0925 | G42: =NTBA!G$287 -> %
E43: Month Counter | G43: counter | J43: 0 | K43: =J43 +1 -> 1 | L43: =K43 +1 -> 2 | M43: =L43 +1 -> 3 | N43: =M43 +1 -> 4 | O43: =N43 +1 -> 5 | P43: =O43+1 -> 6 | Q43: =P43+1 -> 7 | R43: =Q43+1 -> 8 | S43: =R43+1 -> 9 | T43: =S43+1 -> 10 | U43: =T43+1 -> 11 | V43: =U43+1 -> 12 | W43: =V43+1 -> 13 | ... EM43: =EL43+1 -> 133
E44: Monthly Discounting Factor | G44: factor | J44: =1/( 1 + $F$42 / months)^J43 -> 1 | K44: =1/( 1 + $F$42 / months)^K43 -> 0.99235063 | L44: =1/( 1 + $F$42 / months)^L43 -> 0.98475977 | M44: =1/( 1 + $F$42 / months)^M43 -> 0.97722698 | N44: =1/( 1 + $F$42 / months)^N43 -> 0.96975181 | O44: =1/( 1 + $F$42 / months)^O43 -> 0.96233382 | P44: =1/( 1 + $F$42 / months)^P43 -> 0.95497258 | Q44: =1/( 1 + $F$42 / months)^Q43 -> 0.94766764 | ... EH44: =1/( 1 + $F$42 / months)^EH43 -> 0.37423052 | EI44: =1/(1+$F$42/12)^EI43 -> 0.37136789 | EJ44: =1/(1+$F$42/12)^EJ43 -> 0.36852716 | EK44: =1/(1+$F$42/12)^EK43 -> 0.36570816 | EL44: =1/(1+$F$42/12)^EL43 -> 0.36291072 | EM44: =1/(1+$F$42/12)^EM43 -> 0.36013468
E45: =Rollout!E$19 -> Total smart energy meters installed | F45: =Rollout!F$19 -> 0 | G45: =Rollout!G$19 -> Nos | H45: =Rollout!H$19 -> 2767868 | J45: =Rollout!J23 -> 0 | K45: =Rollout!K23 -> 0 | L45: =Rollout!L23 -> 0 | M45: =Rollout!M23 -> 0 | N45: =Rollout!N23 -> 0 | O45: =Rollout!O23 -> 0 | P45: =Rollout!P23 -> 0 | Q45: =Rollout!Q23 -> 230 | ... EH45: =Rollout!EH23 -> 0 | EI45: =Rollout!ED19 -> 0 | EJ45: =Rollout!EE19 -> 0 | EK45: =Rollout!EF19 -> 0 | EL45: =Rollout!EG19 -> 0 | EM45: =Rollout!EH19 -> 0
E46: =Time_M!E$88 -> Upfront flag | F46: =Time_M!F$88 -> 0 | G46: =Time_M!G$88 -> flag | H46: =Time_M!H$88 -> 113 | I46: =Time_M!I$88 -> 0 | J46: =Time_M!J$88 -> 1 | K46: =Time_M!K$88 -> 1 | L46: =Time_M!L$88 -> 1 | ... EH46: =Time_M!EH$88 -> 0
E47: =Time_M!E$9 -> Model column counter | F47: =Time_M!F$9 -> 0 | G47: =Time_M!G$9 -> counter | H47: =Time_M!H$9 -> 0 | I47: =Time_M!I$9 -> 0 | J47: =Time_M!J$9 -> 1 | K47: =Time_M!K$9 -> 2 | L47: =Time_M!L$9 -> 3 | ... EH47: =Time_M!EH$9 -> 129
E49: Month | F49: Smart meters installed | G49: Capex Revenue | H49: NPV of Capex Revenue
E50: {=TRANSPOSE(J47:EH47)} -> 1 | F50: {=TRANSPOSE(J45:EH45)} -> 0 | G50: =SUM(J50:EM50) -> 0 | H50: =SUMPRODUCT(M50:EK50,J$44:EH$44) -> 0 | J50: =IF( J$47 >= $E50, $F50 * $F$38 / Cr,) * J$46 -> 0 | K50: =IF( K$47 >= $E50, $F50 * $F$38 / Cr,) * K$46 -> 0 | L50: =IF( L$47 >= $E50, $F50 * $F$38 / Cr,) * L$46 -> 0 | M50: =IF( M$47 >= $E50, $F50 * $F$38 / Cr,) * M$46 -> 0 | N50: =IF( N$47 >= $E50, $F50 * $F$38 / Cr,) * N$46 -> 0 | O50: =IF( O$47 >= $E50, $F50 * $F$38 / Cr,) * O$46 -> 0 | P50: =IF( P$47 >= $E50, $F50 * $F$38 / Cr,) * P$46 -> 0 | Q50: =IF( Q$47 >= $E50, $F50 * $F$38 / Cr,) * Q$46 -> 0 | ... EH50: =IF( EH$47 >= $E50, $F50 * $F$38 / Cr,) * EH$46 -> 0 | EI50: =IF(ED$3<=NTBA!$F$25,$O$45*$F$38/10^7,0) -> 0 | EJ50: =IF(EE$3<=NTBA!$F$25,$O$45*$F$38/10^7,0) -> 0 | EK50: =IF(EF$3<=NTBA!$F$25,$O$45*$F$38/10^7,0) -> 0 | EL50: =IF(EG$3<=NTBA!$F$25,$O$45*$F$38/10^7,0) -> 0 | EM50: =IF(EH$3<=NTBA!$F$25,$O$45*$F$38/10^7,0) -> 0
E51: 2 | F51: 0 | G51: =SUM(J51:EM51) -> 0 | H51: =SUMPRODUCT(M51:EK51,J$44:EH$44) -> 0 | J51: =IF( J$47 >= $E51, $F51 * $F$38 / Cr,) * J$46 -> 0 | K51: =IF( K$47 >= $E51, $F51 * $F$38 / Cr,) * K$46 -> 0 | L51: =IF( L$47 >= $E51, $F51 * $F$38 / Cr,) * L$46 -> 0 | M51: =IF( M$47 >= $E51, $F51 * $F$38 / Cr,) * M$46 -> 0 | N51: =IF( N$47 >= $E51, $F51 * $F$38 / Cr,) * N$46 -> 0 | O51: =IF( O$47 >= $E51, $F51 * $F$38 / Cr,) * O$46 -> 0 | P51: =IF( P$47 >= $E51, $F51 * $F$38 / Cr,) * P$46 -> 0 | Q51: =IF( Q$47 >= $E51, $F51 * $F$38 / Cr,) * Q$46 -> 0 | ... EH51: =IF( EH$47 >= $E51, $F51 * $F$38 / Cr,) * EH$46 -> 0 | EI51: =IF(ED$3<=NTBA!$F$25,$P$45*$F$38/10^7,0) -> 0 | EJ51: =IF(EE$3<=NTBA!$F$25,$P$45*$F$38/10^7,0) -> 0 | EK51: =IF(EF$3<=NTBA!$F$25,$P$45*$F$38/10^7,0) -> 0 | EL51: =IF(EG$3<=NTBA!$F$25,$P$45*$F$38/10^7,0) -> 0 | EM51: =IF(EH$3<=NTBA!$F$25,$P$45*$F$38/10^7,0) -> 0
E52: 3 | F52: 0 | G52: =SUM(J52:EM52) -> 0 | H52: =SUMPRODUCT(M52:EK52,J$44:EH$44) -> 0 | J52: =IF( J$47 >= $E52, $F52 * $F$38 / Cr,) * J$46 -> 0 | K52: =IF( K$47 >= $E52, $F52 * $F$38 / Cr,) * K$46 -> 0 | L52: =IF( L$47 >= $E52, $F52 * $F$38 / Cr,) * L$46 -> 0 | M52: =IF( M$47 >= $E52, $F52 * $F$38 / Cr,) * M$46 -> 0 | N52: =IF( N$47 >= $E52, $F52 * $F$38 / Cr,) * N$46 -> 0 | O52: =IF( O$47 >= $E52, $F52 * $F$38 / Cr,) * O$46 -> 0 | P52: =IF( P$47 >= $E52, $F52 * $F$38 / Cr,) * P$46 -> 0 | Q52: =IF( Q$47 >= $E52, $F52 * $F$38 / Cr,) * Q$46 -> 0 | ... EH52: =IF( EH$47 >= $E52, $F52 * $F$38 / Cr,) * EH$46 -> 0 | EI52: =IF(ED3<=NTBA!$F$25,$Q$45*$F$38/10^7,0) -> 0 | EJ52: =IF(EE3<=NTBA!$F$25,$Q$45*$F$38/10^7,0) -> 0 | EK52: =IF(EF3<=NTBA!$F$25,$Q$45*$F$38/10^7,0) -> 0 | EL52: =IF(EG3<=NTBA!$F$25,$Q$45*$F$38/10^7,0) -> 0 | EM52: =IF(EH3<=NTBA!$F$25,$Q$45*$F$38/10^7,0) -> 0
E53: 4 | F53: 0 | G53: =SUM(J53:EM53) -> 0 | H53: =SUMPRODUCT(M53:EK53,J$44:EH$44) -> 0 | J53: =IF( J$47 >= $E53, $F53 * $F$38 / Cr,) * J$46 -> 0 | K53: =IF( K$47 >= $E53, $F53 * $F$38 / Cr,) * K$46 -> 0 | L53: =IF( L$47 >= $E53, $F53 * $F$38 / Cr,) * L$46 -> 0 | M53: =IF( M$47 >= $E53, $F53 * $F$38 / Cr,) * M$46 -> 0 | N53: =IF( N$47 >= $E53, $F53 * $F$38 / Cr,) * N$46 -> 0 | O53: =IF( O$47 >= $E53, $F53 * $F$38 / Cr,) * O$46 -> 0 | P53: =IF( P$47 >= $E53, $F53 * $F$38 / Cr,) * P$46 -> 0 | Q53: =IF( Q$47 >= $E53, $F53 * $F$38 / Cr,) * Q$46 -> 0 | ... EH53: =IF( EH$47 >= $E53, $F53 * $F$38 / Cr,) * EH$46 -> 0 | EI53: =IF(ED3<=NTBA!$F$25,$R$45*$F$38/10^7,0) -> 0 | EJ53: =IF(EE3<=NTBA!$F$25,$R$45*$F$38/10^7,0) -> 0 | EK53: =IF(EF3<=NTBA!$F$25,$R$45*$F$38/10^7,0) -> 0 | EL53: =IF(EG3<=NTBA!$F$25,$R$45*$F$38/10^7,0) -> 0 | EM53: =IF(EH3<=NTBA!$F$25,$R$45*$F$38/10^7,0) -> 0
E54: 5 | F54: 0 | G54: =SUM(J54:EM54) -> 0 | H54: =SUMPRODUCT(N54:EL54,J$44:EH$44) -> 0 | J54: =IF( J$47 >= $E54, $F54 * $F$38 / Cr,) * J$46 -> 0 | K54: =IF( K$47 >= $E54, $F54 * $F$38 / Cr,) * K$46 -> 0 | L54: =IF( L$47 >= $E54, $F54 * $F$38 / Cr,) * L$46 -> 0 | M54: =IF( M$47 >= $E54, $F54 * $F$38 / Cr,) * M$46 -> 0 | N54: =IF( N$47 >= $E54, $F54 * $F$38 / Cr,) * N$46 -> 0 | O54: =IF( O$47 >= $E54, $F54 * $F$38 / Cr,) * O$46 -> 0 | P54: =IF( P$47 >= $E54, $F54 * $F$38 / Cr,) * P$46 -> 0 | Q54: =IF( Q$47 >= $E54, $F54 * $F$38 / Cr,) * Q$46 -> 0 | ... EH54: =IF( EH$47 >= $E54, $F54 * $F$38 / Cr,) * EH$46 -> 0 | EI54: =IF(ED3<=NTBA!$F$25,$S$45*$F$38/10^7,0) -> 0 | EJ54: =IF(EE3<=NTBA!$F$25,$S$45*$F$38/10^7,0) -> 0 | EK54: =IF(EF3<=NTBA!$F$25,$S$45*$F$38/10^7,0) -> 0 | EL54: =IF(EG3<=NTBA!$F$25,$S$45*$F$38/10^7,0) -> 0 | EM54: =IF(EH3<=NTBA!$F$25,$S$45*$F$38/10^7,0) -> 0
E55: 6 | F55: 0 | G55: =SUM(J55:EM55) -> 0 | H55: =SUMPRODUCT(O55:EM55,J$44:EH$44) -> 0 | J55: =IF( J$47 >= $E55, $F55 * $F$38 / Cr,) * J$46 -> 0 | K55: =IF( K$47 >= $E55, $F55 * $F$38 / Cr,) * K$46 -> 0 | L55: =IF( L$47 >= $E55, $F55 * $F$38 / Cr,) * L$46 -> 0 | M55: =IF( M$47 >= $E55, $F55 * $F$38 / Cr,) * M$46 -> 0 | N55: =IF( N$47 >= $E55, $F55 * $F$38 / Cr,) * N$46 -> 0 | O55: =IF( O$47 >= $E55, $F55 * $F$38 / Cr,) * O$46 -> 0 | P55: =IF( P$47 >= $E55, $F55 * $F$38 / Cr,) * P$46 -> 0 | Q55: =IF( Q$47 >= $E55, $F55 * $F$38 / Cr,) * Q$46 -> 0 | ... EH55: =IF( EH$47 >= $E55, $F55 * $F$38 / Cr,) * EH$46 -> 0 | EI55: =IF(ED3<=NTBA!$F$25,$T$45*$F$38/10^7,0) -> 0 | EJ55: =IF(EE3<=NTBA!$F$25,$T$45*$F$38/10^7,0) -> 0 | EK55: =IF(EF3<=NTBA!$F$25,$T$45*$F$38/10^7,0) -> 0 | EL55: =IF(EG3<=NTBA!$F$25,$T$45*$F$38/10^7,0) -> 0 | EM55: =IF(EH3<=NTBA!$F$25,$T$45*$F$38/10^7,0) -> 0
E56: 7 | F56: 0 | G56: =SUM(J56:EM56) -> 0 | H56: =SUMPRODUCT(P56:EN56,J$44:EH$44) -> 0 | J56: =IF( J$47 >= $E56, $F56 * $F$38 / Cr,) * J$46 -> 0 | K56: =IF( K$47 >= $E56, $F56 * $F$38 / Cr,) * K$46 -> 0 | L56: =IF( L$47 >= $E56, $F56 * $F$38 / Cr,) * L$46 -> 0 | M56: =IF( M$47 >= $E56, $F56 * $F$38 / Cr,) * M$46 -> 0 | N56: =IF( N$47 >= $E56, $F56 * $F$38 / Cr,) * N$46 -> 0 | O56: =IF( O$47 >= $E56, $F56 * $F$38 / Cr,) * O$46 -> 0 | P56: =IF( P$47 >= $E56, $F56 * $F$38 / Cr,) * P$46 -> 0 | Q56: =IF( Q$47 >= $E56, $F56 * $F$38 / Cr,) * Q$46 -> 0 | ... EH56: =IF( EH$47 >= $E56, $F56 * $F$38 / Cr,) * EH$46 -> 0 | EI56: =IF(ED$3<=NTBA!$F$25,$U$45*$F$38/10^7,0) -> 0 | EJ56: =IF(EE$3<=NTBA!$F$25,$U$45*$F$38/10^7,0) -> 0 | EK56: =IF(EF$3<=NTBA!$F$25,$U$45*$F$38/10^7,0) -> 0 | EL56: =IF(EG$3<=NTBA!$F$25,$U$45*$F$38/10^7,0) -> 0 | EM56: =IF(EH$3<=NTBA!$F$25,$U$45*$F$38/10^7,0) -> 0
E57: 8 | F57: 230 | G57: =SUM(J57:EM57) -> 0.13160129 | H57: =SUMPRODUCT(Q57:EO57,J$44:EH$44) -> 0.09038629 | J57: =IF( J$47 >= $E57, $F57 * $F$38 / Cr,) * J$46 -> 0 | K57: =IF( K$47 >= $E57, $F57 * $F$38 / Cr,) * K$46 -> 0 | L57: =IF( L$47 >= $E57, $F57 * $F$38 / Cr,) * L$46 -> 0 | M57: =IF( M$47 >= $E57, $F57 * $F$38 / Cr,) * M$46 -> 0 | N57: =IF( N$47 >= $E57, $F57 * $F$38 / Cr,) * N$46 -> 0 | O57: =IF( O$47 >= $E57, $F57 * $F$38 / Cr,) * O$46 -> 0 | P57: =IF( P$47 >= $E57, $F57 * $F$38 / Cr,) * P$46 -> 0 | Q57: =IF( Q$47 >= $E57, $F57 * $F$38 / Cr,) * Q$46 -> 0.0012415216 | ... EH57: =IF( EH$47 >= $E57, $F57 * $F$38 / Cr,) * EH$46 -> 0 | EI57: =IF(ED$3<=NTBA!$F$25,$V$45*$F$38/10^7,0) -> 0 | EJ57: =IF(EE$3<=NTBA!$F$25,$V$45*$F$38/10^7,0) -> 0 | EK57: =IF(EF$3<=NTBA!$F$25,$V$45*$F$38/10^7,0) -> 0 | EL57: =IF(EG$3<=NTBA!$F$25,$V$45*$F$38/10^7,0) -> 0 | EM57: =IF(EH$3<=NTBA!$F$25,$V$45*$F$38/10^7,0) -> 0
E58: 9 | F58: 15884 | G58: =SUM(J58:EM58) -> 9.0027589 | H58: =SUMPRODUCT(R58:EP58,J$44:EH$44) -> 6.2038709 | J58: =IF( J$47 >= $E58, $F58 * $F$38 / Cr,) * J$46 -> 0 | K58: =IF( K$47 >= $E58, $F58 * $F$38 / Cr,) * K$46 -> 0 | L58: =IF( L$47 >= $E58, $F58 * $F$38 / Cr,) * L$46 -> 0 | M58: =IF( M$47 >= $E58, $F58 * $F$38 / Cr,) * M$46 -> 0 | N58: =IF( N$47 >= $E58, $F58 * $F$38 / Cr,) * N$46 -> 0 | O58: =IF( O$47 >= $E58, $F58 * $F$38 / Cr,) * O$46 -> 0 | P58: =IF( P$47 >= $E58, $F58 * $F$38 / Cr,) * P$46 -> 0 | Q58: =IF( Q$47 >= $E58, $F58 * $F$38 / Cr,) * Q$46 -> 0 | ... EH58: =IF( EH$47 >= $E58, $F58 * $F$38 / Cr,) * EH$46 -> 0 | EI58: =IF(ED$3<=NTBA!$F$25,$W$45*$F$38/10^7,0) -> 0 | EJ58: =IF(EE$3<=NTBA!$F$25,$W$45*$F$38/10^7,0) -> 0 | EK58: =IF(EF$3<=NTBA!$F$25,$W$45*$F$38/10^7,0) -> 0 | EL58: =IF(EG$3<=NTBA!$F$25,$W$45*$F$38/10^7,0) -> 0 | EM58: =IF(EH$3<=NTBA!$F$25,$W$45*$F$38/10^7,0) -> 0
E59: 10 | F59: 33200 | G59: =SUM(J59:EM59) -> 18.637938 | H59: =SUMPRODUCT(S59:EQ59,J$44:EH$44) -> 12.886405 | J59: =IF( J$47 >= $E59, $F59 * $F$38 / Cr,) * J$46 -> 0 | K59: =IF( K$47 >= $E59, $F59 * $F$38 / Cr,) * K$46 -> 0 | L59: =IF( L$47 >= $E59, $F59 * $F$38 / Cr,) * L$46 -> 0 | M59: =IF( M$47 >= $E59, $F59 * $F$38 / Cr,) * M$46 -> 0 | N59: =IF( N$47 >= $E59, $F59 * $F$38 / Cr,) * N$46 -> 0 | O59: =IF( O$47 >= $E59, $F59 * $F$38 / Cr,) * O$46 -> 0 | P59: =IF( P$47 >= $E59, $F59 * $F$38 / Cr,) * P$46 -> 0 | Q59: =IF( Q$47 >= $E59, $F59 * $F$38 / Cr,) * Q$46 -> 0 | ... EH59: =IF( EH$47 >= $E59, $F59 * $F$38 / Cr,) * EH$46 -> 0 | EI59: =IF(ED$3<=NTBA!$F$25,$X$45*$F$38/10^7,0) -> 0 | EJ59: =IF(EE$3<=NTBA!$F$25,$X$45*$F$38/10^7,0) -> 0 | EK59: =IF(EF$3<=NTBA!$F$25,$X$45*$F$38/10^7,0) -> 0 | EL59: =IF(EG$3<=NTBA!$F$25,$X$45*$F$38/10^7,0) -> 0 | EM59: =IF(EH$3<=NTBA!$F$25,$X$45*$F$38/10^7,0) -> 0
E60: 11 | F60: 78000 | G60: =SUM(J60:EM60) -> 43.366889 | H60: =SUMPRODUCT(T60:ER60,J$44:EH$44) -> 30.084378 | J60: =IF( J$47 >= $E60, $F60 * $F$38 / Cr,) * J$46 -> 0 | K60: =IF( K$47 >= $E60, $F60 * $F$38 / Cr,) * K$46 -> 0 | L60: =IF( L$47 >= $E60, $F60 * $F$38 / Cr,) * L$46 -> 0 | M60: =IF( M$47 >= $E60, $F60 * $F$38 / Cr,) * M$46 -> 0 | N60: =IF( N$47 >= $E60, $F60 * $F$38 / Cr,) * N$46 -> 0 | O60: =IF( O$47 >= $E60, $F60 * $F$38 / Cr,) * O$46 -> 0 | P60: =IF( P$47 >= $E60, $F60 * $F$38 / Cr,) * P$46 -> 0 | Q60: =IF( Q$47 >= $E60, $F60 * $F$38 / Cr,) * Q$46 -> 0 | ... EH60: =IF( EH$47 >= $E60, $F60 * $F$38 / Cr,) * EH$46 -> 0 | EI60: =IF(ED$3<=NTBA!$F$25,$Y$45*$F$38/10^7,0) -> 0 | EJ60: =IF(EE$3<=NTBA!$F$25,$Y$45*$F$38/10^7,0) -> 0 | EK60: =IF(EF$3<=NTBA!$F$25,$Y$45*$F$38/10^7,0) -> 0 | EL60: =IF(EG$3<=NTBA!$F$25,$Y$45*$F$38/10^7,0) -> 0 | EM60: =IF(EH$3<=NTBA!$F$25,$Y$45*$F$38/10^7,0) -> 0
E61: 12 | F61: 88000 | G61: =SUM(J61:EM61) -> 48.45173 | H61: =SUMPRODUCT(U61:ES61,J$44:EH$44) -> 33.724302 | J61: =IF( J$47 >= $E61, $F61 * $F$38 / Cr,) * J$46 -> 0 | K61: =IF( K$47 >= $E61, $F61 * $F$38 / Cr,) * K$46 -> 0 | L61: =IF( L$47 >= $E61, $F61 * $F$38 / Cr,) * L$46 -> 0 | M61: =IF( M$47 >= $E61, $F61 * $F$38 / Cr,) * M$46 -> 0 | N61: =IF( N$47 >= $E61, $F61 * $F$38 / Cr,) * N$46 -> 0 | O61: =IF( O$47 >= $E61, $F61 * $F$38 / Cr,) * O$46 -> 0 | P61: =IF( P$47 >= $E61, $F61 * $F$38 / Cr,) * P$46 -> 0 | Q61: =IF( Q$47 >= $E61, $F61 * $F$38 / Cr,) * Q$46 -> 0 | ... EH61: =IF( EH$47 >= $E61, $F61 * $F$38 / Cr,) * EH$46 -> 0 | EI61: =IF(ED$3<=NTBA!$F$25,$Z$45*$F$38/10^7,0) -> 0 | EJ61: =IF(EE$3<=NTBA!$F$25,$Z$45*$F$38/10^7,0) -> 0 | EK61: =IF(EF$3<=NTBA!$F$25,$Z$45*$F$38/10^7,0) -> 0 | EL61: =IF(EG$3<=NTBA!$F$25,$Z$45*$F$38/10^7,0) -> 0 | EM61: =IF(EH$3<=NTBA!$F$25,$Z$45*$F$38/10^7,0) -> 0
E62: 13 | F62: 88000 | G62: =SUM(J62:EM62) -> 47.976713 | H62: =SUMPRODUCT(V62:ET62,J$44:EH$44) -> 33.505582 | J62: =IF( J$47 >= $E62, $F62 * $F$38 / Cr,) * J$46 -> 0 | K62: =IF( K$47 >= $E62, $F62 * $F$38 / Cr,) * K$46 -> 0 | L62: =IF( L$47 >= $E62, $F62 * $F$38 / Cr,) * L$46 -> 0 | M62: =IF( M$47 >= $E62, $F62 * $F$38 / Cr,) * M$46 -> 0 | N62: =IF( N$47 >= $E62, $F62 * $F$38 / Cr,) * N$46 -> 0 | O62: =IF( O$47 >= $E62, $F62 * $F$38 / Cr,) * O$46 -> 0 | P62: =IF( P$47 >= $E62, $F62 * $F$38 / Cr,) * P$46 -> 0 | Q62: =IF( Q$47 >= $E62, $F62 * $F$38 / Cr,) * Q$46 -> 0 | ... EH62: =IF( EH$47 >= $E62, $F62 * $F$38 / Cr,) * EH$46 -> 0 | EI62: =IF(ED$3<=NTBA!$F$25,$AA$45*$F$38/10^7,0) -> 0 | EJ62: =IF(EE$3<=NTBA!$F$25,$AA$45*$F$38/10^7,0) -> 0 | EK62: =IF(EF$3<=NTBA!$F$25,$AA$45*$F$38/10^7,0) -> 0 | EL62: =IF(EG$3<=NTBA!$F$25,$AA$45*$F$38/10^7,0) -> 0 | EM62: =IF(EH$3<=NTBA!$F$25,$AA$45*$F$38/10^7,0) -> 0
E63: 14 | F63: 88000 | G63: =SUM(J63:EM63) -> 47.501696 | H63: =SUMPRODUCT(W63:EU63,J$44:EH$44) -> 33.285175 | J63: =IF( J$47 >= $E63, $F63 * $F$38 / Cr,) * J$46 -> 0 | K63: =IF( K$47 >= $E63, $F63 * $F$38 / Cr,) * K$46 -> 0 | L63: =IF( L$47 >= $E63, $F63 * $F$38 / Cr,) * L$46 -> 0 | M63: =IF( M$47 >= $E63, $F63 * $F$38 / Cr,) * M$46 -> 0 | N63: =IF( N$47 >= $E63, $F63 * $F$38 / Cr,) * N$46 -> 0 | O63: =IF( O$47 >= $E63, $F63 * $F$38 / Cr,) * O$46 -> 0 | P63: =IF( P$47 >= $E63, $F63 * $F$38 / Cr,) * P$46 -> 0 | Q63: =IF( Q$47 >= $E63, $F63 * $F$38 / Cr,) * Q$46 -> 0 | ... EH63: =IF( EH$47 >= $E63, $F63 * $F$38 / Cr,) * EH$46 -> 0 | EI63: =IF(ED$3<=NTBA!$F$25,$AB$45*$F$38/10^7,0) -> 0 | EJ63: =IF(EE$3<=NTBA!$F$25,$AB$45*$F$38/10^7,0) -> 0 | EK63: =IF(EF$3<=NTBA!$F$25,$AB$45*$F$38/10^7,0) -> 0 | EL63: =IF(EG$3<=NTBA!$F$25,$AB$45*$F$38/10^7,0) -> 0 | EM63: =IF(EH$3<=NTBA!$F$25,$AB$45*$F$38/10^7,0) -> 0
E64: 15 | F64: 108000 | G64: =SUM(J64:EM64) -> 57.714561 | H64: =SUMPRODUCT(X64:EV64,J$44:EH$44) -> 40.577404 | J64: =IF( J$47 >= $E64, $F64 * $F$38 / Cr,) * J$46 -> 0 | K64: =IF( K$47 >= $E64, $F64 * $F$38 / Cr,) * K$46 -> 0 | L64: =IF( L$47 >= $E64, $F64 * $F$38 / Cr,) * L$46 -> 0 | M64: =IF( M$47 >= $E64, $F64 * $F$38 / Cr,) * M$46 -> 0 | N64: =IF( N$47 >= $E64, $F64 * $F$38 / Cr,) * N$46 -> 0 | O64: =IF( O$47 >= $E64, $F64 * $F$38 / Cr,) * O$46 -> 0 | P64: =IF( P$47 >= $E64, $F64 * $F$38 / Cr,) * P$46 -> 0 | Q64: =IF( Q$47 >= $E64, $F64 * $F$38 / Cr,) * Q$46 -> 0 | ... EH64: =IF( EH$47 >= $E64, $F64 * $F$38 / Cr,) * EH$46 -> 0 | EI64: =IF(ED$3<=NTBA!$F$25,$AC$45*$F$38/10^7,0) -> 0 | EJ64: =IF(EE$3<=NTBA!$F$25,$AC$45*$F$38/10^7,0) -> 0 | EK64: =IF(EF$3<=NTBA!$F$25,$AC$45*$F$38/10^7,0) -> 0 | EL64: =IF(EG$3<=NTBA!$F$25,$AC$45*$F$38/10^7,0) -> 0 | EM64: =IF(EH$3<=NTBA!$F$25,$AC$45*$F$38/10^7,0) -> 0
E65: 16 | F65: 130000 | G65: =SUM(J65:EM65) -> 68.769501 | H65: =SUMPRODUCT(Y65:EW65,J$44:EH$44) -> 48.512532 | J65: =IF( J$47 >= $E65, $F65 * $F$38 / Cr,) * J$46 -> 0 | K65: =IF( K$47 >= $E65, $F65 * $F$38 / Cr,) * K$46 -> 0 | L65: =IF( L$47 >= $E65, $F65 * $F$38 / Cr,) * L$46 -> 0 | M65: =IF( M$47 >= $E65, $F65 * $F$38 / Cr,) * M$46 -> 0 | N65: =IF( N$47 >= $E65, $F65 * $F$38 / Cr,) * N$46 -> 0 | O65: =IF( O$47 >= $E65, $F65 * $F$38 / Cr,) * O$46 -> 0 | P65: =IF( P$47 >= $E65, $F65 * $F$38 / Cr,) * P$46 -> 0 | Q65: =IF( Q$47 >= $E65, $F65 * $F$38 / Cr,) * Q$46 -> 0 | ... EH65: =IF( EH$47 >= $E65, $F65 * $F$38 / Cr,) * EH$46 -> 0 | EI65: =IF(ED$3<=NTBA!$F$25,$AD$45*$F$38/10^7,0) -> 0 | EJ65: =IF(EE$3<=NTBA!$F$25,$AD$45*$F$38/10^7,0) -> 0 | EK65: =IF(EF$3<=NTBA!$F$25,$AD$45*$F$38/10^7,0) -> 0 | EL65: =IF(EG$3<=NTBA!$F$25,$AD$45*$F$38/10^7,0) -> 0 | EM65: =IF(EH$3<=NTBA!$F$25,$AD$45*$F$38/10^7,0) -> 0
E66: 17 | F66: 155000 | G66: =SUM(J66:EM66) -> 81.157727 | H66: =SUMPRODUCT(Z66:EX66,J$44:EH$44) -> 57.444603 | J66: =IF( J$47 >= $E66, $F66 * $F$38 / Cr,) * J$46 -> 0 | K66: =IF( K$47 >= $E66, $F66 * $F$38 / Cr,) * K$46 -> 0 | L66: =IF( L$47 >= $E66, $F66 * $F$38 / Cr,) * L$46 -> 0 | M66: =IF( M$47 >= $E66, $F66 * $F$38 / Cr,) * M$46 -> 0 | N66: =IF( N$47 >= $E66, $F66 * $F$38 / Cr,) * N$46 -> 0 | O66: =IF( O$47 >= $E66, $F66 * $F$38 / Cr,) * O$46 -> 0 | P66: =IF( P$47 >= $E66, $F66 * $F$38 / Cr,) * P$46 -> 0 | Q66: =IF( Q$47 >= $E66, $F66 * $F$38 / Cr,) * Q$46 -> 0 | ... EH66: =IF( EH$47 >= $E66, $F66 * $F$38 / Cr,) * EH$46 -> 0 | EI66: =IF(ED$3<=NTBA!$F$25,$AE$45*$F$38/10^7,0) -> 0 | EJ66: =IF(EE$3<=NTBA!$F$25,$AE$45*$F$38/10^7,0) -> 0 | EK66: =IF(EF$3<=NTBA!$F$25,$AE$45*$F$38/10^7,0) -> 0 | EL66: =IF(EG$3<=NTBA!$F$25,$AE$45*$F$38/10^7,0) -> 0 | EM66: =IF(EH$3<=NTBA!$F$25,$AE$45*$F$38/10^7,0) -> 0
E67: 18 | F67: 178000 | G67: =SUM(J67:EM67) -> 92.239657 | H67: =SUMPRODUCT(AA67:EY67,J$44:EH$44) -> 65.508913 | J67: =IF( J$47 >= $E67, $F67 * $F$38 / Cr,) * J$46 -> 0 | K67: =IF( K$47 >= $E67, $F67 * $F$38 / Cr,) * K$46 -> 0 | L67: =IF( L$47 >= $E67, $F67 * $F$38 / Cr,) * L$46 -> 0 | M67: =IF( M$47 >= $E67, $F67 * $F$38 / Cr,) * M$46 -> 0 | N67: =IF( N$47 >= $E67, $F67 * $F$38 / Cr,) * N$46 -> 0 | O67: =IF( O$47 >= $E67, $F67 * $F$38 / Cr,) * O$46 -> 0 | P67: =IF( P$47 >= $E67, $F67 * $F$38 / Cr,) * P$46 -> 0 | Q67: =IF( Q$47 >= $E67, $F67 * $F$38 / Cr,) * Q$46 -> 0 | ... EH67: =IF( EH$47 >= $E67, $F67 * $F$38 / Cr,) * EH$46 -> 0 | EI67: =IF(ED$3<=NTBA!$F$25,$AF$45*$F$38/10^7,0) -> 0 | EJ67: =IF(EE$3<=NTBA!$F$25,$AF$45*$F$38/10^7,0) -> 0 | EK67: =IF(EF$3<=NTBA!$F$25,$AF$45*$F$38/10^7,0) -> 0 | EL67: =IF(EG$3<=NTBA!$F$25,$AF$45*$F$38/10^7,0) -> 0 | EM67: =IF(EH$3<=NTBA!$F$25,$AF$45*$F$38/10^7,0) -> 0
E68: 19 | F68: 205000 | G68: =SUM(J68:EM68) -> 105.12449 | H68: =SUMPRODUCT(AB68:EZ68,J$44:EH$44) -> 74.912115 | J68: =IF( J$47 >= $E68, $F68 * $F$38 / Cr,) * J$46 -> 0 | K68: =IF( K$47 >= $E68, $F68 * $F$38 / Cr,) * K$46 -> 0 | L68: =IF( L$47 >= $E68, $F68 * $F$38 / Cr,) * L$46 -> 0 | M68: =IF( M$47 >= $E68, $F68 * $F$38 / Cr,) * M$46 -> 0 | N68: =IF( N$47 >= $E68, $F68 * $F$38 / Cr,) * N$46 -> 0 | O68: =IF( O$47 >= $E68, $F68 * $F$38 / Cr,) * O$46 -> 0 | P68: =IF( P$47 >= $E68, $F68 * $F$38 / Cr,) * P$46 -> 0 | Q68: =IF( Q$47 >= $E68, $F68 * $F$38 / Cr,) * Q$46 -> 0 | ... EH68: =IF( EH$47 >= $E68, $F68 * $F$38 / Cr,) * EH$46 -> 0 | EI68: =IF(ED$3<=NTBA!$F$25,$AG$45*$F$38/10^7,0) -> 0 | EJ68: =IF(EE$3<=NTBA!$F$25,$AG$45*$F$38/10^7,0) -> 0 | EK68: =IF(EF$3<=NTBA!$F$25,$AG$45*$F$38/10^7,0) -> 0 | EL68: =IF(EG$3<=NTBA!$F$25,$AG$45*$F$38/10^7,0) -> 0 | EM68: =IF(EH$3<=NTBA!$F$25,$AG$45*$F$38/10^7,0) -> 0
E69: 20 | F69: 218091 | G69: =SUM(J69:EM69) -> 110.66035 | H69: =SUMPRODUCT(AC69:FA69,J$44:EH$44) -> 79.123903 | J69: =IF( J$47 >= $E69, $F69 * $F$38 / Cr,) * J$46 -> 0 | K69: =IF( K$47 >= $E69, $F69 * $F$38 / Cr,) * K$46 -> 0 | L69: =IF( L$47 >= $E69, $F69 * $F$38 / Cr,) * L$46 -> 0 | M69: =IF( M$47 >= $E69, $F69 * $F$38 / Cr,) * M$46 -> 0 | N69: =IF( N$47 >= $E69, $F69 * $F$38 / Cr,) * N$46 -> 0 | O69: =IF( O$47 >= $E69, $F69 * $F$38 / Cr,) * O$46 -> 0 | P69: =IF( P$47 >= $E69, $F69 * $F$38 / Cr,) * P$46 -> 0 | Q69: =IF( Q$47 >= $E69, $F69 * $F$38 / Cr,) * Q$46 -> 0 | ... EH69: =IF( EH$47 >= $E69, $F69 * $F$38 / Cr,) * EH$46 -> 0 | EI69: =IF(ED$3<=NTBA!$F$25,$AH$45*$F$38/10^7,0) -> 0 | EJ69: =IF(EE$3<=NTBA!$F$25,$AH$45*$F$38/10^7,0) -> 0 | EK69: =IF(EF$3<=NTBA!$F$25,$AH$45*$F$38/10^7,0) -> 0 | EL69: =IF(EG$3<=NTBA!$F$25,$AH$45*$F$38/10^7,0) -> 0 | EM69: =IF(EH$3<=NTBA!$F$25,$AH$45*$F$38/10^7,0) -> 0
E70: 21 | F70: 155000 | G70: =SUM(J70:EM70) -> 77.811017 | H70: =SUMPRODUCT(AD70:FB70,J$44:EH$44) -> 55.824693 | J70: =IF( J$47 >= $E70, $F70 * $F$38 / Cr,) * J$46 -> 0 | K70: =IF( K$47 >= $E70, $F70 * $F$38 / Cr,) * K$46 -> 0 | L70: =IF( L$47 >= $E70, $F70 * $F$38 / Cr,) * L$46 -> 0 | M70: =IF( M$47 >= $E70, $F70 * $F$38 / Cr,) * M$46 -> 0 | N70: =IF( N$47 >= $E70, $F70 * $F$38 / Cr,) * N$46 -> 0 | O70: =IF( O$47 >= $E70, $F70 * $F$38 / Cr,) * O$46 -> 0 | P70: =IF( P$47 >= $E70, $F70 * $F$38 / Cr,) * P$46 -> 0 | Q70: =IF( Q$47 >= $E70, $F70 * $F$38 / Cr,) * Q$46 -> 0 | ... EH70: =IF( EH$47 >= $E70, $F70 * $F$38 / Cr,) * EH$46 -> 0 | EI70: =IF(ED$3<=NTBA!$F$25,$AI$45*$F$38/10^7,0) -> 0 | EJ70: =IF(EE$3<=NTBA!$F$25,$AI$45*$F$38/10^7,0) -> 0 | EK70: =IF(EF$3<=NTBA!$F$25,$AI$45*$F$38/10^7,0) -> 0 | EL70: =IF(EG$3<=NTBA!$F$25,$AI$45*$F$38/10^7,0) -> 0 | EM70: =IF(EH$3<=NTBA!$F$25,$AI$45*$F$38/10^7,0) -> 0
E71: 22 | F71: 155000 | G71: =SUM(J71:EM71) -> 76.974339 | H71: =SUMPRODUCT(AE71:FC71,J$44:EH$44) -> 55.411882 | J71: =IF( J$47 >= $E71, $F71 * $F$38 / Cr,) * J$46 -> 0 | K71: =IF( K$47 >= $E71, $F71 * $F$38 / Cr,) * K$46 -> 0 | L71: =IF( L$47 >= $E71, $F71 * $F$38 / Cr,) * L$46 -> 0 | M71: =IF( M$47 >= $E71, $F71 * $F$38 / Cr,) * M$46 -> 0 | N71: =IF( N$47 >= $E71, $F71 * $F$38 / Cr,) * N$46 -> 0 | O71: =IF( O$47 >= $E71, $F71 * $F$38 / Cr,) * O$46 -> 0 | P71: =IF( P$47 >= $E71, $F71 * $F$38 / Cr,) * P$46 -> 0 | Q71: =IF( Q$47 >= $E71, $F71 * $F$38 / Cr,) * Q$46 -> 0 | ... EH71: =IF( EH$47 >= $E71, $F71 * $F$38 / Cr,) * EH$46 -> 0 | EI71: =IF(ED$3<=NTBA!$F$25,$AJ$45*$F$38/10^7,0) -> 0 | EJ71: =IF(EE$3<=NTBA!$F$25,$AJ$45*$F$38/10^7,0) -> 0 | EK71: =IF(EF$3<=NTBA!$F$25,$AJ$45*$F$38/10^7,0) -> 0 | EL71: =IF(EG$3<=NTBA!$F$25,$AJ$45*$F$38/10^7,0) -> 0 | EM71: =IF(EH$3<=NTBA!$F$25,$AJ$45*$F$38/10^7,0) -> 0
E72: 23 | F72: 155000 | G72: =SUM(J72:EM72) -> 76.137662 | H72: =SUMPRODUCT(AF72:FD72,J$44:EH$44) -> 54.995888 | J72: =IF( J$47 >= $E72, $F72 * $F$38 / Cr,) * J$46 -> 0 | K72: =IF( K$47 >= $E72, $F72 * $F$38 / Cr,) * K$46 -> 0 | L72: =IF( L$47 >= $E72, $F72 * $F$38 / Cr,) * L$46 -> 0 | M72: =IF( M$47 >= $E72, $F72 * $F$38 / Cr,) * M$46 -> 0 | N72: =IF( N$47 >= $E72, $F72 * $F$38 / Cr,) * N$46 -> 0 | O72: =IF( O$47 >= $E72, $F72 * $F$38 / Cr,) * O$46 -> 0 | P72: =IF( P$47 >= $E72, $F72 * $F$38 / Cr,) * P$46 -> 0 | Q72: =IF( Q$47 >= $E72, $F72 * $F$38 / Cr,) * Q$46 -> 0 | ... EH72: =IF( EH$47 >= $E72, $F72 * $F$38 / Cr,) * EH$46 -> 0 | EI72: =IF(ED$3<=NTBA!$F$25,$AK$45*$F$38/10^7,0) -> 0 | EJ72: =IF(EE$3<=NTBA!$F$25,$AK$45*$F$38/10^7,0) -> 0 | EK72: =IF(EF$3<=NTBA!$F$25,$AK$45*$F$38/10^7,0) -> 0 | EL72: =IF(EG$3<=NTBA!$F$25,$AK$45*$F$38/10^7,0) -> 0 | EM72: =IF(EH$3<=NTBA!$F$25,$AK$45*$F$38/10^7,0) -> 0
E73: 24 | F73: 155000 | G73: =SUM(J73:EM73) -> 75.300984 | H73: =SUMPRODUCT(AG73:FE73,J$44:EH$44) -> 54.576687 | J73: =IF( J$47 >= $E73, $F73 * $F$38 / Cr,) * J$46 -> 0 | K73: =IF( K$47 >= $E73, $F73 * $F$38 / Cr,) * K$46 -> 0 | L73: =IF( L$47 >= $E73, $F73 * $F$38 / Cr,) * L$46 -> 0 | M73: =IF( M$47 >= $E73, $F73 * $F$38 / Cr,) * M$46 -> 0 | N73: =IF( N$47 >= $E73, $F73 * $F$38 / Cr,) * N$46 -> 0 | O73: =IF( O$47 >= $E73, $F73 * $F$38 / Cr,) * O$46 -> 0 | P73: =IF( P$47 >= $E73, $F73 * $F$38 / Cr,) * P$46 -> 0 | Q73: =IF( Q$47 >= $E73, $F73 * $F$38 / Cr,) * Q$46 -> 0 | ... EH73: =IF( EH$47 >= $E73, $F73 * $F$38 / Cr,) * EH$46 -> 0 | EI73: =IF(ED$3<=NTBA!$F$25,$AL$45*$F$38/10^7,0) -> 0 | EJ73: =IF(EE$3<=NTBA!$F$25,$AL$45*$F$38/10^7,0) -> 0 | EK73: =IF(EF$3<=NTBA!$F$25,$AL$45*$F$38/10^7,0) -> 0 | EL73: =IF(EG$3<=NTBA!$F$25,$AL$45*$F$38/10^7,0) -> 0 | EM73: =IF(EH$3<=NTBA!$F$25,$AL$45*$F$38/10^7,0) -> 0
E74: 25 | F74: 155000 | G74: =SUM(J74:EM74) -> 74.464306 | H74: =SUMPRODUCT(AH74:FF74,J$44:EH$44) -> 54.154256 | J74: =IF( J$47 >= $E74, $F74 * $F$38 / Cr,) * J$46 -> 0 | K74: =IF( K$47 >= $E74, $F74 * $F$38 / Cr,) * K$46 -> 0 | L74: =IF( L$47 >= $E74, $F74 * $F$38 / Cr,) * L$46 -> 0 | M74: =IF( M$47 >= $E74, $F74 * $F$38 / Cr,) * M$46 -> 0 | N74: =IF( N$47 >= $E74, $F74 * $F$38 / Cr,) * N$46 -> 0 | O74: =IF( O$47 >= $E74, $F74 * $F$38 / Cr,) * O$46 -> 0 | P74: =IF( P$47 >= $E74, $F74 * $F$38 / Cr,) * P$46 -> 0 | Q74: =IF( Q$47 >= $E74, $F74 * $F$38 / Cr,) * Q$46 -> 0 | ... EH74: =IF( EH$47 >= $E74, $F74 * $F$38 / Cr,) * EH$46 -> 0 | EI74: =IF(ED$3<=NTBA!$F$25,$AM$45*$F$38/10^7,0) -> 0 | EJ74: =IF(EE$3<=NTBA!$F$25,$AM$45*$F$38/10^7,0) -> 0 | EK74: =IF(EF$3<=NTBA!$F$25,$AM$45*$F$38/10^7,0) -> 0 | EL74: =IF(EG$3<=NTBA!$F$25,$AM$45*$F$38/10^7,0) -> 0 | EM74: =IF(EH$3<=NTBA!$F$25,$AM$45*$F$38/10^7,0) -> 0
E75: 26 | F75: 155000 | G75: =SUM(J75:EM75) -> 73.627629 | H75: =SUMPRODUCT(AI75:FG75,J$44:EH$44) -> 53.728568 | J75: =IF( J$47 >= $E75, $F75 * $F$38 / Cr,) * J$46 -> 0 | K75: =IF( K$47 >= $E75, $F75 * $F$38 / Cr,) * K$46 -> 0 | L75: =IF( L$47 >= $E75, $F75 * $F$38 / Cr,) * L$46 -> 0 | M75: =IF( M$47 >= $E75, $F75 * $F$38 / Cr,) * M$46 -> 0 | N75: =IF( N$47 >= $E75, $F75 * $F$38 / Cr,) * N$46 -> 0 | O75: =IF( O$47 >= $E75, $F75 * $F$38 / Cr,) * O$46 -> 0 | P75: =IF( P$47 >= $E75, $F75 * $F$38 / Cr,) * P$46 -> 0 | Q75: =IF( Q$47 >= $E75, $F75 * $F$38 / Cr,) * Q$46 -> 0 | ... EH75: =IF( EH$47 >= $E75, $F75 * $F$38 / Cr,) * EH$46 -> 0 | EI75: =IF(ED$3<=NTBA!$F$25,$AN$45*$F$38/10^7,0) -> 0 | EJ75: =IF(EE$3<=NTBA!$F$25,$AN$45*$F$38/10^7,0) -> 0 | EK75: =IF(EF$3<=NTBA!$F$25,$AN$45*$F$38/10^7,0) -> 0 | EL75: =IF(EG$3<=NTBA!$F$25,$AN$45*$F$38/10^7,0) -> 0 | EM75: =IF(EH$3<=NTBA!$F$25,$AN$45*$F$38/10^7,0) -> 0
E76: 27 | F76: 155000 | G76: =SUM(J76:EM76) -> 72.790951 | H76: =SUMPRODUCT(AJ76:FH76,J$44:EH$44) -> 53.299599 | J76: =IF( J$47 >= $E76, $F76 * $F$38 / Cr,) * J$46 -> 0 | K76: =IF( K$47 >= $E76, $F76 * $F$38 / Cr,) * K$46 -> 0 | L76: =IF( L$47 >= $E76, $F76 * $F$38 / Cr,) * L$46 -> 0 | M76: =IF( M$47 >= $E76, $F76 * $F$38 / Cr,) * M$46 -> 0 | N76: =IF( N$47 >= $E76, $F76 * $F$38 / Cr,) * N$46 -> 0 | O76: =IF( O$47 >= $E76, $F76 * $F$38 / Cr,) * O$46 -> 0 | P76: =IF( P$47 >= $E76, $F76 * $F$38 / Cr,) * P$46 -> 0 | Q76: =IF( Q$47 >= $E76, $F76 * $F$38 / Cr,) * Q$46 -> 0 | ... EH76: =IF( EH$47 >= $E76, $F76 * $F$38 / Cr,) * EH$46 -> 0 | EI76: =IF(ED$3<=NTBA!$F$25,$AO$45*$F$38/10^7,0) -> 0 | EJ76: =IF(EE$3<=NTBA!$F$25,$AO$45*$F$38/10^7,0) -> 0 | EK76: =IF(EF$3<=NTBA!$F$25,$AO$45*$F$38/10^7,0) -> 0 | EL76: =IF(EG$3<=NTBA!$F$25,$AO$45*$F$38/10^7,0) -> 0 | EM76: =IF(EH$3<=NTBA!$F$25,$AO$45*$F$38/10^7,0) -> 0
E77: 28 | F77: 155000 | G77: =SUM(J77:EM77) -> 71.954274 | H77: =SUMPRODUCT(AK77:FI77,J$44:EH$44) -> 52.867323 | J77: =IF( J$47 >= $E77, $F77 * $F$38 / Cr,) * J$46 -> 0 | K77: =IF( K$47 >= $E77, $F77 * $F$38 / Cr,) * K$46 -> 0 | L77: =IF( L$47 >= $E77, $F77 * $F$38 / Cr,) * L$46 -> 0 | M77: =IF( M$47 >= $E77, $F77 * $F$38 / Cr,) * M$46 -> 0 | N77: =IF( N$47 >= $E77, $F77 * $F$38 / Cr,) * N$46 -> 0 | O77: =IF( O$47 >= $E77, $F77 * $F$38 / Cr,) * O$46 -> 0 | P77: =IF( P$47 >= $E77, $F77 * $F$38 / Cr,) * P$46 -> 0 | Q77: =IF( Q$47 >= $E77, $F77 * $F$38 / Cr,) * Q$46 -> 0 | ... EH77: =IF( EH$47 >= $E77, $F77 * $F$38 / Cr,) * EH$46 -> 0 | EI77: =IF(ED$3<=NTBA!$F$25,$AP$45*$F$38/10^7,0) -> 0 | EJ77: =IF(EE$3<=NTBA!$F$25,$AP$45*$F$38/10^7,0) -> 0 | EK77: =IF(EF$3<=NTBA!$F$25,$AP$45*$F$38/10^7,0) -> 0 | EL77: =IF(EG$3<=NTBA!$F$25,$AP$45*$F$38/10^7,0) -> 0 | EM77: =IF(EH$3<=NTBA!$F$25,$AP$45*$F$38/10^7,0) -> 0
E78: 29 | F78: 142463 | G78: =SUM(J78:EM78) -> 59.691117 | H78: =SUMPRODUCT(AL78:FJ78,J$44:EH$44) -> 45.213839 | J78: =IF( J$47 >= $E78, $F78 * $F$38 / Cr,) * J$46 -> 0 | K78: =IF( K$47 >= $E78, $F78 * $F$38 / Cr,) * K$46 -> 0 | L78: =IF( L$47 >= $E78, $F78 * $F$38 / Cr,) * L$46 -> 0 | M78: =IF( M$47 >= $E78, $F78 * $F$38 / Cr,) * M$46 -> 0 | N78: =IF( N$47 >= $E78, $F78 * $F$38 / Cr,) * N$46 -> 0 | O78: =IF( O$47 >= $E78, $F78 * $F$38 / Cr,) * O$46 -> 0 | P78: =IF( P$47 >= $E78, $F78 * $F$38 / Cr,) * P$46 -> 0 | Q78: =IF( Q$47 >= $E78, $F78 * $F$38 / Cr,) * Q$46 -> 0 | ... DQ78: =IF( DQ$47 >= $E78, $F78 * $F$38 / Cr,) * DQ$46 -> 0.76900388 | DR78: -4.9052087 | DS78: =IF( DS$47 >= $E78, $F78 * $F$38 / Cr,) * DS$46 -> 0 | DT78: =IF( DT$47 >= $E78, $F78 * $F$38 / Cr,) * DT$46 -> 0 | DU78: =IF( DU$47 >= $E78, $F78 * $F$38 / Cr,) * DU$46 -> 0 | DV78: =IF( DV$47 >= $E78, $F78 * $F$38 / Cr,) * DV$46 -> 0 | DW78: =IF( DW$47 >= $E78, $F78 * $F$38 / Cr,) * DW$46 -> 0 | DX78: =IF( DX$47 >= $E78, $F78 * $F$38 / Cr,) * DX$46 -> 0 | DY78: =IF( DY$47 >= $E78, $F78 * $F$38 / Cr,) * DY$46 -> 0 | DZ78: =IF( DZ$47 >= $E78, $F78 * $F$38 / Cr,) * DZ$46 -> 0 | ... EH78: =IF( EH$47 >= $E78, $F78 * $F$38 / Cr,) * EH$46 -> 0 | EI78: =IF(ED$3<=NTBA!$F$25,$AQ$45*$F$38/10^7,0) -> 0 | EJ78: =IF(EE$3<=NTBA!$F$25,$AQ$45*$F$38/10^7,0) -> 0 | EK78: =IF(EF$3<=NTBA!$F$25,$AQ$45*$F$38/10^7,0) -> 0 | EL78: =IF(EG$3<=NTBA!$F$25,$AQ$45*$F$38/10^7,0) -> 0 | EM78: =IF(EH$3<=NTBA!$F$25,$AQ$45*$F$38/10^7,0) -> 0
E79: 30 | F79: 0 | G79: =SUM(J79:EM79) -> 0 | H79: =SUMPRODUCT(AM79:FK79,J$44:EH$44) -> 0 | J79: =IF( J$47 >= $E79, $F79 * $F$38 / Cr,) * J$46 -> 0 | K79: =IF( K$47 >= $E79, $F79 * $F$38 / Cr,) * K$46 -> 0 | L79: =IF( L$47 >= $E79, $F79 * $F$38 / Cr,) * L$46 -> 0 | M79: =IF( M$47 >= $E79, $F79 * $F$38 / Cr,) * M$46 -> 0 | N79: =IF( N$47 >= $E79, $F79 * $F$38 / Cr,) * N$46 -> 0 | O79: =IF( O$47 >= $E79, $F79 * $F$38 / Cr,) * O$46 -> 0 | P79: =IF( P$47 >= $E79, $F79 * $F$38 / Cr,) * P$46 -> 0 | Q79: =IF( Q$47 >= $E79, $F79 * $F$38 / Cr,) * Q$46 -> 0 | ... EH79: =IF( EH$47 >= $E79, $F79 * $F$38 / Cr,) * EH$46 -> 0 | EI79: =IF(ED$3<=NTBA!$F$25,$AR$45*$F$38/10^7,0) -> 0 | EJ79: =IF(EE$3<=NTBA!$F$25,$AR$45*$F$38/10^7,0) -> 0 | EK79: =IF(EF$3<=NTBA!$F$25,$AR$45*$F$38/10^7,0) -> 0 | EL79: =IF(EG$3<=NTBA!$F$25,$AR$45*$F$38/10^7,0) -> 0 | EM79: =IF(EH$3<=NTBA!$F$25,$AR$45*$F$38/10^7,0) -> 0
E80: 31 | F80: 0 | G80: =SUM(J80:EM80) -> 0 | H80: =SUMPRODUCT(M80:EK80,J$44:EH$44) -> 0 | J80: =IF( J$47 >= $E80, $F80 * $F$38 / Cr,) * J$46 -> 0 | K80: =IF( K$47 >= $E80, $F80 * $F$38 / Cr,) * K$46 -> 0 | L80: =IF( L$47 >= $E80, $F80 * $F$38 / Cr,) * L$46 -> 0 | M80: =IF( M$47 >= $E80, $F80 * $F$38 / Cr,) * M$46 -> 0 | N80: =IF( N$47 >= $E80, $F80 * $F$38 / Cr,) * N$46 -> 0 | O80: =IF( O$47 >= $E80, $F80 * $F$38 / Cr,) * O$46 -> 0 | P80: =IF( P$47 >= $E80, $F80 * $F$38 / Cr,) * P$46 -> 0 | Q80: =IF( Q$47 >= $E80, $F80 * $F$38 / Cr,) * Q$46 -> 0 | ... EH80: =IF( EH$47 >= $E80, $F80 * $F$38 / Cr,) * EH$46 -> 0 | EI80: =IF(ED$3<=NTBA!$F$25,$AS$45*$F$38/10^7,0) -> 0 | EJ80: =IF(EE$3<=NTBA!$F$25,$AS$45*$F$38/10^7,0) -> 0 | EK80: =IF(EF$3<=NTBA!$F$25,$AS$45*$F$38/10^7,0) -> 0 | EL80: =IF(EG$3<=NTBA!$F$25,$AS$45*$F$38/10^7,0) -> 0 | EM80: =IF(EH$3<=NTBA!$F$25,$AS$45*$F$38/10^7,0) -> 0
E81: 32 | F81: 0 | G81: =SUM(J81:EM81) -> 0 | H81: =SUMPRODUCT(M81:EK81,J$44:EH$44) -> 0 | J81: =IF( J$47 >= $E81, $F81 * $F$38 / Cr,) * J$46 -> 0 | K81: =IF( K$47 >= $E81, $F81 * $F$38 / Cr,) * K$46 -> 0 | L81: =IF( L$47 >= $E81, $F81 * $F$38 / Cr,) * L$46 -> 0 | M81: =IF( M$47 >= $E81, $F81 * $F$38 / Cr,) * M$46 -> 0 | N81: =IF( N$47 >= $E81, $F81 * $F$38 / Cr,) * N$46 -> 0 | O81: =IF( O$47 >= $E81, $F81 * $F$38 / Cr,) * O$46 -> 0 | P81: =IF( P$47 >= $E81, $F81 * $F$38 / Cr,) * P$46 -> 0 | Q81: =IF( Q$47 >= $E81, $F81 * $F$38 / Cr,) * Q$46 -> 0 | ... EH81: =IF( EH$47 >= $E81, $F81 * $F$38 / Cr,) * EH$46 -> 0 | EI81: =IF(ED$3<=NTBA!$F$25,$AT$45*$F$38/10^7,0) -> 0 | EJ81: =IF(EE$3<=NTBA!$F$25,$AT$45*$F$38/10^7,0) -> 0 | EK81: =IF(EF$3<=NTBA!$F$25,$AT$45*$F$38/10^7,0) -> 0 | EL81: =IF(EG$3<=NTBA!$F$25,$AT$45*$F$38/10^7,0) -> 0 | EM81: =IF(EH$3<=NTBA!$F$25,$AT$45*$F$38/10^7,0) -> 0
E82: 33 | F82: 0 | G82: =SUM(J82:EM82) -> 0 | H82: =SUMPRODUCT(M82:EK82,J$44:EH$44) -> 0 | J82: =IF( J$47 >= $E82, $F82 * $F$38 / Cr,) * J$46 -> 0 | K82: =IF( K$47 >= $E82, $F82 * $F$38 / Cr,) * K$46 -> 0 | L82: =IF( L$47 >= $E82, $F82 * $F$38 / Cr,) * L$46 -> 0 | M82: =IF( M$47 >= $E82, $F82 * $F$38 / Cr,) * M$46 -> 0 | N82: =IF( N$47 >= $E82, $F82 * $F$38 / Cr,) * N$46 -> 0 | O82: =IF( O$47 >= $E82, $F82 * $F$38 / Cr,) * O$46 -> 0 | P82: =IF( P$47 >= $E82, $F82 * $F$38 / Cr,) * P$46 -> 0 | Q82: =IF( Q$47 >= $E82, $F82 * $F$38 / Cr,) * Q$46 -> 0 | ... EH82: =IF( EH$47 >= $E82, $F82 * $F$38 / Cr,) * EH$46 -> 0 | EI82: =IF(ED$3<=NTBA!$F$25,$AU$45*$F$38/10^7,0) -> 0 | EJ82: =IF(EE$3<=NTBA!$F$25,$AU$45*$F$38/10^7,0) -> 0 | EK82: =IF(EF$3<=NTBA!$F$25,$AU$45*$F$38/10^7,0) -> 0 | EL82: =IF(EG$3<=NTBA!$F$25,$AU$45*$F$38/10^7,0) -> 0 | EM82: =IF(EH$3<=NTBA!$F$25,$AU$45*$F$38/10^7,0) -> 0
E83: 34 | F83: 0 | G83: =SUM(J83:EM83) -> 0 | H83: =SUMPRODUCT(M83:EK83,J$44:EH$44) -> 0 | J83: =IF( J$47 >= $E83, $F83 * $F$38 / Cr,) * J$46 -> 0 | K83: =IF( K$47 >= $E83, $F83 * $F$38 / Cr,) * K$46 -> 0 | L83: =IF( L$47 >= $E83, $F83 * $F$38 / Cr,) * L$46 -> 0 | M83: =IF( M$47 >= $E83, $F83 * $F$38 / Cr,) * M$46 -> 0 | N83: =IF( N$47 >= $E83, $F83 * $F$38 / Cr,) * N$46 -> 0 | O83: =IF( O$47 >= $E83, $F83 * $F$38 / Cr,) * O$46 -> 0 | P83: =IF( P$47 >= $E83, $F83 * $F$38 / Cr,) * P$46 -> 0 | Q83: =IF( Q$47 >= $E83, $F83 * $F$38 / Cr,) * Q$46 -> 0 | ... EH83: =IF( EH$47 >= $E83, $F83 * $F$38 / Cr,) * EH$46 -> 0 | EI83: =IF(ED$3<=NTBA!$F$25,$AV$45*$F$38/10^7,0) -> 0 | EJ83: =IF(EE$3<=NTBA!$F$25,$AV$45*$F$38/10^7,0) -> 0 | EK83: =IF(EF$3<=NTBA!$F$25,$AV$45*$F$38/10^7,0) -> 0 | EL83: =IF(EG$3<=NTBA!$F$25,$AV$45*$F$38/10^7,0) -> 0 | EM83: =IF(EH$3<=NTBA!$F$25,$AV$45*$F$38/10^7,0) -> 0
E84: 35 | F84: 0 | G84: =SUM(J84:EM84) -> 0 | H84: =SUMPRODUCT(M84:EK84,J$44:EH$44) -> 0 | J84: =IF( J$47 >= $E84, $F84 * $F$38 / Cr,) * J$46 -> 0 | K84: =IF( K$47 >= $E84, $F84 * $F$38 / Cr,) * K$46 -> 0 | L84: =IF( L$47 >= $E84, $F84 * $F$38 / Cr,) * L$46 -> 0 | M84: =IF( M$47 >= $E84, $F84 * $F$38 / Cr,) * M$46 -> 0 | N84: =IF( N$47 >= $E84, $F84 * $F$38 / Cr,) * N$46 -> 0 | O84: =IF( O$47 >= $E84, $F84 * $F$38 / Cr,) * O$46 -> 0 | P84: =IF( P$47 >= $E84, $F84 * $F$38 / Cr,) * P$46 -> 0 | Q84: =IF( Q$47 >= $E84, $F84 * $F$38 / Cr,) * Q$46 -> 0 | ... EH84: =IF( EH$47 >= $E84, $F84 * $F$38 / Cr,) * EH$46 -> 0 | EI84: =IF(ED$3<=NTBA!$F$25,$AW$45*$F$38/10^7,0) -> 0 | EJ84: =IF(EE$3<=NTBA!$F$25,$AW$45*$F$38/10^7,0) -> 0 | EK84: =IF(EF$3<=NTBA!$F$25,$AW$45*$F$38/10^7,0) -> 0 | EL84: =IF(EG$3<=NTBA!$F$25,$AW$45*$F$38/10^7,0) -> 0 | EM84: =IF(EH$3<=NTBA!$F$25,$AW$45*$F$38/10^7,0) -> 0
E85: 36 | F85: 0 | G85: =SUM(J85:EM85) -> 0 | H85: =SUMPRODUCT(M85:EK85,J$44:EH$44) -> 0 | J85: =IF( J$47 >= $E85, $F85 * $F$38 / Cr,) * J$46 -> 0 | K85: =IF( K$47 >= $E85, $F85 * $F$38 / Cr,) * K$46 -> 0 | L85: =IF( L$47 >= $E85, $F85 * $F$38 / Cr,) * L$46 -> 0 | M85: =IF( M$47 >= $E85, $F85 * $F$38 / Cr,) * M$46 -> 0 | N85: =IF( N$47 >= $E85, $F85 * $F$38 / Cr,) * N$46 -> 0 | O85: =IF( O$47 >= $E85, $F85 * $F$38 / Cr,) * O$46 -> 0 | P85: =IF( P$47 >= $E85, $F85 * $F$38 / Cr,) * P$46 -> 0 | Q85: =IF( Q$47 >= $E85, $F85 * $F$38 / Cr,) * Q$46 -> 0 | ... EH85: =IF( EH$47 >= $E85, $F85 * $F$38 / Cr,) * EH$46 -> 0 | EI85: =IF(ED$3<=NTBA!$F$25,$AX$45*$F$38/10^7,0) -> 0 | EJ85: =IF(EE$3<=NTBA!$F$25,$AX$45*$F$38/10^7,0) -> 0 | EK85: =IF(EF$3<=NTBA!$F$25,$AX$45*$F$38/10^7,0) -> 0 | EL85: =IF(EG$3<=NTBA!$F$25,$AX$45*$F$38/10^7,0) -> 0 | EM85: =IF(EH$3<=NTBA!$F$25,$AX$45*$F$38/10^7,0) -> 0
E86: 37 | F86: 0 | G86: =SUM(J86:EM86) -> 0 | H86: =SUMPRODUCT(M86:EK86,J$44:EH$44) -> 0 | J86: =IF( J$47 >= $E86, $F86 * $F$38 / Cr,) * J$46 -> 0 | K86: =IF( K$47 >= $E86, $F86 * $F$38 / Cr,) * K$46 -> 0 | L86: =IF( L$47 >= $E86, $F86 * $F$38 / Cr,) * L$46 -> 0 | M86: =IF( M$47 >= $E86, $F86 * $F$38 / Cr,) * M$46 -> 0 | N86: =IF( N$47 >= $E86, $F86 * $F$38 / Cr,) * N$46 -> 0 | O86: =IF( O$47 >= $E86, $F86 * $F$38 / Cr,) * O$46 -> 0 | P86: =IF( P$47 >= $E86, $F86 * $F$38 / Cr,) * P$46 -> 0 | Q86: =IF( Q$47 >= $E86, $F86 * $F$38 / Cr,) * Q$46 -> 0 | ... EH86: =IF( EH$47 >= $E86, $F86 * $F$38 / Cr,) * EH$46 -> 0 | EI86: =IF(ED$3<=NTBA!$F$25,$AY$45*$F$38/10^7,0) -> 0 | EJ86: =IF(EE$3<=NTBA!$F$25,$AY$45*$F$38/10^7,0) -> 0 | EK86: =IF(EF$3<=NTBA!$F$25,$AY$45*$F$38/10^7,0) -> 0 | EL86: =IF(EG$3<=NTBA!$F$25,$AY$45*$F$38/10^7,0) -> 0 | EM86: =IF(EH$3<=NTBA!$F$25,$AY$45*$F$38/10^7,0) -> 0
E87: 38 | F87: 0 | G87: =SUM(J87:EM87) -> 0 | H87: =SUMPRODUCT(M87:EK87,J$44:EH$44) -> 0 | J87: =IF( J$47 >= $E87, $F87 * $F$38 / Cr,) * J$46 -> 0 | K87: =IF( K$47 >= $E87, $F87 * $F$38 / Cr,) * K$46 -> 0 | L87: =IF( L$47 >= $E87, $F87 * $F$38 / Cr,) * L$46 -> 0 | M87: =IF( M$47 >= $E87, $F87 * $F$38 / Cr,) * M$46 -> 0 | N87: =IF( N$47 >= $E87, $F87 * $F$38 / Cr,) * N$46 -> 0 | O87: =IF( O$47 >= $E87, $F87 * $F$38 / Cr,) * O$46 -> 0 | P87: =IF( P$47 >= $E87, $F87 * $F$38 / Cr,) * P$46 -> 0 | Q87: =IF( Q$47 >= $E87, $F87 * $F$38 / Cr,) * Q$46 -> 0 | ... EH87: =IF( EH$47 >= $E87, $F87 * $F$38 / Cr,) * EH$46 -> 0
E88: 39 | F88: 0 | G88: =SUM(J88:EM88) -> 0 | H88: =SUMPRODUCT(M88:EK88,J$44:EH$44) -> 0 | J88: =IF( J$47 >= $E88, $F88 * $F$38 / Cr,) * J$46 -> 0 | K88: =IF( K$47 >= $E88, $F88 * $F$38 / Cr,) * K$46 -> 0 | L88: =IF( L$47 >= $E88, $F88 * $F$38 / Cr,) * L$46 -> 0 | M88: =IF( M$47 >= $E88, $F88 * $F$38 / Cr,) * M$46 -> 0 | N88: =IF( N$47 >= $E88, $F88 * $F$38 / Cr,) * N$46 -> 0 | O88: =IF( O$47 >= $E88, $F88 * $F$38 / Cr,) * O$46 -> 0 | P88: =IF( P$47 >= $E88, $F88 * $F$38 / Cr,) * P$46 -> 0 | Q88: =IF( Q$47 >= $E88, $F88 * $F$38 / Cr,) * Q$46 -> 0 | ... EH88: =IF( EH$47 >= $E88, $F88 * $F$38 / Cr,) * EH$46 -> 0
E89: 40 | F89: 0 | G89: =SUM(J89:EM89) -> 0 | H89: =SUMPRODUCT(M89:EK89,J$44:EH$44) -> 0 | J89: =IF( J$47 >= $E89, $F89 * $F$38 / Cr,) * J$46 -> 0 | K89: =IF( K$47 >= $E89, $F89 * $F$38 / Cr,) * K$46 -> 0 | L89: =IF( L$47 >= $E89, $F89 * $F$38 / Cr,) * L$46 -> 0 | M89: =IF( M$47 >= $E89, $F89 * $F$38 / Cr,) * M$46 -> 0 | N89: =IF( N$47 >= $E89, $F89 * $F$38 / Cr,) * N$46 -> 0 | O89: =IF( O$47 >= $E89, $F89 * $F$38 / Cr,) * O$46 -> 0 | P89: =IF( P$47 >= $E89, $F89 * $F$38 / Cr,) * P$46 -> 0 | Q89: =IF( Q$47 >= $E89, $F89 * $F$38 / Cr,) * Q$46 -> 0 | ... EH89: =IF( EH$47 >= $E89, $F89 * $F$38 / Cr,) * EH$46 -> 0
E90: 41 | F90: 0 | G90: =SUM(J90:EM90) -> 0 | H90: =SUMPRODUCT(M90:EK90,J$44:EH$44) -> 0 | J90: =IF( J$47 >= $E90, $F90 * $F$38 / Cr,) * J$46 -> 0 | K90: =IF( K$47 >= $E90, $F90 * $F$38 / Cr,) * K$46 -> 0 | L90: =IF( L$47 >= $E90, $F90 * $F$38 / Cr,) * L$46 -> 0 | M90: =IF( M$47 >= $E90, $F90 * $F$38 / Cr,) * M$46 -> 0 | N90: =IF( N$47 >= $E90, $F90 * $F$38 / Cr,) * N$46 -> 0 | O90: =IF( O$47 >= $E90, $F90 * $F$38 / Cr,) * O$46 -> 0 | P90: =IF( P$47 >= $E90, $F90 * $F$38 / Cr,) * P$46 -> 0 | Q90: =IF( Q$47 >= $E90, $F90 * $F$38 / Cr,) * Q$46 -> 0 | ... EH90: =IF( EH$47 >= $E90, $F90 * $F$38 / Cr,) * EH$46 -> 0
E91: 42 | F91: 0 | G91: =SUM(J91:EM91) -> 0 | H91: =SUMPRODUCT(M91:EK91,J$44:EH$44) -> 0 | J91: =IF( J$47 >= $E91, $F91 * $F$38 / Cr,) * J$46 -> 0 | K91: =IF( K$47 >= $E91, $F91 * $F$38 / Cr,) * K$46 -> 0 | L91: =IF( L$47 >= $E91, $F91 * $F$38 / Cr,) * L$46 -> 0 | M91: =IF( M$47 >= $E91, $F91 * $F$38 / Cr,) * M$46 -> 0 | N91: =IF( N$47 >= $E91, $F91 * $F$38 / Cr,) * N$46 -> 0 | O91: =IF( O$47 >= $E91, $F91 * $F$38 / Cr,) * O$46 -> 0 | P91: =IF( P$47 >= $E91, $F91 * $F$38 / Cr,) * P$46 -> 0 | Q91: =IF( Q$47 >= $E91, $F91 * $F$38 / Cr,) * Q$46 -> 0 | ... EH91: =IF( EH$47 >= $E91, $F91 * $F$38 / Cr,) * EH$46 -> 0
E92: 43 | F92: 0 | G92: =SUM(J92:EM92) -> 0 | H92: =SUMPRODUCT(M92:EK92,J$44:EH$44) -> 0 | J92: =IF( J$47 >= $E92, $F92 * $F$38 / Cr,) * J$46 -> 0 | K92: =IF( K$47 >= $E92, $F92 * $F$38 / Cr,) * K$46 -> 0 | L92: =IF( L$47 >= $E92, $F92 * $F$38 / Cr,) * L$46 -> 0 | M92: =IF( M$47 >= $E92, $F92 * $F$38 / Cr,) * M$46 -> 0 | N92: =IF( N$47 >= $E92, $F92 * $F$38 / Cr,) * N$46 -> 0 | O92: =IF( O$47 >= $E92, $F92 * $F$38 / Cr,) * O$46 -> 0 | P92: =IF( P$47 >= $E92, $F92 * $F$38 / Cr,) * P$46 -> 0 | Q92: =IF( Q$47 >= $E92, $F92 * $F$38 / Cr,) * Q$46 -> 0 | ... EH92: =IF( EH$47 >= $E92, $F92 * $F$38 / Cr,) * EH$46 -> 0
E93: 44 | F93: 0 | G93: =SUM(J93:EM93) -> 0 | H93: =SUMPRODUCT(M93:EK93,J$44:EH$44) -> 0 | J93: =IF( J$47 >= $E93, $F93 * $F$38 / Cr,) * J$46 -> 0 | K93: =IF( K$47 >= $E93, $F93 * $F$38 / Cr,) * K$46 -> 0 | L93: =IF( L$47 >= $E93, $F93 * $F$38 / Cr,) * L$46 -> 0 | M93: =IF( M$47 >= $E93, $F93 * $F$38 / Cr,) * M$46 -> 0 | N93: =IF( N$47 >= $E93, $F93 * $F$38 / Cr,) * N$46 -> 0 | O93: =IF( O$47 >= $E93, $F93 * $F$38 / Cr,) * O$46 -> 0 | P93: =IF( P$47 >= $E93, $F93 * $F$38 / Cr,) * P$46 -> 0 | Q93: =IF( Q$47 >= $E93, $F93 * $F$38 / Cr,) * Q$46 -> 0 | ... EH93: =IF( EH$47 >= $E93, $F93 * $F$38 / Cr,) * EH$46 -> 0
E94: 45 | F94: 0 | G94: =SUM(J94:EM94) -> 0 | H94: =SUMPRODUCT(M94:EK94,J$44:EH$44) -> 0 | J94: =IF( J$47 >= $E94, $F94 * $F$38 / Cr,) * J$46 -> 0 | K94: =IF( K$47 >= $E94, $F94 * $F$38 / Cr,) * K$46 -> 0 | L94: =IF( L$47 >= $E94, $F94 * $F$38 / Cr,) * L$46 -> 0 | M94: =IF( M$47 >= $E94, $F94 * $F$38 / Cr,) * M$46 -> 0 | N94: =IF( N$47 >= $E94, $F94 * $F$38 / Cr,) * N$46 -> 0 | O94: =IF( O$47 >= $E94, $F94 * $F$38 / Cr,) * O$46 -> 0 | P94: =IF( P$47 >= $E94, $F94 * $F$38 / Cr,) * P$46 -> 0 | Q94: =IF( Q$47 >= $E94, $F94 * $F$38 / Cr,) * Q$46 -> 0 | ... EH94: =IF( EH$47 >= $E94, $F94 * $F$38 / Cr,) * EH$46 -> 0
E95: 46 | F95: 0 | G95: =SUM(J95:EM95) -> 0 | H95: =SUMPRODUCT(M95:EK95,J$44:EH$44) -> 0 | J95: =IF( J$47 >= $E95, $F95 * $F$38 / Cr,) * J$46 -> 0 | K95: =IF( K$47 >= $E95, $F95 * $F$38 / Cr,) * K$46 -> 0 | L95: =IF( L$47 >= $E95, $F95 * $F$38 / Cr,) * L$46 -> 0 | M95: =IF( M$47 >= $E95, $F95 * $F$38 / Cr,) * M$46 -> 0 | N95: =IF( N$47 >= $E95, $F95 * $F$38 / Cr,) * N$46 -> 0 | O95: =IF( O$47 >= $E95, $F95 * $F$38 / Cr,) * O$46 -> 0 | P95: =IF( P$47 >= $E95, $F95 * $F$38 / Cr,) * P$46 -> 0 | Q95: =IF( Q$47 >= $E95, $F95 * $F$38 / Cr,) * Q$46 -> 0 | ... EH95: =IF( EH$47 >= $E95, $F95 * $F$38 / Cr,) * EH$46 -> 0
E96: 47 | F96: 0 | G96: =SUM(J96:EM96) -> 0 | H96: =SUMPRODUCT(M96:EK96,J$44:EH$44) -> 0 | J96: =IF( J$47 >= $E96, $F96 * $F$38 / Cr,) * J$46 -> 0 | K96: =IF( K$47 >= $E96, $F96 * $F$38 / Cr,) * K$46 -> 0 | L96: =IF( L$47 >= $E96, $F96 * $F$38 / Cr,) * L$46 -> 0 | M96: =IF( M$47 >= $E96, $F96 * $F$38 / Cr,) * M$46 -> 0 | N96: =IF( N$47 >= $E96, $F96 * $F$38 / Cr,) * N$46 -> 0 | O96: =IF( O$47 >= $E96, $F96 * $F$38 / Cr,) * O$46 -> 0 | P96: =IF( P$47 >= $E96, $F96 * $F$38 / Cr,) * P$46 -> 0 | Q96: =IF( Q$47 >= $E96, $F96 * $F$38 / Cr,) * Q$46 -> 0 | ... EH96: =IF( EH$47 >= $E96, $F96 * $F$38 / Cr,) * EH$46 -> 0
E97: 48 | F97: 0 | G97: =SUM(J97:EM97) -> 0 | H97: =SUMPRODUCT(M97:EK97,J$44:EH$44) -> 0 | J97: =IF( J$47 >= $E97, $F97 * $F$38 / Cr,) * J$46 -> 0 | K97: =IF( K$47 >= $E97, $F97 * $F$38 / Cr,) * K$46 -> 0 | L97: =IF( L$47 >= $E97, $F97 * $F$38 / Cr,) * L$46 -> 0 | M97: =IF( M$47 >= $E97, $F97 * $F$38 / Cr,) * M$46 -> 0 | N97: =IF( N$47 >= $E97, $F97 * $F$38 / Cr,) * N$46 -> 0 | O97: =IF( O$47 >= $E97, $F97 * $F$38 / Cr,) * O$46 -> 0 | P97: =IF( P$47 >= $E97, $F97 * $F$38 / Cr,) * P$46 -> 0 | Q97: =IF( Q$47 >= $E97, $F97 * $F$38 / Cr,) * Q$46 -> 0 | ... EH97: =IF( EH$47 >= $E97, $F97 * $F$38 / Cr,) * EH$46 -> 0
E98: 49 | F98: 0 | G98: =SUM(J98:EM98) -> 0 | H98: =SUMPRODUCT(M98:EK98,J$44:EH$44) -> 0 | J98: =IF( J$47 >= $E98, $F98 * $F$38 / Cr,) * J$46 -> 0 | K98: =IF( K$47 >= $E98, $F98 * $F$38 / Cr,) * K$46 -> 0 | L98: =IF( L$47 >= $E98, $F98 * $F$38 / Cr,) * L$46 -> 0 | M98: =IF( M$47 >= $E98, $F98 * $F$38 / Cr,) * M$46 -> 0 | N98: =IF( N$47 >= $E98, $F98 * $F$38 / Cr,) * N$46 -> 0 | O98: =IF( O$47 >= $E98, $F98 * $F$38 / Cr,) * O$46 -> 0 | P98: =IF( P$47 >= $E98, $F98 * $F$38 / Cr,) * P$46 -> 0 | Q98: =IF( Q$47 >= $E98, $F98 * $F$38 / Cr,) * Q$46 -> 0 | ... EH98: =IF( EH$47 >= $E98, $F98 * $F$38 / Cr,) * EH$46 -> 0
... E178: 129 | F178: 0 | G178: =SUM(J178:EM178) -> 0 | H178: =SUMPRODUCT(M178:EK178,J$44:EH$44) -> 0 | J178: =IF( J$47 >= $E178, $F178 * $F$38 / Cr,) * J$46 -> 0 | K178: =IF( K$47 >= $E178, $F178 * $F$38 / Cr,) * K$46 -> 0 | L178: =IF( L$47 >= $E178, $F178 * $F$38 / Cr,) * L$46 -> 0 | M178: =IF( M$47 >= $E178, $F178 * $F$38 / Cr,) * M$46 -> 0 | N178: =IF( N$47 >= $E178, $F178 * $F$38 / Cr,) * N$46 -> 0 | O178: =IF( O$47 >= $E178, $F178 * $F$38 / Cr,) * O$46 -> 0 | P178: =IF( P$47 >= $E178, $F178 * $F$38 / Cr,) * P$46 -> 0 | Q178: =IF( Q$47 >= $E178, $F178 * $F$38 / Cr,) * Q$46 -> 0 | ... EH178: =IF( EH$47 >= $E178, $F178 * $F$38 / Cr,) * EH$46 -> 0
E179: Financial Lease Receivable | G179: INR Cr | H179: =SUM(J179:EH179) -> 1389.4879 | J179: =SUM( J50:J178 ) -> 0 | K179: =SUM( K50:K178 ) -> 0 | L179: =SUM( L50:L178 ) -> 0 | M179: =SUM( M50:M178 ) -> 0 | N179: =SUM( N50:N178 ) -> 0 | O179: =SUM( O50:O178 ) -> 0 | P179: =SUM( P50:P178 ) -> 0 | Q179: =SUM( Q50:Q178 ) -> 0.0012415216 | ... EH179: =SUM( EH50:EH178 ) -> 0 | EI179: =SUM(EI50:EI178) -> 0 | EJ179: =SUM(EJ50:EJ178) -> 0 | EK179: =SUM(EK50:EK178) -> 0 | EL179: =SUM(EL50:EL178) -> 0 | EM179: =SUM(EM50:EM178) -> 0
A184: End of sheet

Sheet Financials
A1: =RIGHT(CELL("FILENAME", $A$1), LEN(CELL("FILENAME", $A$1)) - SEARCH("]", CELL("FILENAME", $A$1))) -> Financials
E2: =Time_A!E$18 -> Model period beginning_A | J2: =Time_A!J$18 -> 45323 | K2: =Time_A!K$18 -> 45383 | L2: =Time_A!L$18 -> 45748 | M2: =Time_A!M$18 -> 46113 | N2: =Time_A!N$18 -> 46478 | O2: =Time_A!O$18 -> 46844 | P2: =Time_A!P$18 -> 47209 | Q2: =Time_A!Q$18 -> 47574 | ... W2: =Time_A!W$18 -> 49766
E3: =Time_A!E$22 -> Model period ending_A | F3: =Check!E$10 -> Model Check | G3: =Check!F$10 -> 0 | H3: =Check!G$10 -> check | J3: =Time_A!J$22 -> 45382 | K3: =Time_A!K$22 -> 45747 | L3: =Time_A!L$22 -> 46112 | M3: =Time_A!M$22 -> 46477 | N3: =Time_A!N$22 -> 46843 | O3: =Time_A!O$22 -> 47208 | P3: =Time_A!P$22 -> 47573 | Q3: =Time_A!Q$22 -> 47938 | ... W3: =Time_A!W$22 -> 50130
E4: =Time_A!E$35 -> Financial year ending period_A | J4: =Time_A!J$35 -> 45382 | K4: =Time_A!K$35 -> 45747 | L4: =Time_A!L$35 -> 46112 | M4: =Time_A!M$35 -> 46477 | N4: =Time_A!N$35 -> 46843 | O4: =Time_A!O$35 -> 47208 | P4: =Time_A!P$35 -> 47573 | Q4: =Time_A!Q$35 -> 47938 | ... W4: =Time_A!W$35 -> 50130
E5: =Time_A!E$32 -> Financial year ending_A | F5: Constant | G5: Unit | H5: Total | J5: =Time_A!J$32 -> 2024 | K5: =Time_A!K$32 -> 2025 | L5: =Time_A!L$32 -> 2026 | M5: =Time_A!M$32 -> 2027 | N5: =Time_A!N$32 -> 2028 | O5: =Time_A!O$32 -> 2029 | P5: =Time_A!P$32 -> 2030 | Q5: =Time_A!Q$32 -> 2031 | ... W5: =Time_A!W$32 -> 2037
A7: PROFIT AND LOSS STATEMENT
E9: Revenue | G9: INR Cr | H9: =SUM(J9:W9) -> 2487.1873 | J9: =SUMIF('Monthly Financials'!$J$4:$EH$4, J3, 'Monthly Financials'!$J$29:$EH$29) + SUMIF('Monthly Financials'!$J$4:$EH$4, J3, 'Monthly Financials'!$J$30:$EH$30) + SUMIF('Monthly Financials'!$J$4:$EH$4, J3, 'Monthly Financials'!$J$31:$EH$31) -> 0 | K9: =SUMIF('Monthly Financials'!$J$4:$EH$4, K3, 'Monthly Financials'!$J$29:$EH$29) + SUMIF('Monthly Financials'!$J$4:$EH$4, K3, 'Monthly Financials'!$J$30:$EH$30) + SUMIF('Monthly Financials'!$J$4:$EH$4, K3, 'Monthly Financials'!$J$31:$EH$31) -> 91.046121 | L9: =SUMIF('Monthly Financials'!$J$4:$EH$4, L3, 'Monthly Financials'!$J$29:$EH$29) + SUMIF('Monthly Financials'!$J$4:$EH$4, L3, 'Monthly Financials'!$J$30:$EH$30) + SUMIF('Monthly Financials'!$J$4:$EH$4, L3, 'Monthly Financials'!$J$31:$EH$31) -> 447.4241 | M9: =SUMIF('Monthly Financials'!$J$4:$EH$4, M3, 'Monthly Financials'!$J$29:$EH$29) + SUMIF('Monthly Financials'!$J$4:$EH$4, M3, 'Monthly Financials'!$J$30:$EH$30) + SUMIF('Monthly Financials'!$J$4:$EH$4, M3, 'Monthly Financials'!$J$31:$EH$31) -> 305.35966 | N9: =SUMIF('Monthly Financials'!$J$4:$EH$4, N3, 'Monthly Financials'!$J$29:$EH$29) + SUMIF('Monthly Financials'!$J$4:$EH$4, N3, 'Monthly Financials'!$J$30:$EH$30) + SUMIF('Monthly Financials'!$J$4:$EH$4, N3, 'Monthly Financials'!$J$31:$EH$31) -> 264.25449 | O9: =SUMIF('Monthly Financials'!$J$4:$EH$4, O3, 'Monthly Financials'!$J$29:$EH$29) + SUMIF('Monthly Financials'!$J$4:$EH$4, O3, 'Monthly Financials'!$J$30:$EH$30) + SUMIF('Monthly Financials'!$J$4:$EH$4, O3, 'Monthly Financials'!$J$31:$EH$31) -> 264.25449 | P9: =SUMIF('Monthly Financials'!$J$4:$EH$4, P3, 'Monthly Financials'!$J$29:$EH$29) + SUMIF('Monthly Financials'!$J$4:$EH$4, P3, 'Monthly Financials'!$J$30:$EH$30) + SUMIF('Monthly Financials'!$J$4:$EH$4, P3, 'Monthly Financials'!$J$31:$EH$31) -> 264.25449 | Q9: =SUMIF('Monthly Financials'!$J$4:$EH$4, Q3, 'Monthly Financials'!$J$29:$EH$29) + SUMIF('Monthly Financials'!$J$4:$EH$4, Q3, 'Monthly Financials'!$J$30:$EH$30) + SUMIF('Monthly Financials'!$J$4:$EH$4, Q3, 'Monthly Financials'!$J$31:$EH$31) -> 264.25449 | ... W9: =SUMIF('Monthly Financials'!$J$4:$EH$4, W3, 'Monthly Financials'!$J$29:$EH$29) + SUMIF('Monthly Financials'!$J$4:$EH$4, W3, 'Monthly Financials'!$J$30:$EH$30) + SUMIF('Monthly Financials'!$J$4:$EH$4, W3, 'Monthly Financials'!$J$31:$EH$31) -> 0
E10: Total Revenue (Without GST) | G10: INR Cr | H10: =SUM(J10:W10) -> 2487.1873 | J10: =J9 -> 0 | K10: =K9 -> 91.046121 | L10: =L9 -> 447.4241 | M10: =M9 -> 305.35966 | N10: =N9 -> 264.25449 | O10: =O9 -> 264.25449 | P10: =P9 -> 264.25449 | Q10: =Q9 -> 264.25449 | ... W10: =W9 -> 0
E12: ='Monthly Financials'!E119 -> O & M/ FMS + PMC Charges + MDM Charges | G12: INR Cr | H12: =SUM(J12:W12) -> 104.67748 | J12: =SUMIF( 'Monthly Financials'!$J$4:$EH$4, 'Ind AS Financials'!J3, 'Monthly Financials'!$J$119:$EH$119 ) -> 0 | K12: =SUMIF( 'Monthly Financials'!$J$4:$EH$4, 'Ind AS Financials'!K3, 'Monthly Financials'!$J$119:$EH$119 ) -> 0.44668017 | L12: =SUMIF( 'Monthly Financials'!$J$4:$EH$4, 'Ind AS Financials'!L3, 'Monthly Financials'!$J$119:$EH$119 ) -> 6.883139 | M12: =SUMIF( 'Monthly Financials'!$J$4:$EH$4, 'Ind AS Financials'!M3, 'Monthly Financials'!$J$119:$EH$119 ) -> 13.273668 | N12: =SUMIF( 'Monthly Financials'!$J$4:$EH$4, 'Ind AS Financials'!N3, 'Monthly Financials'!$J$119:$EH$119 ) -> 13.451838 | O12: =SUMIF( 'Monthly Financials'!$J$4:$EH$4, 'Ind AS Financials'!O3, 'Monthly Financials'!$J$119:$EH$119 ) -> 13.451838 | P12: =SUMIF( 'Monthly Financials'!$J$4:$EH$4, 'Ind AS Financials'!P3, 'Monthly Financials'!$J$119:$EH$119 ) -> 13.451838 | Q12: =SUMIF( 'Monthly Financials'!$J$4:$EH$4, 'Ind AS Financials'!Q3, 'Monthly Financials'!$J$119:$EH$119 ) -> 13.451838 | ... W12: =SUMIF( 'Monthly Financials'!$J$4:$EH$4, 'Ind AS Financials'!W3, 'Monthly Financials'!$J$119:$EH$119 ) -> 0
E13: ='Monthly Financials'!E120 -> ATS Charges on Softwares | G13: INR Cr | H13: =SUM(J13:W13) -> 63.323413 | J13: =SUMIF('Monthly Financials'!$J$4:$EH$4,'Ind AS Financials'!J3,'Monthly Financials'!$J$120:$EH$120) -> 0 | K13: =SUMIF('Monthly Financials'!$J$4:$EH$4,'Ind AS Financials'!K3,'Monthly Financials'!$J$120:$EH$120) -> 0.27021393 | L13: =SUMIF('Monthly Financials'!$J$4:$EH$4,'Ind AS Financials'!L3,'Monthly Financials'!$J$120:$EH$120) -> 4.1638742 | M13: =SUMIF('Monthly Financials'!$J$4:$EH$4,'Ind AS Financials'!M3,'Monthly Financials'!$J$120:$EH$120) -> 8.0297501 | N13: =SUMIF('Monthly Financials'!$J$4:$EH$4,'Ind AS Financials'!N3,'Monthly Financials'!$J$120:$EH$120) -> 8.1375319 | O13: =SUMIF('Monthly Financials'!$J$4:$EH$4,'Ind AS Financials'!O3,'Monthly Financials'!$J$120:$EH$120) -> 8.1375319 | P13: =SUMIF('Monthly Financials'!$J$4:$EH$4,'Ind AS Financials'!P3,'Monthly Financials'!$J$120:$EH$120) -> 8.1375319 | Q13: =SUMIF('Monthly Financials'!$J$4:$EH$4,'Ind AS Financials'!Q3,'Monthly Financials'!$J$120:$EH$120) -> 8.1375319 | ... W13: =SUMIF('Monthly Financials'!$J$4:$EH$4,'Ind AS Financials'!W3,'Monthly Financials'!$J$120:$EH$120) -> 0
E14: ='Monthly Financials'!E121 -> Cloud Hosting Charges | G14: INR Cr | H14: =SUM(J14:W14) -> 72.369615 | J14: =SUMIF('Monthly Financials'!$J$4:$EH$4,'Ind AS Financials'!J3,'Monthly Financials'!$J$121:$EH$121) -> 0 | K14: =SUMIF('Monthly Financials'!$J$4:$EH$4,'Ind AS Financials'!K3,'Monthly Financials'!$J$121:$EH$121) -> 0.30881592 | L14: =SUMIF('Monthly Financials'!$J$4:$EH$4,'Ind AS Financials'!L3,'Monthly Financials'!$J$121:$EH$121) -> 4.7587134 | M14: =SUMIF('Monthly Financials'!$J$4:$EH$4,'Ind AS Financials'!M3,'Monthly Financials'!$J$121:$EH$121) -> 9.1768572 | N14: =SUMIF('Monthly Financials'!$J$4:$EH$4,'Ind AS Financials'!N3,'Monthly Financials'!$J$121:$EH$121) -> 9.3000365 | O14: =SUMIF('Monthly Financials'!$J$4:$EH$4,'Ind AS Financials'!O3,'Monthly Financials'!$J$121:$EH$121) -> 9.3000365 | P14: =SUMIF('Monthly Financials'!$J$4:$EH$4,'Ind AS Financials'!P3,'Monthly Financials'!$J$121:$EH$121) -> 9.3000365 | Q14: =SUMIF('Monthly Financials'!$J$4:$EH$4,'Ind AS Financials'!Q3,'Monthly Financials'!$J$121:$EH$121) -> 9.3000365 | ... W14: =SUMIF('Monthly Financials'!$J$4:$EH$4,'Ind AS Financials'!W3,'Monthly Financials'!$J$121:$EH$121) -> 0
E15: ='Monthly Financials'!E122 -> GPRS Charges for GPRS Meters | G15: INR Cr | H15: =SUM(J15:W15) -> 157.68822 | J15: =SUMIF('Monthly Financials'!$J$4:$EH$4,'Ind AS Financials'!J3,'Monthly Financials'!$J$122:$EH$122) -> 0 | K15: =SUMIF('Monthly Financials'!$J$4:$EH$4,'Ind AS Financials'!K3,'Monthly Financials'!$J$122:$EH$122) -> 0.67288783 | L15: =SUMIF('Monthly Financials'!$J$4:$EH$4,'Ind AS Financials'!L3,'Monthly Financials'!$J$122:$EH$122) -> 10.368897 | M15: =SUMIF('Monthly Financials'!$J$4:$EH$4,'Ind AS Financials'!M3,'Monthly Financials'!$J$122:$EH$122) -> 19.995716 | N15: =SUMIF('Monthly Financials'!$J$4:$EH$4,'Ind AS Financials'!N3,'Monthly Financials'!$J$122:$EH$122) -> 20.264115 | O15: =SUMIF('Monthly Financials'!$J$4:$EH$4,'Ind AS Financials'!O3,'Monthly Financials'!$J$122:$EH$122) -> 20.264115 | P15: =SUMIF('Monthly Financials'!$J$4:$EH$4,'Ind AS Financials'!P3,'Monthly Financials'!$J$122:$EH$122) -> 20.264115 | Q15: =SUMIF('Monthly Financials'!$J$4:$EH$4,'Ind AS Financials'!Q3,'Monthly Financials'!$J$122:$EH$122) -> 20.264115 | ... W15: =SUMIF('Monthly Financials'!$J$4:$EH$4,'Ind AS Financials'!W3,'Monthly Financials'!$J$122:$EH$122) -> 0
E16: ='Monthly Financials'!E123 -> Site Mandays Cost | G16: INR Cr | H16: =SUM(J16:W16) -> 83.246 | J16: =SUMIF('Monthly Financials'!$J$4:$EH$4,'Ind AS Financials'!J3,'Monthly Financials'!$J$123:$EH$123) -> 0 | K16: =SUMIF('Monthly Financials'!$J$4:$EH$4,'Ind AS Financials'!K3,'Monthly Financials'!$J$123:$EH$123) -> 6.224 | L16: =SUMIF('Monthly Financials'!$J$4:$EH$4,'Ind AS Financials'!L3,'Monthly Financials'!$J$123:$EH$123) -> 9.336 | M16: =SUMIF('Monthly Financials'!$J$4:$EH$4,'Ind AS Financials'!M3,'Monthly Financials'!$J$123:$EH$123) -> 9.336 | N16: =SUMIF('Monthly Financials'!$J$4:$EH$4,'Ind AS Financials'!N3,'Monthly Financials'!$J$123:$EH$123) -> 9.336 | O16: =SUMIF('Monthly Financials'!$J$4:$EH$4,'Ind AS Financials'!O3,'Monthly Financials'!$J$123:$EH$123) -> 9.336 | P16: =SUMIF('Monthly Financials'!$J$4:$EH$4,'Ind AS Financials'!P3,'Monthly Financials'!$J$123:$EH$123) -> 9.336 | Q16: =SUMIF('Monthly Financials'!$J$4:$EH$4,'Ind AS Financials'!Q3,'Monthly Financials'!$J$123:$EH$123) -> 9.336 | ... W16: =SUMIF('Monthly Financials'!$J$4:$EH$4,'Ind AS Financials'!W3,'Monthly Financials'!$J$123:$EH$123) -> 0
E17: ='Monthly Financials'!E124 -> Site Running+Auditor+Training Cost | G17: INR Cr | H17: =SUM(J17:W17) -> 30.281 | J17: =SUMIF('Monthly Financials'!$J$4:$EH$4,'Ind AS Financials'!J3,'Monthly Financials'!$J$124:$EH$124) -> 0 | K17: =SUMIF('Monthly Financials'!$J$4:$EH$4,'Ind AS Financials'!K3,'Monthly Financials'!$J$124:$EH$124) -> 2.264 | L17: =SUMIF('Monthly Financials'!$J$4:$EH$4,'Ind AS Financials'!L3,'Monthly Financials'!$J$124:$EH$124) -> 3.396 | M17: =SUMIF('Monthly Financials'!$J$4:$EH$4,'Ind AS Financials'!M3,'Monthly Financials'!$J$124:$EH$124) -> 3.396 | N17: =SUMIF('Monthly Financials'!$J$4:$EH$4,'Ind AS Financials'!N3,'Monthly Financials'!$J$124:$EH$124) -> 3.396 | O17: =SUMIF('Monthly Financials'!$J$4:$EH$4,'Ind AS Financials'!O3,'Monthly Financials'!$J$124:$EH$124) -> 3.396 | P17: =SUMIF('Monthly Financials'!$J$4:$EH$4,'Ind AS Financials'!P3,'Monthly Financials'!$J$124:$EH$124) -> 3.396 | Q17: =SUMIF('Monthly Financials'!$J$4:$EH$4,'Ind AS Financials'!Q3,'Monthly Financials'!$J$124:$EH$124) -> 3.396 | ... W17: =SUMIF('Monthly Financials'!$J$4:$EH$4,'Ind AS Financials'!W3,'Monthly Financials'!$J$124:$EH$124) -> 0
E18: ='Monthly Financials'!E125 -> Travel Cost | G18: INR Cr | H18: =SUM(J18:W18) -> 10.486 | J18: =SUMIF('Monthly Financials'!$J$4:$EH$4,'Ind AS Financials'!J3,'Monthly Financials'!$J$125:$EH$125) -> 0 | K18: =SUMIF('Monthly Financials'!$J$4:$EH$4,'Ind AS Financials'!K3,'Monthly Financials'!$J$125:$EH$125) -> 0.784 | L18: =SUMIF('Monthly Financials'!$J$4:$EH$4,'Ind AS Financials'!L3,'Monthly Financials'!$J$125:$EH$125) -> 1.176 | M18: =SUMIF('Monthly Financials'!$J$4:$EH$4,'Ind AS Financials'!M3,'Monthly Financials'!$J$125:$EH$125) -> 1.176 | N18: =SUMIF('Monthly Financials'!$J$4:$EH$4,'Ind AS Financials'!N3,'Monthly Financials'!$J$125:$EH$125) -> 1.176 | O18: =SUMIF('Monthly Financials'!$J$4:$EH$4,'Ind AS Financials'!O3,'Monthly Financials'!$J$125:$EH$125) -> 1.176 | P18: =SUMIF('Monthly Financials'!$J$4:$EH$4,'Ind AS Financials'!P3,'Monthly Financials'!$J$125:$EH$125) -> 1.176 | Q18: =SUMIF('Monthly Financials'!$J$4:$EH$4,'Ind AS Financials'!Q3,'Monthly Financials'!$J$125:$EH$125) -> 1.176 | ... W18: =SUMIF('Monthly Financials'!$J$4:$EH$4,'Ind AS Financials'!W3,'Monthly Financials'!$J$125:$EH$125) -> 0
E19: ='Monthly Financials'!E126 -> BG, Insurance Cost & Fin. Compliance Cost | G19: INR Cr | H19: =SUM(J19:W19) -> 32.635 | J19: =SUMIF('Monthly Financials'!$J$4:$EH$4,'Ind AS Financials'!J3,'Monthly Financials'!$J$126:$EH$126) -> 0 | K19: =SUMIF('Monthly Financials'!$J$4:$EH$4,'Ind AS Financials'!K3,'Monthly Financials'!$J$126:$EH$126) -> 2.44 | L19: =SUMIF('Monthly Financials'!$J$4:$EH$4,'Ind AS Financials'!L3,'Monthly Financials'!$J$126:$EH$126) -> 3.66 | M19: =SUMIF('Monthly Financials'!$J$4:$EH$4,'Ind AS Financials'!M3,'Monthly Financials'!$J$126:$EH$126) -> 3.66 | N19: =SUMIF('Monthly Financials'!$J$4:$EH$4,'Ind AS Financials'!N3,'Monthly Financials'!$J$126:$EH$126) -> 3.66 | O19: =SUMIF('Monthly Financials'!$J$4:$EH$4,'Ind AS Financials'!O3,'Monthly Financials'!$J$126:$EH$126) -> 3.66 | P19: =SUMIF('Monthly Financials'!$J$4:$EH$4,'Ind AS Financials'!P3,'Monthly Financials'!$J$126:$EH$126) -> 3.66 | Q19: =SUMIF('Monthly Financials'!$J$4:$EH$4,'Ind AS Financials'!Q3,'Monthly Financials'!$J$126:$EH$126) -> 3.66 | ... W19: =SUMIF('Monthly Financials'!$J$4:$EH$4,'Ind AS Financials'!W3,'Monthly Financials'!$J$126:$EH$126) -> 0
E20: ='Monthly Financials'!E128 -> Penalty - SLA | G20: INR Cr | H20: =SUM(J20:W20) -> 13.005905 | J20: =SUMIF('Monthly Financials'!$J$4:$EH$4,'Ind AS Financials'!J4,'Monthly Financials'!$J$128:$EH$128) -> 0 | K20: =SUMIF('Monthly Financials'!$J$4:$EH$4,'Ind AS Financials'!K4,'Monthly Financials'!$J$128:$EH$128) -> 0.17289541 | L20: =SUMIF('Monthly Financials'!$J$4:$EH$4,'Ind AS Financials'!L4,'Monthly Financials'!$J$128:$EH$128) -> 2.704315 | M20: =SUMIF('Monthly Financials'!$J$4:$EH$4,'Ind AS Financials'!M4,'Monthly Financials'!$J$128:$EH$128) -> 1.9119075 | N20: =SUMIF('Monthly Financials'!$J$4:$EH$4,'Ind AS Financials'!N4,'Monthly Financials'!$J$128:$EH$128) -> 1.3212725 | O20: =SUMIF('Monthly Financials'!$J$4:$EH$4,'Ind AS Financials'!O4,'Monthly Financials'!$J$128:$EH$128) -> 1.3212725 | P20: =SUMIF('Monthly Financials'!$J$4:$EH$4,'Ind AS Financials'!P4,'Monthly Financials'!$J$128:$EH$128) -> 1.3212725 | Q20: =SUMIF('Monthly Financials'!$J$4:$EH$4,'Ind AS Financials'!Q4,'Monthly Financials'!$J$128:$EH$128) -> 1.3212725 | ... W20: =SUMIF('Monthly Financials'!$J$4:$EH$4,'Ind AS Financials'!W4,'Monthly Financials'!$J$128:$EH$128) -> 0
E21: Installation of Armoured Cables | G21: INR Cr | H21: =SUM(J21:W21) -> 189.8453 | J21: =SUMIF('Monthly Financials'!$J$4:$EH$4,'Ind AS Financials'!J3,'Monthly Financials'!$J$127:$EH$127) -> 0 | K21: =SUMIF('Monthly Financials'!$J$4:$EH$4,'Ind AS Financials'!K3,'Monthly Financials'!$J$127:$EH$127) -> 43.164018 | L21: =SUMIF('Monthly Financials'!$J$4:$EH$4,'Ind AS Financials'!L3,'Monthly Financials'!$J$127:$EH$127) -> 136.90989 | M21: =SUMIF('Monthly Financials'!$J$4:$EH$4,'Ind AS Financials'!M3,'Monthly Financials'!$J$127:$EH$127) -> 9.7713947 | N21: =SUMIF('Monthly Financials'!$J$4:$EH$4,'Ind AS Financials'!N3,'Monthly Financials'!$J$127:$EH$127) -> 0 | O21: =SUMIF('Monthly Financials'!$J$4:$EH$4,'Ind AS Financials'!O3,'Monthly Financials'!$J$127:$EH$127) -> 0 | P21: =SUMIF('Monthly Financials'!$J$4:$EH$4,'Ind AS Financials'!P3,'Monthly Financials'!$J$127:$EH$127) -> 0 | Q21: =SUMIF('Monthly Financials'!$J$4:$EH$4,'Ind AS Financials'!Q3,'Monthly Financials'!$J$127:$EH$127) -> 0 | ... W21: =SUMIF('Monthly Financials'!$J$4:$EH$4,'Ind AS Financials'!W3,'Monthly Financials'!$J$127:$EH$127) -> 0
E22: Total Expenses (Without GST) | G22: INR Cr | H22: =SUM(J22:W22) -> 757.55793 | J22: =SUM(J12:J21) -> 0 | K22: =SUM(K12:K21) -> 56.747511 | L22: =SUM(L12:L21) -> 183.35682 | M22: =SUM(M12:M21) -> 79.727294 | N22: =SUM(N12:N21) -> 70.042795 | O22: =SUM(O12:O21) -> 70.042795 | P22: =SUM(P12:P21) -> 70.042795 | Q22: =SUM(Q12:Q21) -> 70.042795 | ... W22: =SUM(W12:W21) -> 0
E24: EBITDA | G24: INR Cr | H24: =SUM(J24:W24) -> 1729.6293 | J24: =J10-J22 -> 0 | K24: =K10-K22 -> 34.298609 | L24: =L10-L22 -> 264.06727 | M24: =M10-M22 -> 225.63236 | N24: =N10-N22 -> 194.2117 | O24: =O10-O22 -> 194.2117 | P24: =P10-P22 -> 194.2117 | Q24: =Q10-Q22 -> 194.2117 | ... W24: =W10-W22 -> 0
E25: EBITDA margin | G25: % | H25: =IFERROR(H24 / H$9, 0) -> 0.6954158 | J25: =IFERROR(J24 / J$10, 0) -> 0 | K25: =IFERROR(K24 / K$10, 0) -> 0.37671687 | L25: =IFERROR(L24 / L$10, 0) -> 0.59019457 | M25: =IFERROR(M24 / M$10, 0) -> 0.73890692 | N25: =IFERROR(N24 / N$10, 0) -> 0.7349419 | O25: =IFERROR(O24 / O$10, 0) -> 0.7349419 | P25: =IFERROR(P24 / P$10, 0) -> 0.7349419 | Q25: =IFERROR(Q24 / Q$10, 0) -> 0.7349419 | ... W25: =IFERROR(W24 / W$10, 0) -> 0
E27: Depreciation | G27: INR Cr | H27: =SUM(J27:W27) -> 1058.3969 | J27: =IF( NTBA!$F$270 ="SLM", 'Dep&Tax'!J14, 'Dep&Tax'!J25 ) -> 0 | K27: =IF( NTBA!$F$270 ="SLM", 'Dep&Tax'!K14, 'Dep&Tax'!K25 ) -> 3.7127338 | L27: =IF( NTBA!$F$270 ="SLM", 'Dep&Tax'!L14, 'Dep&Tax'!L25 ) -> 68.893661 | M27: =IF( NTBA!$F$270 ="SLM", 'Dep&Tax'!M14, 'Dep&Tax'!M25 ) -> 148.59962 | N27: =IF( NTBA!$F$270 ="SLM", 'Dep&Tax'!N14, 'Dep&Tax'!N25 ) -> 153.02123 | O27: =IF( NTBA!$F$270 ="SLM", 'Dep&Tax'!O14, 'Dep&Tax'!O25 ) -> 153.02123 | P27: =IF( NTBA!$F$270 ="SLM", 'Dep&Tax'!P14, 'Dep&Tax'!P25 ) -> 153.02123 | Q27: =IF( NTBA!$F$270 ="SLM", 'Dep&Tax'!Q14, 'Dep&Tax'!Q25 ) -> 153.02123 | ... W27: =IF( NTBA!$F$270 ="SLM", 'Dep&Tax'!W14, 'Dep&Tax'!W25 ) -> 0
E29: EBIT | G29: INR Cr | H29: =SUM(J29:W29) -> 671.23248 | J29: =J24-J27 -> 0 | K29: =K24-K27 -> 30.585876 | L29: =L24-L27 -> 195.17361 | M29: =M24-M27 -> 77.032748 | N29: =N24-N27 -> 41.190469 | O29: =O24-O27 -> 41.190469 | P29: =P24-P27 -> 41.190469 | Q29: =Q24-Q27 -> 41.190469 | ... W29: =W24-W27 -> 0
E30: EBIT margin | G30: % | H30: =IFERROR(H29 / H$9, 0) -> 0.26987613 | J30: =IFERROR(J29 / J$10, 0) -> 0 | K30: =IFERROR(K29 / K$10, 0) -> 0.33593826 | L30: =IFERROR(L29 / L$10, 0) -> 0.43621614 | M30: =IFERROR(M29 / M$10, 0) -> 0.25226891 | N30: =IFERROR(N29 / N$10, 0) -> 0.15587424 | O30: =IFERROR(O29 / O$10, 0) -> 0.15587424 | P30: =IFERROR(P29 / P$10, 0) -> 0.15587424 | Q30: =IFERROR(Q29 / Q$10, 0) -> 0.15587424 | ... W30: =IFERROR(W29 / W$10, 0) -> 0
E32: Interest on Term Loan | G32: INR Cr | H32: =SUM(J32:W32) -> 273.39948 | J32: =SUMIF(Rollout!$J$4:$EH$4,J$3,Rollout!$J$219:$EH$219) -> 0 | K32: =SUMIF(Rollout!$J$4:$EH$4,K$3,Rollout!$J$219:$EH$219) -> 4.8793082 | L32: =SUMIF(Rollout!$J$4:$EH$4,L$3,Rollout!$J$219:$EH$219) -> 54.146034 | M32: =SUMIF(Rollout!$J$4:$EH$4,M$3,Rollout!$J$219:$EH$219) -> 67.949969 | N32: =SUMIF(Rollout!$J$4:$EH$4,N$3,Rollout!$J$219:$EH$219) -> 51.628901 | O32: =SUMIF(Rollout!$J$4:$EH$4,O$3,Rollout!$J$219:$EH$219) -> 41.423802 | P32: =SUMIF(Rollout!$J$4:$EH$4,P$3,Rollout!$J$219:$EH$219) -> 30.247304 | Q32: =SUMIF(Rollout!$J$4:$EH$4,Q$3,Rollout!$J$219:$EH$219) -> 18.034466 | ... W32: =SUMIF(Rollout!$J$4:$EH$4,W$3,Rollout!$J$219:$EH$219) -> 0
E33: Interest on Working Capital | G33: INR Cr | H33: =SUM(J33:W33) -> 0 | J33: =SUMIF('Monthly Financials'!$J$4:$EH$4,'Ind AS Financials'!J3,'Monthly Financials'!$J$224:$EH$224) -> 0 | K33: =SUMIF('Monthly Financials'!$J$4:$EH$4,'Ind AS Financials'!K3,'Monthly Financials'!$J$224:$EH$224) -> 0 | L33: =SUMIF('Monthly Financials'!$J$4:$EH$4,'Ind AS Financials'!L3,'Monthly Financials'!$J$224:$EH$224) -> 0 | M33: =SUMIF('Monthly Financials'!$J$4:$EH$4,'Ind AS Financials'!M3,'Monthly Financials'!$J$224:$EH$224) -> 0 | N33: =SUMIF('Monthly Financials'!$J$4:$EH$4,'Ind AS Financials'!N3,'Monthly Financials'!$J$224:$EH$224) -> 0 | O33: =SUMIF('Monthly Financials'!$J$4:$EH$4,'Ind AS Financials'!O3,'Monthly Financials'!$J$224:$EH$224) -> 0 | P33: =SUMIF('Monthly Financials'!$J$4:$EH$4,'Ind AS Financials'!P3,'Monthly Financials'!$J$224:$EH$224) -> 0 | Q33: =SUMIF('Monthly Financials'!$J$4:$EH$4,'Ind AS Financials'!Q3,'Monthly Financials'!$J$224:$EH$224) -> 0 | ... W33: =SUMIF('Monthly Financials'!$J$4:$EH$4,'Ind AS Financials'!W3,'Monthly Financials'!$J$224:$EH$224) -> 0
E34: Interest on Shareholder Loan (Project Cost) | G34: INR Cr | H34: =SUM(J34:W34) -> 0 | J34: =SUMIF(Rollout!$J$4:$EH$4,'Ind AS Financials'!J3,Rollout!$J$235:$EH$235) -> 0 | K34: =SUMIF(Rollout!$J$4:$EH$4,'Ind AS Financials'!K3,Rollout!$J$235:$EH$235) -> 0 | L34: =SUMIF(Rollout!$J$4:$EH$4,'Ind AS Financials'!L3,Rollout!$J$235:$EH$235) -> 0 | M34: =SUMIF(Rollout!$J$4:$EH$4,'Ind AS Financials'!M3,Rollout!$J$235:$EH$235) -> 0 | N34: =SUMIF(Rollout!$J$4:$EH$4,'Ind AS Financials'!N3,Rollout!$J$235:$EH$235) -> 0 | O34: =SUMIF(Rollout!$J$4:$EH$4,'Ind AS Financials'!O3,Rollout!$J$235:$EH$235) -> 0 | P34: =SUMIF(Rollout!$J$4:$EH$4,'Ind AS Financials'!P3,Rollout!$J$235:$EH$235) -> 0 | Q34: =SUMIF(Rollout!$J$4:$EH$4,'Ind AS Financials'!Q3,Rollout!$J$235:$EH$235) -> 0 | ... W34: =SUMIF(Rollout!$J$4:$EH$4,'Ind AS Financials'!W3,Rollout!$J$235:$EH$235) -> 0
E35: Interest on Shareholder loan (Cash Shortfall Funding) | G35: INR Cr | H35: =SUM(J35:W35) -> 0 | J35: =IFERROR(J191,0) -> 0 | K35: =IFERROR(K191,0) -> 0 | L35: =IFERROR(L191,0) -> 0 | M35: =IFERROR(M191,0) -> 0 | N35: =IFERROR(N191,0) -> 0 | O35: =IFERROR(O191,0) -> 0 | P35: =IFERROR(P191,0) -> 0 | Q35: =IFERROR(Q191,0) -> 0 | ... W35: =IFERROR(W191,0) -> 0
E36: PBT | G36: INR Cr | H36: =SUM(J36:W36) -> 397.83299 | J36: =J29 -J32 -J33 -J34 -J35 -> 0 | K36: =K29 -K32 -K33 -K34 -K35 -> 25.706567 | L36: =L29 -L32 -L33 -L34 -L35 -> 141.02758 | M36: =M29 -M32 -M33 -M34 -M35 -> 9.0827793 | N36: =N29 -N32 -N33 -N34 -N35 -> -10.438433 | O36: =O29 -O32 -O33 -O34 -O35 -> -0.2333331 | P36: =P29 -P32 -P33 -P34 -P35 -> 10.943165 | Q36: =Q29 -Q32 -Q33 -Q34 -Q35 -> 23.156003 | ... W36: =W29 -W32 -W33 -W34 -W35 -> 0
E37: PBT margin | G37: % | H37: =IFERROR(H36 / H$9, 0) -> 0.15995297 | J37: =IFERROR(J36 / J$10, 0) -> 0 | K37: =IFERROR(K36 / K$10, 0) -> 0.28234665 | L37: =IFERROR(L36 / L$10, 0) -> 0.31519889 | M37: =IFERROR(M36 / M$10, 0) -> 0.029744529 | N37: =IFERROR(N36 / N$10, 0) -> -0.039501438 | O37: =IFERROR(O36 / O$10, 0) -> -0.00088298629 | P37: =IFERROR(P36 / P$10, 0) -> 0.041411463 | Q37: =IFERROR(Q36 / Q$10, 0) -> 0.087627659 | ... W37: =IFERROR(W36 / W$10, 0) -> 0
E39: Tax | G39: INR Cr | H39: =SUM(J39:W39) -> 43.910953 | J39: =SUMIF('Dep&Tax'!$J$5:$W$5,J$5,'Dep&Tax'!$J$104:$W$104)+SUMIF('Dep&Tax'!$J$5:$W$5,J$5,'Dep&Tax'!$J$111:$W$111) -> 0 | K39: =SUMIF('Dep&Tax'!$J$5:$W$5,K$5,'Dep&Tax'!$J$104:$W$104)+SUMIF('Dep&Tax'!$J$5:$W$5,K$5,'Dep&Tax'!$J$111:$W$111) -> 8.1568812 | L39: =SUMIF('Dep&Tax'!$J$5:$W$5,L$5,'Dep&Tax'!$J$104:$W$104)+SUMIF('Dep&Tax'!$J$5:$W$5,L$5,'Dep&Tax'!$J$111:$W$111) -> 61.033282 | M39: =SUMIF('Dep&Tax'!$J$5:$W$5,M$5,'Dep&Tax'!$J$104:$W$104)+SUMIF('Dep&Tax'!$J$5:$W$5,M$5,'Dep&Tax'!$J$111:$W$111) -> 34.16588 | N39: =SUMIF('Dep&Tax'!$J$5:$W$5,N$5,'Dep&Tax'!$J$104:$W$104)+SUMIF('Dep&Tax'!$J$5:$W$5,N$5,'Dep&Tax'!$J$111:$W$111) -> 4.4268755 | O39: =SUMIF('Dep&Tax'!$J$5:$W$5,O$5,'Dep&Tax'!$J$104:$W$104)+SUMIF('Dep&Tax'!$J$5:$W$5,O$5,'Dep&Tax'!$J$111:$W$111) -> -12.748828 | P39: =SUMIF('Dep&Tax'!$J$5:$W$5,P$5,'Dep&Tax'!$J$104:$W$104)+SUMIF('Dep&Tax'!$J$5:$W$5,P$5,'Dep&Tax'!$J$111:$W$111) -> -23.05425 | Q39: =SUMIF('Dep&Tax'!$J$5:$W$5,Q$5,'Dep&Tax'!$J$104:$W$104)+SUMIF('Dep&Tax'!$J$5:$W$5,Q$5,'Dep&Tax'!$J$111:$W$111) -> -29.237504 | ... W39: =SUMIF('Dep&Tax'!$J$5:$W$5,W$5,'Dep&Tax'!$J$104:$W$104)+SUMIF('Dep&Tax'!$J$5:$W$5,W$5,'Dep&Tax'!$J$111:$W$111) -> 0
E41: PAT | G41: INR Cr | H41: =SUM(J41:W41) -> 353.92204 | J41: =J36-J39 -> 0 | K41: =K36-K39 -> 17.549686 | L41: =L36-L39 -> 79.994296 | M41: =M36-M39 -> -25.083101 | N41: =N36-N39 -> -14.865308 | O41: =O36-O39 -> 12.515495 | P41: =P36-P39 -> 33.997416 | Q41: =Q36-Q39 -> 52.393506 | ... W41: =W36-W39 -> 0
E42: Net Income margin | G42: % | H42: =IFERROR(H41 / H$9, 0) -> 0.14229811 | J42: =IFERROR(J41 / J$10, 0) -> 0 | K42: =IFERROR(K41 / K$10, 0) -> 0.192756 | L42: =IFERROR(L41 / L$10, 0) -> 0.17878853 | M42: =IFERROR(M41 / M$10, 0) -> -0.082142811 | N42: =IFERROR(N41 / N$10, 0) -> -0.056253757 | O42: =IFERROR(O41 / O$10, 0) -> 0.047361522 | P42: =IFERROR(P41 / P$10, 0) -> 0.12865407 | Q42: =IFERROR(Q41 / Q$10, 0) -> 0.19826912 | ... W42: =IFERROR(W41 / W$10, 0) -> 0
A45: CASH FLOW STATEMENT
B47: Cash from Operating Activities
E48: AMISP Service Charge on Meters Installed (Cash Basis) | G48: INR Cr | H48: =SUM(J48:W48) -> 2047.9723 | J48: =SUMIF('Monthly Financials'!$J$4:$EH$4,J$3,'Monthly Financials'!$J$70:$EH$70) -> 0 | K48: =SUMIF('Monthly Financials'!$J$4:$EH$4,K$3,'Monthly Financials'!$J$70:$EH$70) -> 8.6447706 | L48: =SUMIF('Monthly Financials'!$J$4:$EH$4,L$3,'Monthly Financials'!$J$70:$EH$70) -> 135.21575 | M48: =SUMIF('Monthly Financials'!$J$4:$EH$4,M$3,'Monthly Financials'!$J$70:$EH$70) -> 260.75444 | N48: =SUMIF('Monthly Financials'!$J$4:$EH$4,N$3,'Monthly Financials'!$J$70:$EH$70) -> 264.25449 | O48: =SUMIF('Monthly Financials'!$J$4:$EH$4,O$3,'Monthly Financials'!$J$70:$EH$70) -> 264.25449 | P48: =SUMIF('Monthly Financials'!$J$4:$EH$4,P$3,'Monthly Financials'!$J$70:$EH$70) -> 264.25449 | Q48: =SUMIF('Monthly Financials'!$J$4:$EH$4,Q$3,'Monthly Financials'!$J$70:$EH$70) -> 264.25449 | ... W48: =SUMIF('Monthly Financials'!$J$4:$EH$4,W$3,'Monthly Financials'!$J$70:$EH$70) -> 0
E49: GST Received on AMISP Service Charge | G49: INR Cr | H49: =SUM(J49:W49) -> 447.69371 | J49: =SUMIF('Monthly Financials'!$J$4:$EH$4,J$3,'Monthly Financials'!$J$80:$EH$80) -> 0 | K49: =SUMIF('Monthly Financials'!$J$4:$EH$4,K$3,'Monthly Financials'!$J$80:$EH$80) -> 9.5831554 | L49: =SUMIF('Monthly Financials'!$J$4:$EH$4,L$3,'Monthly Financials'!$J$80:$EH$80) -> 49.799599 | M49: =SUMIF('Monthly Financials'!$J$4:$EH$4,M$3,'Monthly Financials'!$J$80:$EH$80) -> 92.506623 | N49: =SUMIF('Monthly Financials'!$J$4:$EH$4,N$3,'Monthly Financials'!$J$80:$EH$80) -> 47.565809 | O49: =SUMIF('Monthly Financials'!$J$4:$EH$4,O$3,'Monthly Financials'!$J$80:$EH$80) -> 47.565809 | P49: =SUMIF('Monthly Financials'!$J$4:$EH$4,P$3,'Monthly Financials'!$J$80:$EH$80) -> 47.565809 | Q49: =SUMIF('Monthly Financials'!$J$4:$EH$4,Q$3,'Monthly Financials'!$J$80:$EH$80) -> 47.565809 | ... W49: =SUMIF('Monthly Financials'!$J$4:$EH$4,W$3,'Monthly Financials'!$J$80:$EH$80) -> 0
E50: Internal Accrual (upfront payment from DISCOM) not utilised as Equity | G50: INR Cr | H50: =SUM(J50:W50) -> 243.07592 | J50: =SUMIF('Monthly Financials'!$J$4:$EH$4,'Ind AS Financials'!J3,'Monthly Financials'!$J$68:$EH$68)-J70 -> 0 | K50: =SUMIF('Monthly Financials'!$J$4:$EH$4,'Ind AS Financials'!K3,'Monthly Financials'!$J$68:$EH$68)-K70 -> 0 | L50: =SUMIF('Monthly Financials'!$J$4:$EH$4,'Ind AS Financials'!L3,'Monthly Financials'!$J$68:$EH$68)-L70 -> 0 | M50: =SUMIF('Monthly Financials'!$J$4:$EH$4,'Ind AS Financials'!M3,'Monthly Financials'!$J$68:$EH$68)-M70 -> 243.07592 | N50: =SUMIF('Monthly Financials'!$J$4:$EH$4,'Ind AS Financials'!N3,'Monthly Financials'!$J$68:$EH$68)-N70 -> 0 | O50: =SUMIF('Monthly Financials'!$J$4:$EH$4,'Ind AS Financials'!O3,'Monthly Financials'!$J$68:$EH$68)-O70 -> 0 | P50: =SUMIF('Monthly Financials'!$J$4:$EH$4,'Ind AS Financials'!P3,'Monthly Financials'!$J$68:$EH$68)-P70 -> 0 | Q50: =SUMIF('Monthly Financials'!$J$4:$EH$4,'Ind AS Financials'!Q3,'Monthly Financials'!$J$68:$EH$68)-Q70 -> 0 | ... W50: =SUMIF('Monthly Financials'!$J$4:$EH$4,'Ind AS Financials'!W3,'Monthly Financials'!$J$68:$EH$68)-W70 -> 0
E51: Upfront Payment for Cables | G51: INR Cr | H51: =SUM(J51:W51) -> 196.13901 | J51: =SUMIF('Monthly Financials'!$J$4:$EH$4,'Ind AS Financials'!J3,'Monthly Financials'!$J$69:$EH$69) -> 0 | K51: =SUMIF('Monthly Financials'!$J$4:$EH$4,'Ind AS Financials'!K3,'Monthly Financials'!$J$69:$EH$69) -> 44.594981 | L51: =SUMIF('Monthly Financials'!$J$4:$EH$4,'Ind AS Financials'!L3,'Monthly Financials'!$J$69:$EH$69) -> 141.44869 | M51: =SUMIF('Monthly Financials'!$J$4:$EH$4,'Ind AS Financials'!M3,'Monthly Financials'!$J$69:$EH$69) -> 10.095334 | N51: =SUMIF('Monthly Financials'!$J$4:$EH$4,'Ind AS Financials'!N3,'Monthly Financials'!$J$69:$EH$69) -> 0 | O51: =SUMIF('Monthly Financials'!$J$4:$EH$4,'Ind AS Financials'!O3,'Monthly Financials'!$J$69:$EH$69) -> 0 | P51: =SUMIF('Monthly Financials'!$J$4:$EH$4,'Ind AS Financials'!P3,'Monthly Financials'!$J$69:$EH$69) -> 0 | Q51: =SUMIF('Monthly Financials'!$J$4:$EH$4,'Ind AS Financials'!Q3,'Monthly Financials'!$J$69:$EH$69) -> 0 | ... W51: =SUMIF('Monthly Financials'!$J$4:$EH$4,'Ind AS Financials'!W3,'Monthly Financials'!$J$69:$EH$69) -> 0
E52: Opex Payment (incl. GST ) | G52: INR Cr | H52: =SUM(J52:W52) -> -893.91836 | J52: =- 1 * SUMIF('Monthly Financials'!$J$4:$EH$4,J$3,'Monthly Financials'!$J$162:$EH$162) -> 0 | K52: =- 1 * SUMIF('Monthly Financials'!$J$4:$EH$4,K$3,'Monthly Financials'!$J$162:$EH$162) -> -66.962063 | L52: =- 1 * SUMIF('Monthly Financials'!$J$4:$EH$4,L$3,'Monthly Financials'!$J$162:$EH$162) -> -216.36105 | M52: =- 1 * SUMIF('Monthly Financials'!$J$4:$EH$4,M$3,'Monthly Financials'!$J$162:$EH$162) -> -94.078207 | N52: =- 1 * SUMIF('Monthly Financials'!$J$4:$EH$4,N$3,'Monthly Financials'!$J$162:$EH$162) -> -82.650498 | O52: =- 1 * SUMIF('Monthly Financials'!$J$4:$EH$4,O$3,'Monthly Financials'!$J$162:$EH$162) -> -82.650498 | P52: =- 1 * SUMIF('Monthly Financials'!$J$4:$EH$4,P$3,'Monthly Financials'!$J$162:$EH$162) -> -82.650498 | Q52: =- 1 * SUMIF('Monthly Financials'!$J$4:$EH$4,Q$3,'Monthly Financials'!$J$162:$EH$162) -> -82.650498 | ... W52: =- 1 * SUMIF('Monthly Financials'!$J$4:$EH$4,W$3,'Monthly Financials'!$J$162:$EH$162) -> 0
E53: Net GST Paid on AMISP Service Charge | G53: INR Cr | H53: =SUM(J53:W53) -> -120.82185 | J53: =-1 * SUMIF('Monthly Financials'!$J$4:$EH$4,J$3,GST!$J$28:$EH$28) -> 0 | K53: =-1 * SUMIF('Monthly Financials'!$J$4:$EH$4,K$3,GST!$J$28:$EH$28) -> 0 | L53: =-1 * SUMIF('Monthly Financials'!$J$4:$EH$4,L$3,GST!$J$28:$EH$28) -> 0 | M53: =-1 * SUMIF('Monthly Financials'!$J$4:$EH$4,M$3,GST!$J$28:$EH$28) -> 0 | N53: =-1 * SUMIF('Monthly Financials'!$J$4:$EH$4,N$3,GST!$J$28:$EH$28) -> 0 | O53: =-1 * SUMIF('Monthly Financials'!$J$4:$EH$4,O$3,GST!$J$28:$EH$28) -> 0 | P53: =-1 * SUMIF('Monthly Financials'!$J$4:$EH$4,P$3,GST!$J$28:$EH$28) -> -8.6825694 | Q53: =-1 * SUMIF('Monthly Financials'!$J$4:$EH$4,Q$3,GST!$J$28:$EH$28) -> -34.958106 | ... W53: =-1 * SUMIF('Monthly Financials'!$J$4:$EH$4,W$3,GST!$J$28:$EH$28) -> 0
